Workbook
Name Anomaly_Benford_Verdict: '20_Anomaly_Detection'!$I$19
Name Anomaly_Earnings_Verdict: '20_Anomaly_Detection'!$G$42
Name Anomaly_Master_Verdict: '20_Anomaly_Detection'!$C$49
Name Anomaly_RollingZ_Count: '20_Anomaly_Detection'!$G$31
Name Anomaly_RollingZ_Verdict: '20_Anomaly_Detection'!$H$31
Name APIGrossIncome: '0_Setup'!$C$87
Name Bankable_Breach_Week: '21_Forecasting_Engine'!$D$64
Name BorrowerName: '0_Setup'!$C$5
Name CAM_Para1: '22_Credit_Memorandum'!$B$16
Name CAM_Para2: '22_Credit_Memorandum'!$B$19
Name CAM_Para3: '22_Credit_Memorandum'!$B$22
Name CAM_Para4: '22_Credit_Memorandum'!$B$25
Name CAM_Synopsis: '22_Credit_Memorandum'!$A$5
Name Cascade_Breakpoint: '15_Stress_Test'!$C$105
Name Cascade_DSCR: '15_Stress_Test'!$C$98
Name Cascade_Selected_Scenario: '15_Stress_Test'!$C$71
Name Cascade_Severity: '15_Stress_Test'!$C$72
Name Cascade_Verdict: '15_Stress_Test'!$E$98
Name CashFlow_MaxFunding: '18_13W_Cash_Flow'!$P$30
Name CashFlow_MinAcrossWeeks: '18_13W_Cash_Flow'!$O$29
Name CashFlow_MinClosing: '18_13W_Cash_Flow'!$P$29
Name ChapterXIA_AggExposure: '10_Credit_Limits'!$E$37
Name ChapterXIA_BankShare: '10_Credit_Limits'!$E$39
Name ChapterXIA_Status: '10_Credit_Limits'!$E$40
Name CurrentEstCol: '0_Setup'!$C$43
Name CurrentFY: '0_Setup'!$C$14
Name CustomerID: '0_Setup'!$C$6
Name DataSource: '0_Setup'!$C$86
Name DCCO_Year: '0_Setup'!$C$83
Name ESG_TotalScore: '16_ESG_Scorecard'!$D$21
Name EWS_CriticalCount: '17_Advanced_EWS'!$D$56
Name EWS_HighCount: '17_Advanced_EWS'!$E$56
Name EWS_TotalPoints: '17_Advanced_EWS'!$F$56
Name EWS_Verdict: '17_Advanced_EWS'!$G$56
Name ExistingFB_TL: '0_Setup'!$B$21
Name ExistingFB_WC: '0_Setup'!$B$20
Name ExistingNFB: '0_Setup'!$B$22
Name ExternalRating: '0_Setup'!$C$9
Name FirstFY: '0_Setup'!$C$12
Name Forecast_Cash_Yr1: '21_Forecasting_Engine'!$E$8
Name Forecast_EBITDA_Yr1: '21_Forecasting_Engine'!$E$7
Name Forecast_Sales_Yr1: '21_Forecasting_Engine'!$E$6
Name IndustryName: '0_Setup'!$C$7
Name InternalRating: '0_Setup'!$C$8
Name LastFY: '0_Setup'!$C$13
Name LastProjCol: '0_Setup'!$C$44
Name LatestAudCol: '0_Setup'!$C$40
Name LatestEstCol: '0_Setup'!$C$41
Name Liquidity_Breach_Week: '21_Forecasting_Engine'!$D$63
Name MaxDPOStretch: '0_Setup'!$F$31
Name MaxDSOIncrease: '0_Setup'!$F$30
Name MaxInvDays: '0_Setup'!$F$29
Name MaxLeverage: '0_Setup'!$C$30
Name MaxNWCErosion: '0_Setup'!$F$28
Name MaxTOLTNW: '0_Setup'!$C$29
Name Min_Projected_Cash: '21_Forecasting_Engine'!$D$65
Name MinCR: '0_Setup'!$C$26
Name MinDSCR_Any: '0_Setup'!$C$27
Name MinDSCR_Avg: '0_Setup'!$C$28
Name MinFACR: '0_Setup'!$F$27

Sheet 0A_Executive_Dashboard
A1: CMA AUTO-ANALYTICS · EXECUTIVE DASHBOARD · SANCTION COMMITTEE SNAPSHOT
A2: =IF(BorrowerName="","[Borrower Not Set]","Borrower: "&BorrowerName) -> [Borrower Not Set] | C2: =IF(IndustryName="","Industry: —","Industry: "&IndustryName) -> Industry: — | E2: =IF(ProposalType="","Proposal: —","Proposal: "&ProposalType) -> Proposal: — | G2: =TODAY() -> 46150
B4: 📊 KEY PERFORMANCE INDICATORS | G4: 🔴 RISK SCORE & RECOMMENDATION
B5: Metric | C5: Latest Aud | D5: Threshold | E5: Status | G5: Score Basis
B6: Net Sales (₹ Cr) | C6: =IFERROR(INDEX('2_Operating_Statement'!C13:N13,1,LatestAudCol),0) -> 0 | D6: — (trend) | E6: =IF(IFERROR(INDEX('2_Operating_Statement'!C13:N13,1,LatestAudCol),0)>0,"🟢 POSITIVE","⚠ ZERO/NEG") -> ⚠ ZERO/NEG | G6: "Absolute revenue base — check YoY trajectory"
B7: Sales Growth YoY (Latest Aud) | C7: =IFERROR(INDEX('8_Performance_Indicators'!C8:N8,1,LatestAudCol),0) | D7: ≥ MinSalesGrowth | E7: =IF(IFERROR(INDEX('8_Performance_Indicators'!C8:N8,1,LatestAudCol),0)>=0.1,"🟢 STRONG",IF(IFERROR(INDEX('8_Performance_Indicators'!C8:N8,1,LatestAudCol),0)>=MinSalesGrowth,"🟡 WATCH","🔴 WEAK")) -> 🟢 STRONG | G7: "Revenue momentum — verify with GST/banking"
B8: EBITDA Margin | C8: =IFERROR((IFERROR(INDEX('2_Operating_Statement'!C33:N33,1,LatestAudCol),0)+IFERROR(INDEX('2_Operating_Statement'!C24:N24,1,LatestAudCol),0))/IF(IFERROR(INDEX('2_Operating_Statement'!C13:N13,1,LatestAudCol),0)=0,1,IFERROR(INDEX('2_Operating_Statement'!C13:N13,1,LatestAudCol),0)),0) -> 0 | D8: ≥ 10% (watch) | E8: =IF(IFERROR((IFERROR(INDEX('2_Operating_Statement'!C33:N33,1,LatestAudCol),0)+IFERROR(INDEX('2_Operating_Statement'!C24:N24,1,LatestAudCol),0))/IF(IFERROR(INDEX('2_Operating_Statement'!C13:N13,1,LatestAudCol),0)=0,1,IFERROR(INDEX('2_Operating_Statement'!C13:N13,1,LatestAudCol),0)),0)>=0.1,"🟢 HEALTHY",IF(IFERROR((IFERROR(INDEX('2_Operating_Statement'!C33:N33,1,LatestAudCol),0)+IFERROR(INDEX('2_Operating_Statement'!C24:N24,1,LatestAudCol),0))/IF(IFERROR(INDEX('2_Operating_Statement'!C13:N13,1,LatestAudCol),0)=0,1,IFERROR(INDEX('2_Operating_Statement'!C13:N13,1,LatestAudCol),0)),0)>=0.05,"🟡 MARGINAL","🔴 THIN")) -> 🔴 THIN | G8: "Cash-generating capacity — EBITDA/Sales"
B9: PAT Margin | C9: =IFERROR(INDEX('8_Performance_Indicators'!C10:N10,1,LatestAudCol),0) -> 0 | D9: ≥ 2% | E9: =IF(IFERROR(INDEX('8_Performance_Indicators'!C10:N10,1,LatestAudCol),0)>=0.05,"🟢 STRONG",IF(IFERROR(INDEX('8_Performance_Indicators'!C10:N10,1,LatestAudCol),0)>=0.02,"🟡 OK","🔴 THIN")) -> 🔴 THIN | G9: "Retained earnings power"
B10: Current Ratio | C10: =IFERROR(INDEX('8_Performance_Indicators'!C14:N14,1,LatestAudCol),0) -> 0 | D10: ≥ MinCR | E10: =IF(IFERROR(INDEX('8_Performance_Indicators'!C14:N14,1,LatestAudCol),0)>=MinCR+0.3,"🟢 STRONG",IF(IFERROR(INDEX('8_Performance_Indicators'!C14:N14,1,LatestAudCol),0)>=MinCR,"🟡 WATCH","🔴 BREACH")) -> 🔴 BREACH | G10: "Short-term solvency buffer"
B11: TOL / TNW | C11: =IFERROR(INDEX('8_Performance_Indicators'!C19:N19,1,LatestAudCol),0) -> 0 | D11: ≤ MaxTOLTNW | E11: =IF(IFERROR(INDEX('8_Performance_Indicators'!C19:N19,1,LatestAudCol),0)<=0,"🔴 NEG TNW",IF(IFERROR(INDEX('8_Performance_Indicators'!C19:N19,1,LatestAudCol),0)<=MaxTOLTNW-1,"🟢 LOW LVRG",IF(IFERROR(INDEX('8_Performance_Indicators'!C19:N19,1,LatestAudCol),0)<=MaxTOLTNW,"🟡 WATCH","🔴 BREACH"))) -> 🔴 NEG TNW | G11: "Balance sheet leverage — outside liabilities vs equity"
B12: Interest Coverage (ICR) | C12: =IFERROR(INDEX('8_Performance_Indicators'!C23:N23,1,LatestAudCol),0) -> 0 | D12: ≥ MinICR | E12: =IF(IFERROR(INDEX('8_Performance_Indicators'!C23:N23,1,LatestAudCol),0)<=0,"🔴 NEG/NIL",IF(IFERROR(INDEX('8_Performance_Indicators'!C23:N23,1,LatestAudCol),0)>=MinICR+1,"🟢 STRONG",IF(IFERROR(INDEX('8_Performance_Indicators'!C23:N23,1,LatestAudCol),0)>=MinICR,"🟡 OK","🔴 BREACH"))) -> 🔴 NEG/NIL | G12: "Operating profit coverage of interest cost"
B13: DSCR (Gross, Latest Aud Yr) | C13: =IFERROR(INDEX('4_DSCR'!C17:N17,1,LatestAudCol),0) -> 0 | D13: ≥ MinDSCR_Any | E13: =IF(IFERROR(INDEX('4_DSCR'!C17:N17,1,LatestAudCol),0)<=0,"🔴 NO DATA",IF(IFERROR(INDEX('4_DSCR'!C17:N17,1,LatestAudCol),0)>=2,"🟢 STRONG",IF(IFERROR(INDEX('4_DSCR'!C17:N17,1,LatestAudCol),0)>=MinDSCR_Any,"🟡 OK","🔴 BREACH"))) -> 🔴 NO DATA | G13: "Term loan debt service — cash accruals vs repayment"
B14: Cash Conversion Cycle (Days) | C14: =IFERROR(INDEX('8_Performance_Indicators'!C30:N30,1,LatestAudCol),0) -> 0 | D14: < 120 days | E14: =IF(IFERROR(INDEX('8_Performance_Indicators'!C30:N30,1,LatestAudCol),0)=0,"—",IF(IFERROR(INDEX('8_Performance_Indicators'!C30:N30,1,LatestAudCol),0)<90,"🟢 EFFICIENT",IF(IFERROR(INDEX('8_Performance_Indicators'!C30:N30,1,LatestAudCol),0)<120,"🟡 WATCH","🔴 STRETCHED"))) -> — | G14: "Inv days + DSO − DPO; WC efficiency"
B15: Red Flags Triggered (/ 30 tests) | C15: ='12_Red_Flags'!D47 -> 0 | D15: 0 preferred | E15: =IF('12_Red_Flags'!D47=0,"🟢 CLEAN",IF('12_Red_Flags'!D47<=3,"🟡 MINOR",IF('12_Red_Flags'!D47<=7,"🔴 MULTIPLE","🔴 MATERIAL"))) -> 🟢 CLEAN | G15: "Automated diagnostic battery — review each flag"
B17: 🚨 RED FLAG VERDICT & LENDING STANCE
B18: Total Tests Triggered | C18: Overall Risk Score (/ 30) | D18: Red Flag Verdict | E18: =IF('0B_Credit_Scoring'!D29>=75,"✅ STRONG APPROVE — Credit profile robust. Recommend sanction with standard covenants.",IF('0B_Credit_Scoring'!D29>=60,"⚠ APPROVE WITH CONDITIONS — Satisfactory profile with noted concerns. Enhanced monitoring required.",IF('0B_Credit_Scoring'!D29>=50,"⚠ CAUTIOUS — Marginal profile. Sanction only with strong mitigants and committee approval.",IF('0B_Credit_Scoring'!D29>=40,"🔴 HIGH RISK — Significant weaknesses. Defer / restructure before sanction.","🔴 DECLINE — Material concerns across multiple dimensions. Not recommended.")))) -> 🔴 DECLINE — Material concerns across multiple dimensions. Not recommended.
B19: ='12_Red_Flags'!D47 -> 0 | C19: ='12_Red_Flags'!D49 -> 0 | D19: ='12_Red_Flags'!D50 -> 0
B20: Credit Scoring Engine Score (see 0B_Credit_Scoring sheet):
B21: ='0B_Credit_Scoring'!G29 -> 14.1
B23: 💚 TOP 5 CREDIT STRENGTHS (auto-assessed) | G23: 🔴 TOP 5 RISKS
B24: =IF(IFERROR(INDEX('8_Performance_Indicators'!C10:N10,1,LatestAudCol),0)>=0.05,"✓ PAT Margin "&TEXT(IFERROR(INDEX('8_Performance_Indicators'!C10:N10,1,LatestAudCol),0),"0.0%")&" — profitable operations","—") -> — | G24: =IF(IFERROR(INDEX('8_Performance_Indicators'!C14:N14,1,LatestAudCol),0)<MinCR,"⚠ CR "&TEXT(IFERROR(INDEX('8_Performance_Indicators'!C14:N14,1,LatestAudCol),0),"0.00x")&" — liquidity breach (threshold "&TEXT(MinCR,"0.00x")&")","—") -> ⚠ CR 0.00x — liquidity breach (threshold 1.17x)
B25: =IF(IFERROR(INDEX('8_Performance_Indicators'!C14:N14,1,LatestAudCol),0)>=MinCR+0.3,"✓ Current Ratio "&TEXT(IFERROR(INDEX('8_Performance_Indicators'!C14:N14,1,LatestAudCol),0),"0.00x")&" — strong liquidity","—") -> — | G25: =IF(IFERROR(INDEX('8_Performance_Indicators'!C19:N19,1,LatestAudCol),0)>MaxTOLTNW,"⚠ TOL/TNW "&TEXT(IFERROR(INDEX('8_Performance_Indicators'!C19:N19,1,LatestAudCol),0),"0.0x")&" — high leverage","—") -> —
B26: =IF(IFERROR(INDEX('8_Performance_Indicators'!C19:N19,1,LatestAudCol),0)<2.5,"✓ TOL/TNW "&TEXT(IFERROR(INDEX('8_Performance_Indicators'!C19:N19,1,LatestAudCol),0),"0.0x")&" — conservative leverage","—") -> ✓ TOL/TNW 0.0x — conservative leverage | G26: =IF(IFERROR(INDEX('4_DSCR'!C17:N17,1,LatestAudCol),0)<MinDSCR_Any,"⚠ DSCR "&TEXT(IFERROR(INDEX('4_DSCR'!C17:N17,1,LatestAudCol),0),"0.00x")&" — debt coverage below minimum","—") -> ⚠ DSCR 0.00x — debt coverage below minimum
B27: =IF(IFERROR(INDEX('4_DSCR'!C17:N17,1,LatestAudCol),0)>=2,"✓ DSCR "&TEXT(IFERROR(INDEX('4_DSCR'!C17:N17,1,LatestAudCol),0),"0.00x")&" — robust debt coverage","—") -> — | G27: =IF(IFERROR(INDEX('8_Performance_Indicators'!C10:N10,1,LatestAudCol),0)<0.02,"⚠ PAT Margin "&TEXT(IFERROR(INDEX('8_Performance_Indicators'!C10:N10,1,LatestAudCol),0),"0.0%")&" — thin profitability","—") -> ⚠ PAT Margin 0.0% — thin profitability
B28: =IF(IFERROR(INDEX('8_Performance_Indicators'!C23:N23,1,LatestAudCol),0)>=3,"✓ ICR "&TEXT(IFERROR(INDEX('8_Performance_Indicators'!C23:N23,1,LatestAudCol),0),"0.00x")&" — strong interest cover","—") -> — | G28: =IF(IFERROR(INDEX('8_Performance_Indicators'!C8:N8,1,LatestAudCol),0)<MinSalesGrowth,"⚠ Sales Growth "&TEXT(IFERROR(INDEX('8_Performance_Indicators'!C8:N8,1,LatestAudCol),0),"0.0%")&" — revenue under pressure","—") -> —
A32: 🚨 REGULATORY COMPLIANCE & ADVANCED RISK STATUS
B33: Compliance Module | C33: Status / Score | D33: Regulator / Source | F33: Implication for Sanction Committee
B34: Chapter XIA — Current/OD Account | C34: =ChapterXIA_Status -> 🟢 NO RESTRICTION | D34: RBI Amendment Apr 2026 | F34: =IF(LEFT(ChapterXIA_Status,1)="🔴","🔴 Account operations restricted. Only Collection Account (T+2 sweep) permitted. NOT eligible for standard CC/OD operation. CRITICAL constraint for sanction.",IF(ChapterXIA_AggExposure<10,"🟢 Aggregate exposure < ₹10 Cr threshold — full operational flexibility.","🟢 Bank holds compliant share (≥10%) of aggregate banking exposure.")) -> 🟢 Aggregate exposure < ₹10 Cr threshold — full operational flexibility.
B35: Early Warning Signals (RBI MD) | C35: =TEXT(EWS_TotalPoints,"0")&" pts" -> 0 pts | D35: RBI Master Direction Jul 2024 | F35: =EWS_Verdict -> 🟢 NORMAL — STANDARD MONITORING
B36: ESG & Climate Resilience | C36: =TEXT(ESG_TotalScore,"0.0")&" /100" -> 50.0 /100 | D36: RBI Climate MD Nov 2025 | F36: =IF(ESG_TotalScore>=65,"🟢 Strong ESG profile — supports lending pricing and reputation.",IF(ESG_TotalScore>=50,"🟡 Adequate ESG — monitor BRSR disclosures and transition pathway.","🔴 Weak ESG profile — climate transition risk exposure. Consider pricing premium and ESG covenants.")) -> 🟡 Adequate ESG — monitor BRSR disclosures and transition pathway.
B37: 13-Week Cash Flow Liquidity | C37: ="₹"&TEXT(CashFlow_MinClosing,"0.00")&" Cr" -> ₹0.00 Cr | D37: Treasury Best Practice | F37: =IF(CashFlow_MinClosing<0,"🔴 ACUTE 13-WEEK LIQUIDITY DEFICIT — Existing WC limits insufficient to bridge cash conversion cycle. Reassess MPBF & DSRA structure.","🟢 Closing balance projected positive across 13-week horizon. Liquidity adequate.") -> 🟢 Closing balance projected positive across 13-week horizon. Liquidity adequate.
B38: Project Finance Overlay | C38: =IF(ProjectFinance="Yes","Active","N/A") -> N/A | D38: RBI Project Finance Dir 2025 | F38: =IF(ProjectFinance="Yes",IF(ProjectPhase="Under-Construction",IF(ProjectSector="Commercial Real Estate","⚠ Standard provisioning at 1.25% (CRE under-construction). Pricing must absorb elevated capital cost.",IF(ProjectSector="Infrastructure","⚠ Standard provisioning at 1.00% (Infrastructure under-construction). DSCR alerts suppressed pre-DCCO.","⚠ Project finance under construction — review provisioning per RBI Project Finance Directions 2025.")),"🟢 Project operational — standard provisioning (0.40%) applies."),"Not a project finance facility.") -> Not a project finance facility.
B39: Probabilistic Default Model (Ohlson) | C39: =IF('19_Ohlson_O_Score'!O7=0,"— No data —",TEXT(Ohlson_PD_Latest,"0.0%")&" PD") -> — No data — | D39: Logistic Regression Model | F39: =IF('19_Ohlson_O_Score'!O7=0,"— Populate financials to activate Ohlson model",IF(Ohlson_PD_Latest>=0.5,"🔴 SEVERE distress probability — model assigns >50% PD. Override risk grade ceiling to BB or below regardless of categorical score.",IF(Ohlson_PD_Latest>=0.2,"🟡 ELEVATED PD — investigate top driver flagged on 19_Ohlson_O_Score. Cross-check with categorical score for divergence.",IF(Ohlson_PD_Latest>=0.038,"🟠 WATCH — PD above Ohlson optimal cutoff (0.038) but below severe. Acceptable with covenants.","🟢 HEALTHY — PD below Ohlson optimal cutoff. Probabilistic model concurs with low default risk.")))) -> — Populate financials to activate Ohlson model
B40: Benford's Law (Forensic) | C40: =IF('20_Anomaly_Detection'!E17<30,"— Need ≥30 obs",TEXT('20_Anomaly_Detection'!E17,"0")&" obs") -> — Need ≥30 obs | D40: AICPA Forensic Std | F40: =IF('20_Anomaly_Detection'!E17<30,"⚪ Insufficient sample — paste ≥30 monetary entries into 20_Anomaly_Detection col M",Anomaly_Benford_Verdict&" — see 20_Anomaly_Detection Section A") -> ⚪ Insufficient sample — paste ≥30 monetary entries into 20_Anomaly_Detection col M
B41: Rolling Z-Score (Trend) | C41: =Anomaly_RollingZ_Count&"/6 metrics" -> 0/6 metrics | D41: Statistical Z-Test | F41: =Anomaly_RollingZ_Verdict&" — see 20_Anomaly_Detection Section B" -> 🟢 No statistical outliers — see 20_Anomaly_Detection Section B
B42: Earnings Manipulation (Beneish) | C42: =TEXT('20_Anomaly_Detection'!F42,"0")&"/5 signals" -> 0/5 signals | D42: Beneish M-Score | F42: =Anomaly_Earnings_Verdict&" — see 20_Anomaly_Detection Section C" -> 🟢 No manipulation signature detected — see 20_Anomaly_Detection Section C
B43: Causal Cascade DSCR (selected scenario) | C43: =TEXT(Cascade_DSCR,"0.00x") -> 0.00x | D43: =Cascade_Selected_Scenario&" @ "&TEXT(Cascade_Severity,"0%") -> Brent Oil Shock @ 100% | F43: =Cascade_Verdict&" — see 15_Stress_Test Section F.4 | Breakpoint: "&Cascade_Breakpoint -> 🔴 DEBT SERVICE FAILURE — see 15_Stress_Test Section F.4 | Breakpoint: ⚠ Insufficient data
B44: 13-Week Forecast (FORECAST.ETS) | C44: =Min_Projected_Cash -> ⚠ Paste ≥8 weeks of historical receipts/disbursements first | D44: Holt-Winters ETS | F44: =IF(LEFT(Bankable_Breach_Week,1)="🔴",Bankable_Breach_Week,IF(LEFT(Liquidity_Breach_Week,1)="✓","🟢 "&Liquidity_Breach_Week,"🟠 "&Liquidity_Breach_Week)) -> 🟢 ✓ No cash-negative week in 13W horizon
B45: Annual Forecast Yr+1 (Net Sales) | C45: =IF(NOT(ISNUMBER(Forecast_Sales_Yr1)),"— Need ≥4 yrs history",TEXT(Forecast_Sales_Yr1,"#,##0")&" Cr") -> — Need ≥4 yrs history | D45: FORECAST.ETS | F45: =IF(NOT(ISNUMBER(Forecast_Sales_Yr1)),"⚪ Insufficient annual history (need ≥4 audited yrs)","Forecast YoY: "&TEXT(IFERROR(Forecast_Sales_Yr1/INDEX('2_Operating_Statement'!C13:N13,1,LatestAudCol)-1,0),"+0.0%;-0.0%")&" — see 21_Forecasting_Engine Section A") -> ⚪ Insufficient annual history (need ≥4 audited yrs)
B46: Credit Justification Memorandum | C46: ="See sheet 22_Credit_Memorandum" -> See sheet 22_Credit_Memorandum | D46: Auto-NLG (Module 5) | F46: =IFERROR(IF(OR(IFERROR(Ohlson_PD_Latest,0)>=0.5,LEFT(IFERROR(Anomaly_Master_Verdict,""),1)="🔴",IFERROR(Cascade_DSCR,99)<1,LEFT(IFERROR(Bankable_Breach_Week,""),1)="🔴"),"🔴 DECLINE recommended",IF(OR(IFERROR(Ohlson_PD_Latest,0)>=0.2,LEFT(IFERROR(Anomaly_Master_Verdict,""),1)="🟠",IFERROR(Cascade_DSCR,99)<MinDSCR_Any,LEFT(IFERROR(EWS_Verdict,""),1)="🚨"),"🟠 APPROVE WITH COVENANTS",IF(OR(IFERROR(Cascade_DSCR,99)<1.5,LEFT(IFERROR(EWS_Verdict,""),1)="⚠"),"🟡 APPROVE WITH STANDARD COVENANTS","🟢 APPROVE at standard terms"))),"⚪ Awaiting data") -> 🔴 DECLINE recommended

Sheet 0B_Credit_Scoring
A1: DYNAMIC CREDIT SCORING ENGINE | Weighted 10-Category Risk Model
A2: =IF(BorrowerName="","[Complete borrower name in 0_Setup]","Borrower: "&BorrowerName&" | Industry: "&IF(IndustryName="","—",IndustryName)&" | Proposal: "&IF(ProposalType="","—",ProposalType)) -> [Complete borrower name in 0_Setup]
B4: Scoring Category | C4: Weight % | D4: Auto-Score (0-10) | E4: Manual Override | F4: Effective Score | G4: Weighted Score | H4: Basis / Commentary
B6: 1. Profitability | C6: 0.14 | D6: =IFERROR((IF(IFERROR(INDEX('8_Performance_Indicators'!C9:N9,1,LatestAudCol),0)>=0.15,10,IF(IFERROR(INDEX('8_Performance_Indicators'!C9:N9,1,LatestAudCol),0)>=0.1,8,IF(IFERROR(INDEX('8_Performance_Indicators'!C9:N9,1,LatestAudCol),0)>=0.07,6,IF(IFERROR(INDEX('8_Performance_Indicators'!C9:N9,1,LatestAudCol),0)>=0.05,4,IF(IFERROR(INDEX('8_Performance_Indicators'!C9:N9,1,LatestAudCol),0)>=0.03,2,0)))))+IF(IFERROR(INDEX('8_Performance_Indicators'!C10:N10,1,LatestAudCol),0)>=0.08,10,IF(IFERROR(INDEX('8_Performance_Indicators'!C10:N10,1,LatestAudCol),0)>=0.05,8,IF(IFERROR(INDEX('8_Performance_Indicators'!C10:N10,1,LatestAudCol),0)>=0.03,6,IF(IFERROR(INDEX('8_Performance_Indicators'!C10:N10,1,LatestAudCol),0)>=0.02,4,IF(IFERROR(INDEX('8_Performance_Indicators'!C10:N10,1,LatestAudCol),0)>=0.01,2,0))))))/2,0) -> 0 | F6: =IF(E6<>"",E6,D6) -> 0 | G6: =F6*C6 -> 0 | H6: "OPM & PAT Margin vs thresholds. ≥15%/≥8%→10; ≥5%/≥2%→4"
B7: 2. Liquidity | C7: 0.11 | D7: =IFERROR((IF(IFERROR(INDEX('8_Performance_Indicators'!C14:N14,1,LatestAudCol),0)>=2,10,IF(IFERROR(INDEX('8_Performance_Indicators'!C14:N14,1,LatestAudCol),0)>=1.5,8,IF(IFERROR(INDEX('8_Performance_Indicators'!C14:N14,1,LatestAudCol),0)>=1.33,6,IF(IFERROR(INDEX('8_Performance_Indicators'!C14:N14,1,LatestAudCol),0)>=1.17,4,IF(IFERROR(INDEX('8_Performance_Indicators'!C14:N14,1,LatestAudCol),0)>=1,2,0)))))+IF(IFERROR(INDEX('8_Performance_Indicators'!C15:N15,1,LatestAudCol),0)>=1.5,10,IF(IFERROR(INDEX('8_Performance_Indicators'!C15:N15,1,LatestAudCol),0)>=1.2,8,IF(IFERROR(INDEX('8_Performance_Indicators'!C15:N15,1,LatestAudCol),0)>=1,6,IF(IFERROR(INDEX('8_Performance_Indicators'!C15:N15,1,LatestAudCol),0)>=0.8,4,IF(IFERROR(INDEX('8_Performance_Indicators'!C15:N15,1,LatestAudCol),0)>=0.6,2,0))))))/2,0) -> 0 | F7: =IF(E7<>"",E7,D7) -> 0 | G7: =F7*C7 -> 0 | H7: "Current Ratio & Quick Ratio. CR≥2.0/QR≥1.5→10; CR<MinCR→≤4"
B8: 3. Leverage | C8: 0.11 | D8: =IFERROR(IF(IFERROR(INDEX('8_Performance_Indicators'!C19:N19,1,LatestAudCol),0)<=0,0,IF(10-IFERROR(INDEX('8_Performance_Indicators'!C19:N19,1,LatestAudCol),0)*2>=7,10,IF(10-IFERROR(INDEX('8_Performance_Indicators'!C19:N19,1,LatestAudCol),0)*2>=5,8,IF(10-IFERROR(INDEX('8_Performance_Indicators'!C19:N19,1,LatestAudCol),0)*2>=3,6,IF(10-IFERROR(INDEX('8_Performance_Indicators'!C19:N19,1,LatestAudCol),0)*2>=1,4,IF(10-IFERROR(INDEX('8_Performance_Indicators'!C19:N19,1,LatestAudCol),0)*2>=-1,2,0)))))),0) -> 0 | F8: =IF(E8<>"",E8,D8) -> 0 | G8: =F8*C8 -> 0 | H8: "TOL/TNW — lower is better. ≤1.5→10; ≤2.5→6; >MaxTOLTNW→2"
B9: 4. Debt Coverage | C9: 0.14 | D9: =IFERROR((IF(IFERROR(INDEX('4_DSCR'!C17:N17,1,LatestAudCol),0)>=2.5,10,IF(IFERROR(INDEX('4_DSCR'!C17:N17,1,LatestAudCol),0)>=2,8,IF(IFERROR(INDEX('4_DSCR'!C17:N17,1,LatestAudCol),0)>=1.75,6,IF(IFERROR(INDEX('4_DSCR'!C17:N17,1,LatestAudCol),0)>=1.25,4,IF(IFERROR(INDEX('4_DSCR'!C17:N17,1,LatestAudCol),0)>=1,2,0)))))+IF(IFERROR(INDEX('8_Performance_Indicators'!C23:N23,1,LatestAudCol),0)>=5,10,IF(IFERROR(INDEX('8_Performance_Indicators'!C23:N23,1,LatestAudCol),0)>=4,8,IF(IFERROR(INDEX('8_Performance_Indicators'!C23:N23,1,LatestAudCol),0)>=3,6,IF(IFERROR(INDEX('8_Performance_Indicators'!C23:N23,1,LatestAudCol),0)>=1.5,4,IF(IFERROR(INDEX('8_Performance_Indicators'!C23:N23,1,LatestAudCol),0)>=1,2,0))))))/2,0) -> 0 | F9: =IF(E9<>"",E9,D9) -> 0 | G9: =F9*C9 -> 0 | H9: "DSCR & ICR. DSCR≥2.5/ICR≥5→10. Breach of either→≤4"
B10: 5. Banking Conduct | C10: 0.08 | D10: =IF(E14<>"",E14,5) -> 5 | F10: =IF(E10<>"",E10,D10) -> 5 | G10: =F10*C10 -> 0.4 | H10: "Manual input (0-10). Default=5. Rate based on utilisation, cheque returns, overdrawing, EMI history"
B11: 6. Industry Outlook | C11: 0.08 | D11: =IFERROR(IF('0_Setup'!C68="Positive",9,IF('0_Setup'!C68="Stable",7,IF('0_Setup'!C68="Cautious",5,IF('0_Setup'!C68="Negative",3,5)))),5) -> 5 | F11: =IF(E11<>"",E11,D11) -> 5 | G11: =F11*C11 -> 0.4 | H11: "Auto-pulled from Industry_Outlook via Setup. Positive→9; Stable→7; Cautious→5; Negative→3"
B12: 7. Financial Trend Stability | C12: 0.1 | D12: =IFERROR(MAX(0,10-COUNTIF('12_Red_Flags'!F5:F44,"⚠*")*1.2),0) -> 1.6 | F12: =IF(E12<>"",E12,D12) -> 1.6 | G12: =F12*C12 -> 0.16 | H12: "Deducts 1.2 pts per red flag triggered. Clean sheet (0 flags)→10; 8 flags→~0"
B13: 8. Working Capital Discipline | C13: 0.08 | D13: =IFERROR(IF(365/IFERROR(INDEX('8_Performance_Indicators'!C30:N30,1,LatestAudCol),0)>=6,10,IF(365/IFERROR(INDEX('8_Performance_Indicators'!C30:N30,1,LatestAudCol),0)>=4,8,IF(365/IFERROR(INDEX('8_Performance_Indicators'!C30:N30,1,LatestAudCol),0)>=3,6,IF(365/IFERROR(INDEX('8_Performance_Indicators'!C30:N30,1,LatestAudCol),0)>=2,4,IF(365/IFERROR(INDEX('8_Performance_Indicators'!C30:N30,1,LatestAudCol),0)>=1,2,0))))),0) -> 0 | F13: =IF(E13<>"",E13,D13) -> 0 | G13: =F13*C13 -> 0 | H13: "CCC efficiency. CCC<60d→10; CCC<90d→8; CCC>180d→2. Zero CCC treated as efficient"
B14: 9. Promoter Contribution | C14: 0.07 | D14: =IFERROR(IF(IFERROR(INDEX('3_Balance_Sheet'!C52:N52,1,LatestAudCol),0)/IF(IFERROR(INDEX('3_Balance_Sheet'!C52:N52,1,LatestAudCol),0)+IFERROR(INDEX('3_Balance_Sheet'!C39:N39,1,LatestAudCol),0)=0,1,IFERROR(INDEX('3_Balance_Sheet'!C52:N52,1,LatestAudCol),0)+IFERROR(INDEX('3_Balance_Sheet'!C39:N39,1,LatestAudCol),0))>=0.5,10,IF(IFERROR(INDEX('3_Balance_Sheet'!C52:N52,1,LatestAudCol),0)/IF(IFERROR(INDEX('3_Balance_Sheet'!C52:N52,1,LatestAudCol),0)+IFERROR(INDEX('3_Balance_Sheet'!C39:N39,1,LatestAudCol),0)=0,1,IFERROR(INDEX('3_Balance_Sheet'!C52:N52,1,LatestAudCol),0)+IFERROR(INDEX('3_Balance_Sheet'!C39:N39,1,LatestAudCol),0))>=0.4,8,IF(IFERROR(INDEX('3_Balance_Sheet'!C52:N52,1,LatestAudCol),0)/IF(IFERROR(INDEX('3_Balance_Sheet'!C52:N52,1,LatestAudCol),0)+IFERROR(INDEX('3_Balance_Sheet'!C39:N39,1,LatestAudCol),0)=0,1,IFERROR(INDEX('3_Balance_Sheet'!C52:N52,1,LatestAudCol),0)+IFERROR(INDEX('3_Balance_Sheet'!C39:N39,1,LatestAudCol),0))>=0.3,6,IF(IFERROR(INDEX('3_Balance_Sheet'!C52:N52,1,LatestAudCol),0)/IF(IFERROR(INDEX('3_Balance_Sheet'!C52:N52,1,LatestAudCol),0)+IFERROR(INDEX('3_Balance_Sheet'!C39:N39,1,LatestAudCol),0)=0,1,IFERROR(INDEX('3_Balance_Sheet'!C52:N52,1,LatestAudCol),0)+IFERROR(INDEX('3_Balance_Sheet'!C39:N39,1,LatestAudCol),0))>=0.25,4,IF(IFERROR(INDEX('3_Balance_Sheet'!C52:N52,1,LatestAudCol),0)/IF(IFERROR(INDEX('3_Balance_Sheet'!C52:N52,1,LatestAudCol),0)+IFERROR(INDEX('3_Balance_Sheet'!C39:N39,1,LatestAudCol),0)=0,1,IFERROR(INDEX('3_Balance_Sheet'!C52:N52,1,LatestAudCol),0)+IFERROR(INDEX('3_Balance_Sheet'!C39:N39,1,LatestAudCol),0))>=0.2,2,0))))),0) -> 0 | F14: =IF(E14<>"",E14,D14) -> 0 | G14: =F14*C14 -> 0 | H14: "TNW/(TNW+TTL). ≥50%→10; ≥40%→8; ≥25%→4. Low promoter skin-in→lower score"
B15: 10. Projection Reliability | C15: 0.04 | D15: =IF(E23<>"",E23,5) -> 5 | F15: =IF(E15<>"",E15,D15) -> 5 | G15: =F15*C15 -> 0.2 | H15: "Manual input (0-10). Default=5. Assess: CAGR vs history, margin assumptions, capacity utilisation realism"
B16: 11. ESG Risk & Climate Resilience | C16: 0.05 | D16: =IFERROR(ESG_TotalScore/10,5) -> 5 | F16: =IF(E16<>"",E16,D16) -> 5 | G16: =F16*C16 -> 0.25 | H16: "Auto-pulled from 16_ESG_Scorecard total ÷ 10. Includes hard-to-abate sector penalty if applicable."
B27: SCORE SUMMARY | F27: Effective Score | G27: Weighted Score | H27: Score Basis / Guidance
F28: Total Weights Used | G28: TOTAL WEIGHTED SCORE | H28: Internal Risk Grade
F29: =SUM(C6:C16) -> 1 | G29: =SUM(G6:G16)*10 -> 14.1 | H29: =IF(G29>=80,"AAA — Excellent",IF(G29>=70,"AA — Strong",IF(G29>=60,"A — Good",IF(G29>=50,"BBB — Satisfactory",IF(G29>=40,"BB — Marginal","B/C — Weak / Decline"))))) -> B/C — Weak / Decline
F30: =IF(G29>=75,"✅ STRONG APPROVE — Recommend full sanction with standard conditions",IF(G29>=60,"⚠ APPROVE WITH CONDITIONS — Enhanced monitoring + specific covenants required",IF(G29>=50,"⚠ CAUTIOUS — Committee discretion; strong mitigants needed",IF(G29>=40,"🔴 HIGH RISK — Defer for improvement or partial sanction only","🔴 DECLINE — Material weaknesses; not recommended without major restructure")))) -> 🔴 DECLINE — Material weaknesses; not recommended without major restructure
B31: NOTE: Column E (Manual Override) accepts 0-10 inputs for Banking Conduct & Projection Reliability categories. Override any auto-score by entering a value in Column E. Auto-scores reflect latest audited year ratios only.

Sheet 0_Setup
A1: CMA AUTO-ANALYTICS TOOL | v2.0 | Borrower Setup
A2: Fill the YELLOW cells. Computed cells (green text) auto-derive. Year structure auto-builds across all data sheets based on inputs in Section 2.
A4: 1. BORROWER IDENTIFICATION
A5: Borrower Name | B5: → | F5: (Enter legal name)
A6: Customer / CIF ID | B6: → | F6: (Bank's customer ID)
A7: Industry / Activity | B7: → | F7: (Select from dropdown)
A8: Internal Rating | B8: → | F8: (e.g., SB-3, AAA-)
A9: External Rating | B9: → | F9: (e.g., CRISIL A+, ICRA AA-)
A11: 2. YEAR CONFIGURATION (drives column structure across all data sheets)
A12: First Fiscal Year (start year, e.g., 2022 for FY2022-23) | B12: → | C12: 2022 | F12: (Start year of first audited FY)
A13: Last Fiscal Year (start year, e.g., 2029 for FY2029-30) | B13: → | C13: 2029 | F13: (Start year of last projected FY)
A14: Current Fiscal Year (start year, e.g., 2025 for FY2025-26) | B14: → | C14: 2025 | F14: (THE CURRENT FY = Estimated)
A16: 3. PROPOSAL TYPE & LIMITS
A17: Proposal Type | B17: → | F17: (Select from dropdown)
A19: Facility | B19: Existing Limit (₹ Cr) | D19: Proposed Limit (₹ Cr) | F19: Notes
A20: FB - Working Capital
A21: FB - Term Loan Outstanding
A22: Non-Fund Based (LC/BG)
A23: Note: | B23: =IF(C17="Renewal at Existing Level","Renewal: only Existing limits used.",IF(C17="Renewal with Reduction","Renewal w/ Reduction: BOTH existing and proposed (lower) limits considered.",IF(OR(C17="Enhancement",C17="Greenfield Unit",C17="Fresh Sanction"),"Enhancement / Greenfield / Fresh: BOTH existing and proposed limits used.","Select proposal type above."))) -> Select proposal type above.
A25: 4. KEY THRESHOLDS (override defaults if industry/internal policy varies)
A26: Min Acceptable Current Ratio | B26: → | C26: 1.17 | D26: Acceptable Sales Growth Floor (Y-o-Y) | E26: → | F26: -0.05
A27: Min Acceptable DSCR (any year) | B27: → | C27: 1.25 | D27: Min FACR (TL Coverage) | E27: → | F27: 1.1
A28: Min Acceptable Avg DSCR | B28: → | C28: 1.5 | D28: Max NWC Erosion vs Prior Yr | E28: → | F28: -0.3
A29: Max Acceptable TOL/TNW | B29: → | C29: 4 | D29: Max Inventory-Days Increase | E29: → | F29: 0.4
A30: Max Acceptable Leverage (Debt/EBITDA) | B30: → | C30: 4.5 | D30: Max DSO Increase (Y-o-Y) | E30: → | F30: 0.3
A31: Min Acceptable Interest Coverage (ICR) | B31: → | C31: 1.5 | D31: Max DPO Stretch | E31: → | F31: 0.5
A33: 5. COMPUTED YEAR ARCHITECTURE (auto-derived — do not edit)
A34: Number of Fiscal Years | B34: → | C34: =$C$13-$C$12+1 -> 8 | F34: (Last - First + 1)
A35: Prior FY (year before current) | B35: → | C35: =$C$14-1 -> 2024 | F35: (Used for dual columns)
A36: Position of Prior FY | B36: → | C36: =$C$35-$C$12+1 -> 3 | F36: (1-indexed)
A37: Total Columns Used (incl. dual Estimated) | B37: → | C37: =$C$34+1 -> 9 | F37: (Capped at 12 max)
A39: ANCHOR INDICES
A40: Latest Audited (Audited/Provisional) col | B40: → | C40: =$C$36+1 -> 4
A41: Latest Estimated (dual, before Audited) | B41: → | C41: =$C$36 -> 3
A42: Prior Audited (year before dual) | B42: → | C42: =MAX($C$36-1,1) -> 2
A43: Current FY Estimated | B43: → | C43: =$C$36+2 -> 5
A44: Last Projected (terminal) | B44: → | C44: =$C$37 -> 9
A46: YEAR-LABEL HELPER TABLE (referenced by Row 4 of all data sheets)
A47: Col Idx | B47: Year Label | C47: Financial Type
A48: 1 | B48: =IF(1>$C$37,"",IF(1<$C$36,$C$12+1-1&"-"&RIGHT($C$12+1,2),IF(1=$C$36,$C$35&"-"&RIGHT($C$35+1,2),IF(1=$C$36+1,$C$35&"-"&RIGHT($C$35+1,2),IF(1=$C$36+2,$C$14&"-"&RIGHT($C$14+1,2),$C$14+(1-$C$36-2)&"-"&RIGHT($C$14+(1-$C$36-2)+1,2)))))) -> 2022-23 | C48: =IF(1>$C$37,"",IF(1<$C$36,"Audited",IF(1=$C$36,"Estimated",IF(1=$C$36+1,"Audited/Provisional",IF(1=$C$36+2,"Estimated","Projected"))))) -> Audited
A49: 2 | B49: =IF(2>$C$37,"",IF(2<$C$36,$C$12+2-1&"-"&RIGHT($C$12+2,2),IF(2=$C$36,$C$35&"-"&RIGHT($C$35+1,2),IF(2=$C$36+1,$C$35&"-"&RIGHT($C$35+1,2),IF(2=$C$36+2,$C$14&"-"&RIGHT($C$14+1,2),$C$14+(2-$C$36-2)&"-"&RIGHT($C$14+(2-$C$36-2)+1,2)))))) -> 2023-24 | C49: =IF(2>$C$37,"",IF(2<$C$36,"Audited",IF(2=$C$36,"Estimated",IF(2=$C$36+1,"Audited/Provisional",IF(2=$C$36+2,"Estimated","Projected"))))) -> Audited
A50: 3 | B50: =IF(3>$C$37,"",IF(3<$C$36,$C$12+3-1&"-"&RIGHT($C$12+3,2),IF(3=$C$36,$C$35&"-"&RIGHT($C$35+1,2),IF(3=$C$36+1,$C$35&"-"&RIGHT($C$35+1,2),IF(3=$C$36+2,$C$14&"-"&RIGHT($C$14+1,2),$C$14+(3-$C$36-2)&"-"&RIGHT($C$14+(3-$C$36-2)+1,2)))))) -> 2024-25 | C50: =IF(3>$C$37,"",IF(3<$C$36,"Audited",IF(3=$C$36,"Estimated",IF(3=$C$36+1,"Audited/Provisional",IF(3=$C$36+2,"Estimated","Projected"))))) -> Estimated
A51: 4 | B51: =IF(4>$C$37,"",IF(4<$C$36,$C$12+4-1&"-"&RIGHT($C$12+4,2),IF(4=$C$36,$C$35&"-"&RIGHT($C$35+1,2),IF(4=$C$36+1,$C$35&"-"&RIGHT($C$35+1,2),IF(4=$C$36+2,$C$14&"-"&RIGHT($C$14+1,2),$C$14+(4-$C$36-2)&"-"&RIGHT($C$14+(4-$C$36-2)+1,2)))))) -> 2024-25 | C51: =IF(4>$C$37,"",IF(4<$C$36,"Audited",IF(4=$C$36,"Estimated",IF(4=$C$36+1,"Audited/Provisional",IF(4=$C$36+2,"Estimated","Projected"))))) -> Audited/Provisional
A52: 5 | B52: =IF(5>$C$37,"",IF(5<$C$36,$C$12+5-1&"-"&RIGHT($C$12+5,2),IF(5=$C$36,$C$35&"-"&RIGHT($C$35+1,2),IF(5=$C$36+1,$C$35&"-"&RIGHT($C$35+1,2),IF(5=$C$36+2,$C$14&"-"&RIGHT($C$14+1,2),$C$14+(5-$C$36-2)&"-"&RIGHT($C$14+(5-$C$36-2)+1,2)))))) -> 2025-26 | C52: =IF(5>$C$37,"",IF(5<$C$36,"Audited",IF(5=$C$36,"Estimated",IF(5=$C$36+1,"Audited/Provisional",IF(5=$C$36+2,"Estimated","Projected"))))) -> Estimated
A53: 6 | B53: =IF(6>$C$37,"",IF(6<$C$36,$C$12+6-1&"-"&RIGHT($C$12+6,2),IF(6=$C$36,$C$35&"-"&RIGHT($C$35+1,2),IF(6=$C$36+1,$C$35&"-"&RIGHT($C$35+1,2),IF(6=$C$36+2,$C$14&"-"&RIGHT($C$14+1,2),$C$14+(6-$C$36-2)&"-"&RIGHT($C$14+(6-$C$36-2)+1,2)))))) -> 2026-27 | C53: =IF(6>$C$37,"",IF(6<$C$36,"Audited",IF(6=$C$36,"Estimated",IF(6=$C$36+1,"Audited/Provisional",IF(6=$C$36+2,"Estimated","Projected"))))) -> Projected
A54: 7 | B54: =IF(7>$C$37,"",IF(7<$C$36,$C$12+7-1&"-"&RIGHT($C$12+7,2),IF(7=$C$36,$C$35&"-"&RIGHT($C$35+1,2),IF(7=$C$36+1,$C$35&"-"&RIGHT($C$35+1,2),IF(7=$C$36+2,$C$14&"-"&RIGHT($C$14+1,2),$C$14+(7-$C$36-2)&"-"&RIGHT($C$14+(7-$C$36-2)+1,2)))))) -> 2027-28 | C54: =IF(7>$C$37,"",IF(7<$C$36,"Audited",IF(7=$C$36,"Estimated",IF(7=$C$36+1,"Audited/Provisional",IF(7=$C$36+2,"Estimated","Projected"))))) -> Projected
A55: 8 | B55: =IF(8>$C$37,"",IF(8<$C$36,$C$12+8-1&"-"&RIGHT($C$12+8,2),IF(8=$C$36,$C$35&"-"&RIGHT($C$35+1,2),IF(8=$C$36+1,$C$35&"-"&RIGHT($C$35+1,2),IF(8=$C$36+2,$C$14&"-"&RIGHT($C$14+1,2),$C$14+(8-$C$36-2)&"-"&RIGHT($C$14+(8-$C$36-2)+1,2)))))) -> 2028-29 | C55: =IF(8>$C$37,"",IF(8<$C$36,"Audited",IF(8=$C$36,"Estimated",IF(8=$C$36+1,"Audited/Provisional",IF(8=$C$36+2,"Estimated","Projected"))))) -> Projected
A56: 9 | B56: =IF(9>$C$37,"",IF(9<$C$36,$C$12+9-1&"-"&RIGHT($C$12+9,2),IF(9=$C$36,$C$35&"-"&RIGHT($C$35+1,2),IF(9=$C$36+1,$C$35&"-"&RIGHT($C$35+1,2),IF(9=$C$36+2,$C$14&"-"&RIGHT($C$14+1,2),$C$14+(9-$C$36-2)&"-"&RIGHT($C$14+(9-$C$36-2)+1,2)))))) -> 2029-30 | C56: =IF(9>$C$37,"",IF(9<$C$36,"Audited",IF(9=$C$36,"Estimated",IF(9=$C$36+1,"Audited/Provisional",IF(9=$C$36+2,"Estimated","Projected"))))) -> Projected
A57: 10 | B57: =IF(10>$C$37,"",IF(10<$C$36,$C$12+10-1&"-"&RIGHT($C$12+10,2),IF(10=$C$36,$C$35&"-"&RIGHT($C$35+1,2),IF(10=$C$36+1,$C$35&"-"&RIGHT($C$35+1,2),IF(10=$C$36+2,$C$14&"-"&RIGHT($C$14+1,2),$C$14+(10-$C$36-2)&"-"&RIGHT($C$14+(10-$C$36-2)+1,2)))))) | C57: =IF(10>$C$37,"",IF(10<$C$36,"Audited",IF(10=$C$36,"Estimated",IF(10=$C$36+1,"Audited/Provisional",IF(10=$C$36+2,"Estimated","Projected")))))
A58: 11 | B58: =IF(11>$C$37,"",IF(11<$C$36,$C$12+11-1&"-"&RIGHT($C$12+11,2),IF(11=$C$36,$C$35&"-"&RIGHT($C$35+1,2),IF(11=$C$36+1,$C$35&"-"&RIGHT($C$35+1,2),IF(11=$C$36+2,$C$14&"-"&RIGHT($C$14+1,2),$C$14+(11-$C$36-2)&"-"&RIGHT($C$14+(11-$C$36-2)+1,2)))))) | C58: =IF(11>$C$37,"",IF(11<$C$36,"Audited",IF(11=$C$36,"Estimated",IF(11=$C$36+1,"Audited/Provisional",IF(11=$C$36+2,"Estimated","Projected")))))
A59: 12 | B59: =IF(12>$C$37,"",IF(12<$C$36,$C$12+12-1&"-"&RIGHT($C$12+12,2),IF(12=$C$36,$C$35&"-"&RIGHT($C$35+1,2),IF(12=$C$36+1,$C$35&"-"&RIGHT($C$35+1,2),IF(12=$C$36+2,$C$14&"-"&RIGHT($C$14+1,2),$C$14+(12-$C$36-2)&"-"&RIGHT($C$14+(12-$C$36-2)+1,2)))))) | C59: =IF(12>$C$37,"",IF(12<$C$36,"Audited",IF(12=$C$36,"Estimated",IF(12=$C$36+1,"Audited/Provisional",IF(12=$C$36+2,"Estimated","Projected")))))
A61: 6. INDUSTRY OUTLOOK SNAPSHOT (auto-pulled — read-only)
A62: Outlook (Stable / Positive / Negative / Cautious) | B62: → | C62: =IFERROR(VLOOKUP($C$7,Industry_Outlook!$A:$H,2,FALSE()),"Select Industry above") -> Select Industry above
A63: Prior Performance (FY25) | B63: → | C63: =IFERROR(VLOOKUP($C$7,Industry_Outlook!$A:$H,3,FALSE()),"Select Industry above") -> Select Industry above
A64: Forecast FY26 | B64: → | C64: =IFERROR(VLOOKUP($C$7,Industry_Outlook!$A:$H,4,FALSE()),"Select Industry above") -> Select Industry above
A65: Forecast FY27 | B65: → | C65: =IFERROR(VLOOKUP($C$7,Industry_Outlook!$A:$H,5,FALSE()),"Select Industry above") -> Select Industry above
A66: Key Drivers | B66: → | C66: =IFERROR(VLOOKUP($C$7,Industry_Outlook!$A:$H,6,FALSE()),"Select Industry above") -> Select Industry above
A67: Key Risks | B67: → | C67: =IFERROR(VLOOKUP($C$7,Industry_Outlook!$A:$H,7,FALSE()),"Select Industry above") -> Select Industry above
A68: Source | B68: → | C68: =IFERROR(VLOOKUP($C$7,Industry_Outlook!$A:$H,8,FALSE()),"Select Industry above") -> Select Industry above
A70: Industry Data Last Refreshed: | B70: → | C70: April 2026 — CRISIL Sep 2025 + Apr 2026, ICRA Jan-Apr 2026, IBEF, Govt sources. Manually refresh hidden Industry_Outlook sheet to update.
A72: LEGEND
B73: Hardcoded input (paste your data here)
B74: Formula / computed (do not edit)
B75: Red flag triggered — needs critical analysis
B76: Healthy / within acceptable range
B77: Caution — marginal / requires review
A79: 7. PROJECT FINANCE OVERLAY (per RBI Project Finance Directions, 2025)
A80: Is this a Project Finance facility? | B80: → | C80: No | F80: (Yes / No — auto-applies elevated provisioning logic)
A81: Project Phase | B81: → | C81: Operational | F81: (Under-Construction / Operational / Pre-DCCO)
A82: Project Sector | B82: → | C82: — | F82: (Infrastructure / Commercial Real Estate / Other / —)
A83: Date of Commencement of Commercial Ops (DCCO) | B83: → | F83: (FY year-start, e.g., 2027 — used to suppress DSCR alerts during construction)
A85: 8. DATA SOURCE TOGGLE (Manual / Account Aggregator API mode)
A86: Data Source Mode | B86: → | C86: Manual Entry | F86: (Manual Entry / Account Aggregator API)
A87: API Gross Income — Latest Aud Yr (₹ Cr) | B87: → | C87: 0 | F87: (0 if API not connected. Fed by SAANS/AA. Reconciles vs Net Sales)
A88: Reconciliation Variance (vs Op Stmt Net Sales) | B88: → | C88: =IF(C87<=0,"— No API data —","Variance: "&TEXT((INDEX('2_Operating_Statement'!C13:N13,1,LatestAudCol)-C87)/C87,"0.0%")) -> — No API data — | F88: (Auto. >10% variance triggers EWS alert)

Sheet 1_How_To_Use
A1: HOW TO USE THIS TOOL | v2.0
A3: STEP 1 — SETUP | B3: Open 0_Setup. Enter Borrower Name, Customer ID, Industry (dropdown), Internal & External rating. Set First/Last/Current fiscal years. Set Proposal Type. Enter Existing limits; for enhancements/greenfield/renewal-with-reduction also enter Proposed limits. Override threshold defaults if your internal policy differs.
A4: STEP 2 — YEAR ARCHITECTURE | B4: All data sheets auto-build year columns based on Setup Section 2. Year labels (row 4) and financial-type tags (row 5) update automatically. The dual 'Estimated/Audited-Provisional' columns appear immediately around the prior FY for direct comparison.
A5: STEP 3 — PASTE DATA | B5: Open SBI LLMS exports. Paste-Special → Values into each blue input cell across these sheets:
A6: Sheet 2 | B6: Operating Statement
A7: Sheet 3 | B7: Balance Sheet
A8: Sheet 4 | B8: DSCR Calculation
A9: Sheet 5 | B9: Holding Levels
A10: Sheet 6 | B10: Working Capital Assessment (MPBF II)
A11: Sheet 7 | B11: Funds Flow Statement
A12: STEP 4 — REVIEW ANALYTICS | B12: Sheets 8 (Performance Indicators) and 9 (Cross Checks) auto-populate. Red highlighting flags breaches; green = healthy; amber = caution. Δ column shows YoY (Latest Audited vs Prior Audited) movement.
A13: STEP 5 — CREDIT LIMITS & SECURITY | B13: Sheet 10: facility-wise limits (existing + proposed conditional on proposal type). Sheet 11: Primary & Collateral. Coverage % auto-computes.
A14: STEP 6 — RED FLAGS | B14: Sheet 12 — 30+ automated red-flag tests. Each breach is annotated with the underlying ratio/value AND the source columns/rows that drove the conclusion (full traceability).
... A16: STEP 8 — JUSTIFICATION | B16: Sheet 14 produces a polished, conversational, formal justification ready to paste into the CAM. Adjusts based on proposal type and existing/proposed limits.
A18: KEY MECHANICS
A19: Year Sequencing | B19: Cols C-N support up to 12 fiscal years. The dual Estimated+Audited columns sit just before the current FY for direct comparison of estimated vs realised.
A20: Trend Analysis | B20: All Δ columns and red-flag tests use 'Latest Audited' (the Audited/Provisional col) vs 'Prior Audited' (col 2 before that, skipping the dual Estimated). This captures real Y-o-Y, ignoring estimates.
A21: Industry Outlook | B21: Section 6 of Setup auto-pulls latest available industry data (CRISIL/ICRA/IBEF) for the selected sector. Refresh manually by editing the hidden Industry_Outlook sheet.
A22: Negative Numbers | B22: Display in (parentheses); zeros display as '-'. All ratios use IFERROR to avoid #DIV/0.
A24: WHEN TO RECALCULATE | B24: If formulas show 0s or stale numbers after pasting, press F9 (Excel) or Ctrl+Shift+F9 to force recalc. LibreOffice users: Tools → Cell Contents → Recalculate Hard.

Sheet 2_Operating_Statement
A1: =CONCATENATE("OPERATING STATEMENT | ₹ Crores | ", BorrowerName) -> OPERATING STATEMENT | ₹ Crores |
A2: Paste values from SBI LLMS Operating Statement → blue cells. Subtotals/totals auto-compute.
A3: Sr | B3: Particulars | C3: Yr 1 | D3: Yr 2 | E3: Yr 3 | F3: Yr 4 | G3: Yr 5 | H3: Yr 6 | I3: Yr 7 | J3: Yr 8 | K3: Yr 9 | L3: Yr 10 | M3: Yr 11 | N3: Yr 12 | O3: Δ Latest vs Prior Aud | P3: Auto-Comment
B4: Year → | C4: =INDEX('0_Setup'!$B$48:$B$59,1) -> 2022-23 | D4: =INDEX('0_Setup'!$B$48:$B$59,2) -> 2023-24 | E4: =INDEX('0_Setup'!$B$48:$B$59,3) -> 2024-25 | F4: =INDEX('0_Setup'!$B$48:$B$59,4) -> 2024-25 | G4: =INDEX('0_Setup'!$B$48:$B$59,5) -> 2025-26 | H4: =INDEX('0_Setup'!$B$48:$B$59,6) -> 2026-27 | I4: =INDEX('0_Setup'!$B$48:$B$59,7) -> 2027-28 | J4: =INDEX('0_Setup'!$B$48:$B$59,8) -> 2028-29 | K4: =INDEX('0_Setup'!$B$48:$B$59,9) -> 2029-30 | L4: =INDEX('0_Setup'!$B$48:$B$59,10) | M4: =INDEX('0_Setup'!$B$48:$B$59,11) | N4: =INDEX('0_Setup'!$B$48:$B$59,12)
B5: Type → | C5: =INDEX('0_Setup'!$C$48:$C$59,1) -> Audited | D5: =INDEX('0_Setup'!$C$48:$C$59,2) -> Audited | E5: =INDEX('0_Setup'!$C$48:$C$59,3) -> Estimated | F5: =INDEX('0_Setup'!$C$48:$C$59,4) -> Audited/Provisional | G5: =INDEX('0_Setup'!$C$48:$C$59,5) -> Estimated | H5: =INDEX('0_Setup'!$C$48:$C$59,6) -> Projected | I5: =INDEX('0_Setup'!$C$48:$C$59,7) -> Projected | J5: =INDEX('0_Setup'!$C$48:$C$59,8) -> Projected | K5: =INDEX('0_Setup'!$C$48:$C$59,9) -> Projected | L5: =INDEX('0_Setup'!$C$48:$C$59,10) | M5: =INDEX('0_Setup'!$C$48:$C$59,11) | N5: =INDEX('0_Setup'!$C$48:$C$59,12)
A6: A. SALES
A7: 1 | B7: Domestic Sales
A8: 2 | B8: Export Sales
A9: 3 | B9: Other Operating / Revenue Income
A10: 4 | B10: Total Gross Sales | C10: =C7+C8+C9 -> 0 | D10: =D7+D8+D9 -> 0 | E10: =E7+E8+E9 -> 0 | F10: =F7+F8+F9 -> 0 | G10: =G7+G8+G9 -> 0 | H10: =H7+H8+H9 -> 0 | I10: =I7+I8+I9 -> 0 | J10: =J7+J8+J9 -> 0 | ... N10: =N7+N8+N9 -> 0 | O10: =IFERROR((INDEX(C10:N10,1,LatestAudCol)-INDEX(C10:N10,1,PriorAudCol))/ABS(INDEX(C10:N10,1,PriorAudCol)),"")
A11: 5 | B11: Deduct: Excise Duty / Service Tax
A12: 6 | B12: Deduct: Other Items
A13: 7 | B13: Net Sales | C13: =C10-C11-C12 -> 0 | D13: =D10-D11-D12 -> 0 | E13: =E10-E11-E12 -> 0 | F13: =F10-F11-F12 -> 0 | G13: =G10-G11-G12 -> 0 | H13: =H10-H11-H12 -> 0 | I13: =I10-I11-I12 -> 0 | J13: =J10-J11-J12 -> 0 | ... N13: =N10-N11-N12 -> 0 | O13: =IFERROR((INDEX(C13:N13,1,LatestAudCol)-INDEX(C13:N13,1,PriorAudCol))/ABS(INDEX(C13:N13,1,PriorAudCol)),"")
A14: B. COST OF SALES
A15: 8 | B15: Raw Material - Imported
A16: 9 | B16: Raw Material - Indigenous
A17: 10 | B17: Total Raw Material | C17: =C15+C16 -> 0 | D17: =D15+D16 -> 0 | E17: =E15+E16 -> 0 | F17: =F15+F16 -> 0 | G17: =G15+G16 -> 0 | H17: =H15+H16 -> 0 | I17: =I15+I16 -> 0 | J17: =J15+J16 -> 0 | ... N17: =N15+N16 -> 0
A18: 11 | B18: Spares - Imported
A19: 12 | B19: Spares - Indigenous
A20: 13 | B20: Total Spares | C20: =C18+C19 -> 0 | D20: =D18+D19 -> 0 | E20: =E18+E19 -> 0 | F20: =F18+F19 -> 0 | G20: =G18+G19 -> 0 | H20: =H18+H19 -> 0 | I20: =I18+I19 -> 0 | J20: =J18+J19 -> 0 | ... N20: =N18+N19 -> 0
A21: 14 | B21: Power & Fuel
A22: 15 | B22: Direct Labour
A23: 16 | B23: Other Manufacturing / Direct Costs
A24: 17 | B24: Depreciation & Amortisation
A25: 18 | B25: Add: Opening Stock-in-Process
A26: 19 | B26: Less: Closing Stock-in-Process
A27: 20 | B27: Cost of Production | C27: =C17+C20+C21+C22+C23+C24+C25-C26 -> 0 | D27: =D17+D20+D21+D22+D23+D24+D25-D26 -> 0 | E27: =E17+E20+E21+E22+E23+E24+E25-E26 -> 0 | F27: =F17+F20+F21+F22+F23+F24+F25-F26 -> 0 | G27: =G17+G20+G21+G22+G23+G24+G25-G26 -> 0 | H27: =H17+H20+H21+H22+H23+H24+H25-H26 -> 0 | I27: =I17+I20+I21+I22+I23+I24+I25-I26 -> 0 | J27: =J17+J20+J21+J22+J23+J24+J25-J26 -> 0 | ... N27: =N17+N20+N21+N22+N23+N24+N25-N26 -> 0
A28: 21 | B28: Add: Opening Stock of FG
A29: 22 | B29: Less: Closing Stock of FG
A30: 23 | B30: Cost of Sales | C30: =C27+C28-C29 -> 0 | D30: =D27+D28-D29 -> 0 | E30: =E27+E28-E29 -> 0 | F30: =F27+F28-F29 -> 0 | G30: =G27+G28-G29 -> 0 | H30: =H27+H28-H29 -> 0 | I30: =I27+I28-I29 -> 0 | J30: =J27+J28-J29 -> 0 | ... N30: =N27+N28-N29 -> 0
A31: C. OPERATING PROFIT
A32: 24 | B32: Selling & General Admin Expenses
A33: 25 | B33: Operating Profit Before Interest (OPBI) | C33: =C13-C30-C32 -> 0 | D33: =D13-D30-D32 -> 0 | E33: =E13-E30-E32 -> 0 | F33: =F13-F30-F32 -> 0 | G33: =G13-G30-G32 -> 0 | H33: =H13-H30-H32 -> 0 | I33: =I13-I30-I32 -> 0 | J33: =J13-J30-J32 -> 0 | ... N33: =N13-N30-N32 -> 0 | O33: =IFERROR((INDEX(C33:N33,1,LatestAudCol)-INDEX(C33:N33,1,PriorAudCol))/ABS(INDEX(C33:N33,1,PriorAudCol)),"")
A34: 26 | B34: Interest on Working Capital
A35: 27 | B35: Interest on Term Loans
A36: 28 | B36: Other Finance Charges
A37: 29 | B37: Total Interest Outgo | C37: =C34+C35+C36 -> 0 | D37: =D34+D35+D36 -> 0 | E37: =E34+E35+E36 -> 0 | F37: =F34+F35+F36 -> 0 | G37: =G34+G35+G36 -> 0 | H37: =H34+H35+H36 -> 0 | I37: =I34+I35+I36 -> 0 | J37: =J34+J35+J36 -> 0 | ... N37: =N34+N35+N36 -> 0
A38: 30 | B38: Operating Profit After Interest (OPAI) | C38: =C33-C37 -> 0 | D38: =D33-D37 -> 0 | E38: =E33-E37 -> 0 | F38: =F33-F37 -> 0 | G38: =G33-G37 -> 0 | H38: =H33-H37 -> 0 | I38: =I33-I37 -> 0 | J38: =J33-J37 -> 0 | ... N38: =N33-N37 -> 0 | O38: =IFERROR((INDEX(C38:N38,1,LatestAudCol)-INDEX(C38:N38,1,PriorAudCol))/ABS(INDEX(C38:N38,1,PriorAudCol)),"")
A39: D. OTHER NON-OPERATING
A40: 31 | B40: Interest on Unsecured / Related-party Loans
A41: 32 | B41: Income from Investments & Deposits
A42: 33 | B42: Forex Gain
A43: 34 | B43: Profit on Sale of Fixed Assets
A44: 35 | B44: Profit on Sale of Investments
A45: 36 | B45: Total Other Non-Op Income | C45: =SUM(C40:C44) -> 0 | D45: =SUM(D40:D44) -> 0 | E45: =SUM(E40:E44) -> 0 | F45: =SUM(F40:F44) -> 0 | G45: =SUM(G40:G44) -> 0 | H45: =SUM(H40:H44) -> 0 | I45: =SUM(I40:I44) -> 0 | J45: =SUM(J40:J44) -> 0 | ... N45: =SUM(N40:N44) -> 0
A46: 37 | B46: Goodwill / Intangibles Written off
A47: 38 | B47: Preliminary Expenses Written off
A48: 39 | B48: Other Misc Expenses Written off
A49: 40 | B49: Forex Loss
A50: 41 | B50: Loss on Sale of Fixed Assets
A51: 42 | B51: Total Other Non-Op Expenses | C51: =SUM(C46:C50) -> 0 | D51: =SUM(D46:D50) -> 0 | E51: =SUM(E46:E50) -> 0 | F51: =SUM(F46:F50) -> 0 | G51: =SUM(G46:G50) -> 0 | H51: =SUM(H46:H50) -> 0 | I51: =SUM(I46:I50) -> 0 | J51: =SUM(J46:J50) -> 0 | ... N51: =SUM(N46:N50) -> 0
A52: 43 | B52: Net Non-Operating Income | C52: =C45-C51 -> 0 | D52: =D45-D51 -> 0 | E52: =E45-E51 -> 0 | F52: =F45-F51 -> 0 | G52: =G45-G51 -> 0 | H52: =H45-H51 -> 0 | I52: =I45-I51 -> 0 | J52: =J45-J51 -> 0 | ... N52: =N45-N51 -> 0
A53: E. PROFIT
A54: 44 | B54: Profit Before Tax (PBT) | C54: =C38+C52 -> 0 | D54: =D38+D52 -> 0 | E54: =E38+E52 -> 0 | F54: =F38+F52 -> 0 | G54: =G38+G52 -> 0 | H54: =H38+H52 -> 0 | I54: =I38+I52 -> 0 | J54: =J38+J52 -> 0 | ... N54: =N38+N52 -> 0 | O54: =IFERROR((INDEX(C54:N54,1,LatestAudCol)-INDEX(C54:N54,1,PriorAudCol))/ABS(INDEX(C54:N54,1,PriorAudCol)),"")
A55: 45 | B55: MAT Credit
A56: 46 | B56: Provision for Taxes
A57: 47 | B57: Prior Period Expenses
A58: 48 | B58: Net Profit / Loss (PAT) | C58: =C54-C56-C57+C55 -> 0 | D58: =D54-D56-D57+D55 -> 0 | E58: =E54-E56-E57+E55 -> 0 | F58: =F54-F56-F57+F55 -> 0 | G58: =G54-G56-G57+G55 -> 0 | H58: =H54-H56-H57+H55 -> 0 | I58: =I54-I56-I57+I55 -> 0 | J58: =J54-J56-J57+J55 -> 0 | ... N58: =N54-N56-N57+N55 -> 0 | O58: =IFERROR((INDEX(C58:N58,1,LatestAudCol)-INDEX(C58:N58,1,PriorAudCol))/ABS(INDEX(C58:N58,1,PriorAudCol)),"")
A59: 49 | B59: Equity Dividend Paid (incl. DDT)
A60: 50 | B60: Retained Profit | C60: =C58-C59 -> 0 | D60: =D58-D59 -> 0 | E60: =E58-E59 -> 0 | F60: =F58-F59 -> 0 | G60: =G58-G59 -> 0 | H60: =H58-H59 -> 0 | I60: =I58-I59 -> 0 | J60: =J58-J59 -> 0 | ... N60: =N58-N59 -> 0 | O60: =IFERROR((INDEX(C60:N60,1,LatestAudCol)-INDEX(C60:N60,1,PriorAudCol))/ABS(INDEX(C60:N60,1,PriorAudCol)),"")

Sheet 3_Balance_Sheet
A1: =CONCATENATE("BALANCE SHEET | ₹ Crores | ", BorrowerName) -> BALANCE SHEET | ₹ Crores |
A2: Liabilities first, then Assets. CHECK row at bottom must = 0.
A3: Sr | B3: Particulars | C3: Yr 1 | D3: Yr 2 | E3: Yr 3 | F3: Yr 4 | G3: Yr 5 | H3: Yr 6 | I3: Yr 7 | J3: Yr 8 | K3: Yr 9 | L3: Yr 10 | M3: Yr 11 | N3: Yr 12 | O3: Δ Latest vs Prior Aud | P3: Auto-Comment
B4: Year → | C4: =INDEX('0_Setup'!$B$48:$B$59,1) -> 2022-23 | D4: =INDEX('0_Setup'!$B$48:$B$59,2) -> 2023-24 | E4: =INDEX('0_Setup'!$B$48:$B$59,3) -> 2024-25 | F4: =INDEX('0_Setup'!$B$48:$B$59,4) -> 2024-25 | G4: =INDEX('0_Setup'!$B$48:$B$59,5) -> 2025-26 | H4: =INDEX('0_Setup'!$B$48:$B$59,6) -> 2026-27 | I4: =INDEX('0_Setup'!$B$48:$B$59,7) -> 2027-28 | J4: =INDEX('0_Setup'!$B$48:$B$59,8) -> 2028-29 | K4: =INDEX('0_Setup'!$B$48:$B$59,9) -> 2029-30 | L4: =INDEX('0_Setup'!$B$48:$B$59,10) | M4: =INDEX('0_Setup'!$B$48:$B$59,11) | N4: =INDEX('0_Setup'!$B$48:$B$59,12)
B5: Type → | C5: =INDEX('0_Setup'!$C$48:$C$59,1) -> Audited | D5: =INDEX('0_Setup'!$C$48:$C$59,2) -> Audited | E5: =INDEX('0_Setup'!$C$48:$C$59,3) -> Estimated | F5: =INDEX('0_Setup'!$C$48:$C$59,4) -> Audited/Provisional | G5: =INDEX('0_Setup'!$C$48:$C$59,5) -> Estimated | H5: =INDEX('0_Setup'!$C$48:$C$59,6) -> Projected | I5: =INDEX('0_Setup'!$C$48:$C$59,7) -> Projected | J5: =INDEX('0_Setup'!$C$48:$C$59,8) -> Projected | K5: =INDEX('0_Setup'!$C$48:$C$59,9) -> Projected | L5: =INDEX('0_Setup'!$C$48:$C$59,10) | M5: =INDEX('0_Setup'!$C$48:$C$59,11) | N5: =INDEX('0_Setup'!$C$48:$C$59,12)
A6: CURRENT LIABILITIES — Short Term Borrowings from Banks
A7: 1 | B7: From Applicant Bank
A8: 2 | B8: From Other Banks
A9: 3 | B9: Under Buyers Credit
A10: 4 | B10: (of which Bills Purchased & Discounted)
A11: 5 | B11: Total Short Term Borrowings from Banks | C11: =C7+C8+C9 -> 0 | D11: =D7+D8+D9 -> 0 | E11: =E7+E8+E9 -> 0 | F11: =F7+F8+F9 -> 0 | G11: =G7+G8+G9 -> 0 | H11: =H7+H8+H9 -> 0 | I11: =I7+I8+I9 -> 0 | J11: =J7+J8+J9 -> 0 | ... N11: =N7+N8+N9 -> 0
A12: CURRENT LIABILITIES — Others
A13: 6 | B13: Short Term Borrowings from Others
A14: 7 | B14: Sundry Creditors (Trade — Without LC)
A15: 8 | B15: Sundry Creditors (Trade — Under LC)
A16: 9 | B16: Advance from Customers & Dealer Deposits
A17: 10 | B17: Provision for Taxation
A18: 11 | B18: Dividend Payable (incl. Tax)
A19: 12 | B19: Other Statutory Liab. (within 1 yr)
A20: 13 | B20: TL Instalments (within 1 yr)
A21: 14 | B21: Other CL & Provisions (within 1 yr)
A22: 15 | B22: Provision for Expenditure
A23: 16 | B23: Sundry Creditors for Capital Goods
A24: 17 | B24: Sundry Creditors for Expenses
A25: 18 | B25: Others (Current Liab.)
A26: 19 | B26: Total Other Current Liabilities | C26: =SUM(C13:C25) -> 0 | D26: =SUM(D13:D25) -> 0 | E26: =SUM(E13:E25) -> 0 | F26: =SUM(F13:F25) -> 0 | G26: =SUM(G13:G25) -> 0 | H26: =SUM(H13:H25) -> 0 | I26: =SUM(I13:I25) -> 0 | J26: =SUM(J13:J25) -> 0 | ... N26: =SUM(N13:N25) -> 0
A27: 20 | B27: Total Current Liabilities (TCL) | C27: =C11+C26 -> 0 | D27: =D11+D26 -> 0 | E27: =E11+E26 -> 0 | F27: =F11+F26 -> 0 | G27: =G11+G26 -> 0 | H27: =H11+H26 -> 0 | I27: =I11+I26 -> 0 | J27: =J11+J26 -> 0 | ... N27: =N11+N26 -> 0 | O27: =IFERROR((INDEX(C27:N27,1,LatestAudCol)-INDEX(C27:N27,1,PriorAudCol))/ABS(INDEX(C27:N27,1,PriorAudCol)),"")
A28: TERM LIABILITIES
A29: 21 | B29: Debentures (>1 yr)
A30: 22 | B30: Preference Shares (1-12 yrs)
A31: 23 | B31: Secured Term Loans (excl. <1yr instalments)
A32: 24 | B32: Deferred Payment Credits (excl. <1yr instalments)
A33: 25 | B33: Term/Public Deposits (>1 yr)
A34: 26 | B34: Unsecured Loans from Promoters / Group Cos
A35: 27 | B35: Unsecured Loans — Others
A36: 28 | B36: Capex Creditors (>1 yr)
A37: 29 | B37: Non-Current Provisions
A38: 30 | B38: Deferred Tax Liabilities
A39: 31 | B39: Total Term Liabilities (TTL) | C39: =SUM(C29:C38) -> 0 | D39: =SUM(D29:D38) -> 0 | E39: =SUM(E29:E38) -> 0 | F39: =SUM(F29:F38) -> 0 | G39: =SUM(G29:G38) -> 0 | H39: =SUM(H29:H38) -> 0 | I39: =SUM(I29:I38) -> 0 | J39: =SUM(J29:J38) -> 0 | ... N39: =SUM(N29:N38) -> 0 | O39: =IFERROR((INDEX(C39:N39,1,LatestAudCol)-INDEX(C39:N39,1,PriorAudCol))/ABS(INDEX(C39:N39,1,PriorAudCol)),"")
A40: 32 | B40: Total Outside Liabilities (TOL) | C40: =C27+C39 -> 0 | D40: =D27+D39 -> 0 | E40: =E27+E39 -> 0 | F40: =F27+F39 -> 0 | G40: =G27+G39 -> 0 | H40: =H27+H39 -> 0 | I40: =I27+I39 -> 0 | J40: =J27+J39 -> 0 | ... N40: =N27+N39 -> 0 | O40: =IFERROR((INDEX(C40:N40,1,LatestAudCol)-INDEX(C40:N40,1,PriorAudCol))/ABS(INDEX(C40:N40,1,PriorAudCol)),"")
A41: 33 | B41: Memo: Corporate Guarantees in favour of Group Cos
A42: NET WORTH
A43: 34 | B43: Equity Share Capital
A44: 35 | B44: Preference Share Capital
A45: 36 | B45: General Reserve
A46: 37 | B46: Revaluation Reserve
A47: 38 | B47: Surplus / Deficit in P&L A/c
A48: 39 | B48: Other Reserves (excl. Provisions)
A49: 40 | B49: Security Premium
A50: 41 | B50: Warrants / Options / ESOPs
A51: 42 | B51: Share Application Money
A52: 43 | B52: Total Net Worth (TNW) | C52: =SUM(C43:C51) -> 0 | D52: =SUM(D43:D51) -> 0 | E52: =SUM(E43:E51) -> 0 | F52: =SUM(F43:F51) -> 0 | G52: =SUM(G43:G51) -> 0 | H52: =SUM(H43:H51) -> 0 | I52: =SUM(I43:I51) -> 0 | J52: =SUM(J43:J51) -> 0 | ... N52: =SUM(N43:N51) -> 0 | O52: =IFERROR((INDEX(C52:N52,1,LatestAudCol)-INDEX(C52:N52,1,PriorAudCol))/ABS(INDEX(C52:N52,1,PriorAudCol)),"")
A53: 44 | B53: TOTAL LIABILITIES | C53: =C40+C52 -> 0 | D53: =D40+D52 -> 0 | E53: =E40+E52 -> 0 | F53: =F40+F52 -> 0 | G53: =G40+G52 -> 0 | H53: =H40+H52 -> 0 | I53: =I40+I52 -> 0 | J53: =J40+J52 -> 0 | ... N53: =N40+N52 -> 0 | O53: =IFERROR((INDEX(C53:N53,1,LatestAudCol)-INDEX(C53:N53,1,PriorAudCol))/ABS(INDEX(C53:N53,1,PriorAudCol)),"")
A54: CURRENT ASSETS
A55: 45 | B55: Cash & Cash Equivalents
A56: 46 | B56: Investments in Govt & Trustee Securities
A57: 47 | B57: Fixed Deposits with Banks
A58: 48 | B58: Total Investments (other than LT) | C58: =C55+C56+C57 -> 0 | D58: =D55+D56+D57 -> 0 | E58: =E55+E56+E57 -> 0 | F58: =F55+F56+F57 -> 0 | G58: =G55+G56+G57 -> 0 | H58: =H55+H56+H57 -> 0 | I58: =I55+I56+I57 -> 0 | J58: =J55+J56+J57 -> 0 | ... N58: =N55+N56+N57 -> 0
A59: 49 | B59: Receivables (excl. deferred / exports / BP&BD)
A60: 50 | B60: Export Receivables
A61: 51 | B61: Bills Purchased & Discounted
A62: 52 | B62: Instalments & Deferred Receivables (within 1 yr)
A63: 53 | B63: Total Other Receivables | C63: =SUM(C59:C62) -> 0 | D63: =SUM(D59:D62) -> 0 | E63: =SUM(E59:E62) -> 0 | F63: =SUM(F59:F62) -> 0 | G63: =SUM(G59:G62) -> 0 | H63: =SUM(H59:H62) -> 0 | I63: =SUM(I59:I62) -> 0 | J63: =SUM(J59:J62) -> 0 | ... N63: =SUM(N59:N62) -> 0 | O63: =IFERROR((INDEX(C63:N63,1,LatestAudCol)-INDEX(C63:N63,1,PriorAudCol))/ABS(INDEX(C63:N63,1,PriorAudCol)),"")
A64: INVENTORY
A65: 54 | B65: Raw Material — Imported
A66: 55 | B66: Raw Material — Indigenous
A67: 56 | B67: Total Raw Material | C67: =C65+C66 -> 0 | D67: =D65+D66 -> 0 | E67: =E65+E66 -> 0 | F67: =F65+F66 -> 0 | G67: =G65+G66 -> 0 | H67: =H65+H66 -> 0 | I67: =I65+I66 -> 0 | J67: =J65+J66 -> 0 | ... N67: =N65+N66 -> 0
A68: 57 | B68: Stock-in-Process
A69: 58 | B69: Finished Goods
A70: 59 | B70: Other Consumable Spares — Imported
A71: 60 | B71: Other Consumable Spares — Indigenous
A72: 61 | B72: Total Other Consumable Spares | C72: =C70+C71 -> 0 | D72: =D70+D71 -> 0 | E72: =E70+E71 -> 0 | F72: =F70+F71 -> 0 | G72: =G70+G71 -> 0 | H72: =H70+H71 -> 0 | I72: =I70+I71 -> 0 | J72: =J70+J71 -> 0 | ... N72: =N70+N71 -> 0
A73: 62 | B73: Total Inventory | C73: =C67+C68+C69+C72 -> 0 | D73: =D67+D68+D69+D72 -> 0 | E73: =E67+E68+E69+E72 -> 0 | F73: =F67+F68+F69+F72 -> 0 | G73: =G67+G68+G69+G72 -> 0 | H73: =H67+H68+H69+H72 -> 0 | I73: =I67+I68+I69+I72 -> 0 | J73: =J67+J68+J69+J72 -> 0 | ... N73: =N67+N68+N69+N72 -> 0 | O73: =IFERROR((INDEX(C73:N73,1,LatestAudCol)-INDEX(C73:N73,1,PriorAudCol))/ABS(INDEX(C73:N73,1,PriorAudCol)),"")
A74: 63 | B74: Advances to Suppliers of RM
A75: 64 | B75: Advance Payment of Taxes
A76: OTHER CURRENT ASSETS
A77: 65 | B77: TUFS
A78: 66 | B78: Excise / Customs Duty Receivables
A79: 67 | B79: CENVAT Credit / GST Input
A80: 68 | B80: Others (OCA)
A81: 69 | B81: Total Other Current Assets | C81: =SUM(C77:C80) -> 0 | D81: =SUM(D77:D80) -> 0 | E81: =SUM(E77:E80) -> 0 | F81: =SUM(F77:F80) -> 0 | G81: =SUM(G77:G80) -> 0 | H81: =SUM(H77:H80) -> 0 | I81: =SUM(I77:I80) -> 0 | J81: =SUM(J77:J80) -> 0 | ... N81: =SUM(N77:N80) -> 0
A82: 70 | B82: Total Current Assets (TCA) | C82: =C58+C63+C73+C74+C75+C81 -> 0 | D82: =D58+D63+D73+D74+D75+D81 -> 0 | E82: =E58+E63+E73+E74+E75+E81 -> 0 | F82: =F58+F63+F73+F74+F75+F81 -> 0 | G82: =G58+G63+G73+G74+G75+G81 -> 0 | H82: =H58+H63+H73+H74+H75+H81 -> 0 | I82: =I58+I63+I73+I74+I75+I81 -> 0 | J82: =J58+J63+J73+J74+J75+J81 -> 0 | ... N82: =N58+N63+N73+N74+N75+N81 -> 0 | O82: =IFERROR((INDEX(C82:N82,1,LatestAudCol)-INDEX(C82:N82,1,PriorAudCol))/ABS(INDEX(C82:N82,1,PriorAudCol)),"")
A83: FIXED ASSETS
A84: 71 | B84: Gross Block
A85: 72 | B85: Capital Work in Progress
A86: 73 | B86: Depreciation (till date)
A87: 74 | B87: Net Block | C87: =C84+C85-C86 -> 0 | D87: =D84+D85-D86 -> 0 | E87: =E84+E85-E86 -> 0 | F87: =F84+F85-F86 -> 0 | G87: =G84+G85-G86 -> 0 | H87: =H84+H85-H86 -> 0 | I87: =I84+I85-I86 -> 0 | J87: =J84+J85-J86 -> 0 | ... N87: =N84+N85-N86 -> 0 | O87: =IFERROR((INDEX(C87:N87,1,LatestAudCol)-INDEX(C87:N87,1,PriorAudCol))/ABS(INDEX(C87:N87,1,PriorAudCol)),"")
A88: NON-CURRENT ASSETS
A89: 75 | B89: Investments in Group Companies
A90: 76 | B90: Other Investments
A91: 77 | B91: Total Investments (LT) | C91: =C89+C90 -> 0 | D91: =D89+D90 -> 0 | E91: =E89+E90 -> 0 | F91: =F89+F90 -> 0 | G91: =G89+G90 -> 0 | H91: =H89+H90 -> 0 | I91: =I89+I90 -> 0 | J91: =J89+J90 -> 0 | ... N91: =N89+N90 -> 0
A92: 78 | B92: Advances to Suppliers of Capital Goods
A93: 79 | B93: Deferred Receivables (>1 yr)
A94: 80 | B94: Deposits
A95: 81 | B95: Loans & Advances to Group Entities
A96: 82 | B96: Receivables (over 6 months)
A97: 83 | B97: A/R from Group Entities
A98: 84 | B98: Receivables from Directors / Employees
A99: 85 | B99: Others (NCA)
A100: 86 | B100: Total Non-Current Assets — Others | C100: =SUM(C92:C99) -> 0 | D100: =SUM(D92:D99) -> 0 | E100: =SUM(E92:E99) -> 0 | F100: =SUM(F92:F99) -> 0 | G100: =SUM(G92:G99) -> 0 | H100: =SUM(H92:H99) -> 0 | I100: =SUM(I92:I99) -> 0 | J100: =SUM(J92:J99) -> 0 | ... N100: =SUM(N92:N99) -> 0
...

Sheet 4_DSCR
A1: =CONCATENATE("DSCR CALCULATION | ₹ Crores | ", BorrowerName) -> DSCR CALCULATION | ₹ Crores |
A2: Cash Accruals + Interest pulled from Operating Statement automatically.
A3: Sr | B3: Particulars | C3: Yr 1 | D3: Yr 2 | E3: Yr 3 | F3: Yr 4 | G3: Yr 5 | H3: Yr 6 | I3: Yr 7 | J3: Yr 8 | K3: Yr 9 | L3: Yr 10 | M3: Yr 11 | N3: Yr 12 | O3: Δ Latest vs Prior Aud | P3: Auto-Comment
B4: Year → | C4: =INDEX('0_Setup'!$B$48:$B$59,1) -> 2022-23 | D4: =INDEX('0_Setup'!$B$48:$B$59,2) -> 2023-24 | E4: =INDEX('0_Setup'!$B$48:$B$59,3) -> 2024-25 | F4: =INDEX('0_Setup'!$B$48:$B$59,4) -> 2024-25 | G4: =INDEX('0_Setup'!$B$48:$B$59,5) -> 2025-26 | H4: =INDEX('0_Setup'!$B$48:$B$59,6) -> 2026-27 | I4: =INDEX('0_Setup'!$B$48:$B$59,7) -> 2027-28 | J4: =INDEX('0_Setup'!$B$48:$B$59,8) -> 2028-29 | K4: =INDEX('0_Setup'!$B$48:$B$59,9) -> 2029-30 | L4: =INDEX('0_Setup'!$B$48:$B$59,10) | M4: =INDEX('0_Setup'!$B$48:$B$59,11) | N4: =INDEX('0_Setup'!$B$48:$B$59,12)
B5: Type → | C5: =INDEX('0_Setup'!$C$48:$C$59,1) -> Audited | D5: =INDEX('0_Setup'!$C$48:$C$59,2) -> Audited | E5: =INDEX('0_Setup'!$C$48:$C$59,3) -> Estimated | F5: =INDEX('0_Setup'!$C$48:$C$59,4) -> Audited/Provisional | G5: =INDEX('0_Setup'!$C$48:$C$59,5) -> Estimated | H5: =INDEX('0_Setup'!$C$48:$C$59,6) -> Projected | I5: =INDEX('0_Setup'!$C$48:$C$59,7) -> Projected | J5: =INDEX('0_Setup'!$C$48:$C$59,8) -> Projected | K5: =INDEX('0_Setup'!$C$48:$C$59,9) -> Projected | L5: =INDEX('0_Setup'!$C$48:$C$59,10) | M5: =INDEX('0_Setup'!$C$48:$C$59,11) | N5: =INDEX('0_Setup'!$C$48:$C$59,12)
A6: A. CASH ACCRUALS
A7: 1 | B7: PAT + Depreciation (Cash Accruals) | C7: ='2_Operating_Statement'!C58+'2_Operating_Statement'!C24 -> 0 | D7: ='2_Operating_Statement'!D58+'2_Operating_Statement'!D24 -> 0 | E7: ='2_Operating_Statement'!E58+'2_Operating_Statement'!E24 -> 0 | F7: ='2_Operating_Statement'!F58+'2_Operating_Statement'!F24 -> 0 | G7: ='2_Operating_Statement'!G58+'2_Operating_Statement'!G24 -> 0 | H7: ='2_Operating_Statement'!H58+'2_Operating_Statement'!H24 -> 0 | I7: ='2_Operating_Statement'!I58+'2_Operating_Statement'!I24 -> 0 | J7: ='2_Operating_Statement'!J58+'2_Operating_Statement'!J24 -> 0 | ... N7: ='2_Operating_Statement'!N58+'2_Operating_Statement'!N24 -> 0
A8: 2 | B8: Less: Cash Accruals utilised in projects by Borrower
A9: 3 | B9: Net Cash Accruals available for Debt Service | C9: =C7-C8 -> 0 | D9: =D7-D8 -> 0 | E9: =E7-E8 -> 0 | F9: =F7-F8 -> 0 | G9: =G7-G8 -> 0 | H9: =H7-H8 -> 0 | I9: =I7-I8 -> 0 | J9: =J7-J8 -> 0 | ... N9: =N7-N8 -> 0
A10: B. DEBT SERVICE OBLIGATIONS
A11: 4 | B11: TL Instalments — Applicant Bank
A12: 5 | B12: TL Instalments — Other Banks
A13: 6 | B13: Total TL Instalments (All Banks) | C13: =C11+C12 -> 0 | D13: =D11+D12 -> 0 | E13: =E11+E12 -> 0 | F13: =F11+F12 -> 0 | G13: =G11+G12 -> 0 | H13: =H11+H12 -> 0 | I13: =I11+I12 -> 0 | J13: =J11+J12 -> 0 | ... N13: =N11+N12 -> 0
A14: 7 | B14: Interest on Term Loans (from Op Stmt) | C14: ='2_Operating_Statement'!C35 -> 0 | D14: ='2_Operating_Statement'!D35 -> 0 | E14: ='2_Operating_Statement'!E35 -> 0 | F14: ='2_Operating_Statement'!F35 -> 0 | G14: ='2_Operating_Statement'!G35 -> 0 | H14: ='2_Operating_Statement'!H35 -> 0 | I14: ='2_Operating_Statement'!I35 -> 0 | J14: ='2_Operating_Statement'!J35 -> 0 | ... N14: ='2_Operating_Statement'!N35 -> 0
A15: 8 | B15: Total Debt Service | C15: =C13+C14 -> 0 | D15: =D13+D14 -> 0 | E15: =E13+E14 -> 0 | F15: =F13+F14 -> 0 | G15: =G13+G14 -> 0 | H15: =H13+H14 -> 0 | I15: =I13+I14 -> 0 | J15: =J13+J14 -> 0 | ... N15: =N13+N14 -> 0
A16: C. DSCR RATIOS
A17: 9 | B17: Gross DSCR = (NCA + Int TL) / (Inst + Int TL) | C17: =IFERROR((C9+C14)/(C13+C14),0) -> 0 | D17: =IFERROR((D9+D14)/(D13+D14),0) -> 0 | E17: =IFERROR((E9+E14)/(E13+E14),0) -> 0 | F17: =IFERROR((F9+F14)/(F13+F14),0) -> 0 | G17: =IFERROR((G9+G14)/(G13+G14),0) -> 0 | H17: =IFERROR((H9+H14)/(H13+H14),0) -> 0 | I17: =IFERROR((I9+I14)/(I13+I14),0) -> 0 | J17: =IFERROR((J9+J14)/(J13+J14),0) -> 0 | ... N17: =IFERROR((N9+N14)/(N13+N14),0) -> 0
A18: 10 | B18: Net DSCR = NCA / Instalments | C18: =IFERROR(C9/C13,0) -> 0 | D18: =IFERROR(D9/D13,0) -> 0 | E18: =IFERROR(E9/E13,0) -> 0 | F18: =IFERROR(F9/F13,0) -> 0 | G18: =IFERROR(G9/G13,0) -> 0 | H18: =IFERROR(H9/H13,0) -> 0 | I18: =IFERROR(I9/I13,0) -> 0 | J18: =IFERROR(J9/J13,0) -> 0 | ... N18: =IFERROR(N9/N13,0) -> 0
A19: 11 | B19: Average Gross DSCR (over years with TL instalments) | C19: =IFERROR(AVERAGEIF(C13:N13,">0",C17:N17),0) -> 0 | P19: =IF(C19<MinDSCR_Avg,"⚠ Average DSCR "&TEXT(C19,"0.00x")&" below threshold of "&TEXT(MinDSCR_Avg,"0.00x"),"✓ Average DSCR "&TEXT(C19,"0.00x")&" meets threshold") -> ⚠ Average DSCR 0.00x below threshold of 1.50x
A21: PROJECT FINANCE OVERLAY (DSCR threshold suppression for construction phase)
A22: =IF(ProjectFinance="Yes","⚠ This is a Project Finance facility (Phase: "&ProjectPhase&"). "&IF(ProjectPhase="Under-Construction","DSCR thresholds are SUPPRESSED during construction years. Greenfield projects generate zero cash flows pre-DCCO; apply DSCR covenant only from FY"&IF(DCCO_Year="","[DCCO not set]",DCCO_Year)&" onwards. Validate via Construction Period Interest moratorium and DSRA arrangement per RBI Project Finance Directions 2025.","Project is operational — standard DSCR covenants apply across all years."),"Standard corporate facility — DSCR covenants apply across all projection years per Setup thresholds.") -> Standard corporate facility — DSCR covenants apply across all projection years per Setup thresholds.

Sheet 5_Holding_Levels
A1: =CONCATENATE("HOLDING LEVELS | ", BorrowerName) -> HOLDING LEVELS |
A2: Inventory & receivables/payables in months. Auto-pulled where possible.
A3: Sr | B3: Particulars | C3: Yr 1 | D3: Yr 2 | E3: Yr 3 | F3: Yr 4 | G3: Yr 5 | H3: Yr 6 | I3: Yr 7 | J3: Yr 8 | K3: Yr 9 | L3: Yr 10 | M3: Yr 11 | N3: Yr 12 | O3: Δ Latest vs Prior Aud | P3: Auto-Comment
B4: Year → | C4: =INDEX('0_Setup'!$B$48:$B$59,1) -> 2022-23 | D4: =INDEX('0_Setup'!$B$48:$B$59,2) -> 2023-24 | E4: =INDEX('0_Setup'!$B$48:$B$59,3) -> 2024-25 | F4: =INDEX('0_Setup'!$B$48:$B$59,4) -> 2024-25 | G4: =INDEX('0_Setup'!$B$48:$B$59,5) -> 2025-26 | H4: =INDEX('0_Setup'!$B$48:$B$59,6) -> 2026-27 | I4: =INDEX('0_Setup'!$B$48:$B$59,7) -> 2027-28 | J4: =INDEX('0_Setup'!$B$48:$B$59,8) -> 2028-29 | K4: =INDEX('0_Setup'!$B$48:$B$59,9) -> 2029-30 | L4: =INDEX('0_Setup'!$B$48:$B$59,10) | M4: =INDEX('0_Setup'!$B$48:$B$59,11) | N4: =INDEX('0_Setup'!$B$48:$B$59,12)
B5: Type → | C5: =INDEX('0_Setup'!$C$48:$C$59,1) -> Audited | D5: =INDEX('0_Setup'!$C$48:$C$59,2) -> Audited | E5: =INDEX('0_Setup'!$C$48:$C$59,3) -> Estimated | F5: =INDEX('0_Setup'!$C$48:$C$59,4) -> Audited/Provisional | G5: =INDEX('0_Setup'!$C$48:$C$59,5) -> Estimated | H5: =INDEX('0_Setup'!$C$48:$C$59,6) -> Projected | I5: =INDEX('0_Setup'!$C$48:$C$59,7) -> Projected | J5: =INDEX('0_Setup'!$C$48:$C$59,8) -> Projected | K5: =INDEX('0_Setup'!$C$48:$C$59,9) -> Projected | L5: =INDEX('0_Setup'!$C$48:$C$59,10) | M5: =INDEX('0_Setup'!$C$48:$C$59,11) | N5: =INDEX('0_Setup'!$C$48:$C$59,12)
A6: INVENTORY HOLDING — RAW MATERIAL
A7: 1 | B7: RM Imported (linked from BS) | C7: ='3_Balance_Sheet'!C65 -> 0 | D7: ='3_Balance_Sheet'!D65 -> 0 | E7: ='3_Balance_Sheet'!E65 -> 0 | F7: ='3_Balance_Sheet'!F65 -> 0 | G7: ='3_Balance_Sheet'!G65 -> 0 | H7: ='3_Balance_Sheet'!H65 -> 0 | I7: ='3_Balance_Sheet'!I65 -> 0 | J7: ='3_Balance_Sheet'!J65 -> 0 | ... N7: ='3_Balance_Sheet'!N65 -> 0
A8: 2 | B8: Months' RM Imported consumption | C8: =IFERROR(C7*12/'2_Operating_Statement'!C15,0) -> 0 | D8: =IFERROR(D7*12/'2_Operating_Statement'!D15,0) -> 0 | E8: =IFERROR(E7*12/'2_Operating_Statement'!E15,0) -> 0 | F8: =IFERROR(F7*12/'2_Operating_Statement'!F15,0) -> 0 | G8: =IFERROR(G7*12/'2_Operating_Statement'!G15,0) -> 0 | H8: =IFERROR(H7*12/'2_Operating_Statement'!H15,0) -> 0 | I8: =IFERROR(I7*12/'2_Operating_Statement'!I15,0) -> 0 | J8: =IFERROR(J7*12/'2_Operating_Statement'!J15,0) -> 0 | ... N8: =IFERROR(N7*12/'2_Operating_Statement'!N15,0) -> 0
A9: 3 | B9: RM Indigenous (linked from BS) | C9: ='3_Balance_Sheet'!C66 -> 0 | D9: ='3_Balance_Sheet'!D66 -> 0 | E9: ='3_Balance_Sheet'!E66 -> 0 | F9: ='3_Balance_Sheet'!F66 -> 0 | G9: ='3_Balance_Sheet'!G66 -> 0 | H9: ='3_Balance_Sheet'!H66 -> 0 | I9: ='3_Balance_Sheet'!I66 -> 0 | J9: ='3_Balance_Sheet'!J66 -> 0 | ... N9: ='3_Balance_Sheet'!N66 -> 0
A10: 4 | B10: Months' RM Indigenous consumption | C10: =IFERROR(C9*12/'2_Operating_Statement'!C16,0) -> 0 | D10: =IFERROR(D9*12/'2_Operating_Statement'!D16,0) -> 0 | E10: =IFERROR(E9*12/'2_Operating_Statement'!E16,0) -> 0 | F10: =IFERROR(F9*12/'2_Operating_Statement'!F16,0) -> 0 | G10: =IFERROR(G9*12/'2_Operating_Statement'!G16,0) -> 0 | H10: =IFERROR(H9*12/'2_Operating_Statement'!H16,0) -> 0 | I10: =IFERROR(I9*12/'2_Operating_Statement'!I16,0) -> 0 | J10: =IFERROR(J9*12/'2_Operating_Statement'!J16,0) -> 0 | ... N10: =IFERROR(N9*12/'2_Operating_Statement'!N16,0) -> 0
A11: INVENTORY HOLDING — SPARES
A12: 5 | B12: Spares Imported (override)
A13: 6 | B13: Months' Spares Imported | C13: =IFERROR(C12*12/'2_Operating_Statement'!C18,0) -> 0 | D13: =IFERROR(D12*12/'2_Operating_Statement'!D18,0) -> 0 | E13: =IFERROR(E12*12/'2_Operating_Statement'!E18,0) -> 0 | F13: =IFERROR(F12*12/'2_Operating_Statement'!F18,0) -> 0 | G13: =IFERROR(G12*12/'2_Operating_Statement'!G18,0) -> 0 | H13: =IFERROR(H12*12/'2_Operating_Statement'!H18,0) -> 0 | I13: =IFERROR(I12*12/'2_Operating_Statement'!I18,0) -> 0 | J13: =IFERROR(J12*12/'2_Operating_Statement'!J18,0) -> 0 | ... N13: =IFERROR(N12*12/'2_Operating_Statement'!N18,0) -> 0
A14: 7 | B14: Spares Indigenous (override)
A15: 8 | B15: Months' Spares Indigenous | C15: =IFERROR(C14*12/'2_Operating_Statement'!C19,0) -> 0 | D15: =IFERROR(D14*12/'2_Operating_Statement'!D19,0) -> 0 | E15: =IFERROR(E14*12/'2_Operating_Statement'!E19,0) -> 0 | F15: =IFERROR(F14*12/'2_Operating_Statement'!F19,0) -> 0 | G15: =IFERROR(G14*12/'2_Operating_Statement'!G19,0) -> 0 | H15: =IFERROR(H14*12/'2_Operating_Statement'!H19,0) -> 0 | I15: =IFERROR(I14*12/'2_Operating_Statement'!I19,0) -> 0 | J15: =IFERROR(J14*12/'2_Operating_Statement'!J19,0) -> 0 | ... N15: =IFERROR(N14*12/'2_Operating_Statement'!N19,0) -> 0
A16: INVENTORY HOLDING — WIP & FG
A17: 9 | B17: Stock-in-Process (linked) | C17: ='3_Balance_Sheet'!C68 -> 0 | D17: ='3_Balance_Sheet'!D68 -> 0 | E17: ='3_Balance_Sheet'!E68 -> 0 | F17: ='3_Balance_Sheet'!F68 -> 0 | G17: ='3_Balance_Sheet'!G68 -> 0 | H17: ='3_Balance_Sheet'!H68 -> 0 | I17: ='3_Balance_Sheet'!I68 -> 0 | J17: ='3_Balance_Sheet'!J68 -> 0 | ... N17: ='3_Balance_Sheet'!N68 -> 0
A18: 10 | B18: Months' SIP / Cost of Production | C18: =IFERROR(C17*12/'2_Operating_Statement'!C27,0) -> 0 | D18: =IFERROR(D17*12/'2_Operating_Statement'!D27,0) -> 0 | E18: =IFERROR(E17*12/'2_Operating_Statement'!E27,0) -> 0 | F18: =IFERROR(F17*12/'2_Operating_Statement'!F27,0) -> 0 | G18: =IFERROR(G17*12/'2_Operating_Statement'!G27,0) -> 0 | H18: =IFERROR(H17*12/'2_Operating_Statement'!H27,0) -> 0 | I18: =IFERROR(I17*12/'2_Operating_Statement'!I27,0) -> 0 | J18: =IFERROR(J17*12/'2_Operating_Statement'!J27,0) -> 0 | ... N18: =IFERROR(N17*12/'2_Operating_Statement'!N27,0) -> 0
A19: 11 | B19: Finished Goods (linked) | C19: ='3_Balance_Sheet'!C69 -> 0 | D19: ='3_Balance_Sheet'!D69 -> 0 | E19: ='3_Balance_Sheet'!E69 -> 0 | F19: ='3_Balance_Sheet'!F69 -> 0 | G19: ='3_Balance_Sheet'!G69 -> 0 | H19: ='3_Balance_Sheet'!H69 -> 0 | I19: ='3_Balance_Sheet'!I69 -> 0 | J19: ='3_Balance_Sheet'!J69 -> 0 | ... N19: ='3_Balance_Sheet'!N69 -> 0
A20: 12 | B20: Months' FG / Cost of Sales | C20: =IFERROR(C19*12/'2_Operating_Statement'!C30,0) -> 0 | D20: =IFERROR(D19*12/'2_Operating_Statement'!D30,0) -> 0 | E20: =IFERROR(E19*12/'2_Operating_Statement'!E30,0) -> 0 | F20: =IFERROR(F19*12/'2_Operating_Statement'!F30,0) -> 0 | G20: =IFERROR(G19*12/'2_Operating_Statement'!G30,0) -> 0 | H20: =IFERROR(H19*12/'2_Operating_Statement'!H30,0) -> 0 | I20: =IFERROR(I19*12/'2_Operating_Statement'!I30,0) -> 0 | J20: =IFERROR(J19*12/'2_Operating_Statement'!J30,0) -> 0 | ... N20: =IFERROR(N19*12/'2_Operating_Statement'!N30,0) -> 0
A21: RECEIVABLES
A22: 13 | B22: Domestic Receivables (linked) | C22: ='3_Balance_Sheet'!C59 -> 0 | D22: ='3_Balance_Sheet'!D59 -> 0 | E22: ='3_Balance_Sheet'!E59 -> 0 | F22: ='3_Balance_Sheet'!F59 -> 0 | G22: ='3_Balance_Sheet'!G59 -> 0 | H22: ='3_Balance_Sheet'!H59 -> 0 | I22: ='3_Balance_Sheet'!I59 -> 0 | J22: ='3_Balance_Sheet'!J59 -> 0 | ... N22: ='3_Balance_Sheet'!N59 -> 0
A23: 14 | B23: Months' Domestic Sales (excl. exports) | C23: =IFERROR(C22*12/'2_Operating_Statement'!C7,0) -> 0 | D23: =IFERROR(D22*12/'2_Operating_Statement'!D7,0) -> 0 | E23: =IFERROR(E22*12/'2_Operating_Statement'!E7,0) -> 0 | F23: =IFERROR(F22*12/'2_Operating_Statement'!F7,0) -> 0 | G23: =IFERROR(G22*12/'2_Operating_Statement'!G7,0) -> 0 | H23: =IFERROR(H22*12/'2_Operating_Statement'!H7,0) -> 0 | I23: =IFERROR(I22*12/'2_Operating_Statement'!I7,0) -> 0 | J23: =IFERROR(J22*12/'2_Operating_Statement'!J7,0) -> 0 | ... N23: =IFERROR(N22*12/'2_Operating_Statement'!N7,0) -> 0
A24: 15 | B24: Export Receivables (linked) | C24: ='3_Balance_Sheet'!C60 -> 0 | D24: ='3_Balance_Sheet'!D60 -> 0 | E24: ='3_Balance_Sheet'!E60 -> 0 | F24: ='3_Balance_Sheet'!F60 -> 0 | G24: ='3_Balance_Sheet'!G60 -> 0 | H24: ='3_Balance_Sheet'!H60 -> 0 | I24: ='3_Balance_Sheet'!I60 -> 0 | J24: ='3_Balance_Sheet'!J60 -> 0 | ... N24: ='3_Balance_Sheet'!N60 -> 0
A25: 16 | B25: Months' Export Sales | C25: =IFERROR(C24*12/'2_Operating_Statement'!C8,0) -> 0 | D25: =IFERROR(D24*12/'2_Operating_Statement'!D8,0) -> 0 | E25: =IFERROR(E24*12/'2_Operating_Statement'!E8,0) -> 0 | F25: =IFERROR(F24*12/'2_Operating_Statement'!F8,0) -> 0 | G25: =IFERROR(G24*12/'2_Operating_Statement'!G8,0) -> 0 | H25: =IFERROR(H24*12/'2_Operating_Statement'!H8,0) -> 0 | I25: =IFERROR(I24*12/'2_Operating_Statement'!I8,0) -> 0 | J25: =IFERROR(J24*12/'2_Operating_Statement'!J8,0) -> 0 | ... N25: =IFERROR(N24*12/'2_Operating_Statement'!N8,0) -> 0
A26: OTHER CURRENT ASSETS
A27: 17 | B27: Cash & Bank Balances | C27: ='3_Balance_Sheet'!C55 -> 0 | D27: ='3_Balance_Sheet'!D55 -> 0 | E27: ='3_Balance_Sheet'!E55 -> 0 | F27: ='3_Balance_Sheet'!F55 -> 0 | G27: ='3_Balance_Sheet'!G55 -> 0 | H27: ='3_Balance_Sheet'!H55 -> 0 | I27: ='3_Balance_Sheet'!I55 -> 0 | J27: ='3_Balance_Sheet'!J55 -> 0 | ... N27: ='3_Balance_Sheet'!N55 -> 0
A28: 18 | B28: Govt & Other Trustee Securities | C28: ='3_Balance_Sheet'!C56 -> 0 | D28: ='3_Balance_Sheet'!D56 -> 0 | E28: ='3_Balance_Sheet'!E56 -> 0 | F28: ='3_Balance_Sheet'!F56 -> 0 | G28: ='3_Balance_Sheet'!G56 -> 0 | H28: ='3_Balance_Sheet'!H56 -> 0 | I28: ='3_Balance_Sheet'!I56 -> 0 | J28: ='3_Balance_Sheet'!J56 -> 0 | ... N28: ='3_Balance_Sheet'!N56 -> 0
A29: 19 | B29: Fixed Deposits with Banks | C29: ='3_Balance_Sheet'!C57 -> 0 | D29: ='3_Balance_Sheet'!D57 -> 0 | E29: ='3_Balance_Sheet'!E57 -> 0 | F29: ='3_Balance_Sheet'!F57 -> 0 | G29: ='3_Balance_Sheet'!G57 -> 0 | H29: ='3_Balance_Sheet'!H57 -> 0 | I29: ='3_Balance_Sheet'!I57 -> 0 | J29: ='3_Balance_Sheet'!J57 -> 0 | ... N29: ='3_Balance_Sheet'!N57 -> 0
A30: 20 | B30: Total Current Assets (linked from BS) | C30: ='3_Balance_Sheet'!C82 -> 0 | D30: ='3_Balance_Sheet'!D82 -> 0 | E30: ='3_Balance_Sheet'!E82 -> 0 | F30: ='3_Balance_Sheet'!F82 -> 0 | G30: ='3_Balance_Sheet'!G82 -> 0 | H30: ='3_Balance_Sheet'!H82 -> 0 | I30: ='3_Balance_Sheet'!I82 -> 0 | J30: ='3_Balance_Sheet'!J82 -> 0 | ... N30: ='3_Balance_Sheet'!N82 -> 0
A31: CURRENT LIABILITIES
A32: 21 | B32: Sundry Creditors (Trade — linked) | C32: ='3_Balance_Sheet'!C14+'3_Balance_Sheet'!C15 -> 0 | D32: ='3_Balance_Sheet'!D14+'3_Balance_Sheet'!D15 -> 0 | E32: ='3_Balance_Sheet'!E14+'3_Balance_Sheet'!E15 -> 0 | F32: ='3_Balance_Sheet'!F14+'3_Balance_Sheet'!F15 -> 0 | G32: ='3_Balance_Sheet'!G14+'3_Balance_Sheet'!G15 -> 0 | H32: ='3_Balance_Sheet'!H14+'3_Balance_Sheet'!H15 -> 0 | I32: ='3_Balance_Sheet'!I14+'3_Balance_Sheet'!I15 -> 0 | J32: ='3_Balance_Sheet'!J14+'3_Balance_Sheet'!J15 -> 0 | ... N32: ='3_Balance_Sheet'!N14+'3_Balance_Sheet'!N15 -> 0
A33: 22 | B33: Months' Purchases (Sundry Creditors) | C33: =IFERROR(C32*12/('2_Operating_Statement'!C17+'2_Operating_Statement'!C20),0) -> 0 | D33: =IFERROR(D32*12/('2_Operating_Statement'!D17+'2_Operating_Statement'!D20),0) -> 0 | E33: =IFERROR(E32*12/('2_Operating_Statement'!E17+'2_Operating_Statement'!E20),0) -> 0 | F33: =IFERROR(F32*12/('2_Operating_Statement'!F17+'2_Operating_Statement'!F20),0) -> 0 | G33: =IFERROR(G32*12/('2_Operating_Statement'!G17+'2_Operating_Statement'!G20),0) -> 0 | H33: =IFERROR(H32*12/('2_Operating_Statement'!H17+'2_Operating_Statement'!H20),0) -> 0 | I33: =IFERROR(I32*12/('2_Operating_Statement'!I17+'2_Operating_Statement'!I20),0) -> 0 | J33: =IFERROR(J32*12/('2_Operating_Statement'!J17+'2_Operating_Statement'!J20),0) -> 0 | ... N33: =IFERROR(N32*12/('2_Operating_Statement'!N17+'2_Operating_Statement'!N20),0) -> 0
A34: 23 | B34: TL Instalments (within 1 yr — linked) | C34: ='3_Balance_Sheet'!C20 -> 0 | D34: ='3_Balance_Sheet'!D20 -> 0 | E34: ='3_Balance_Sheet'!E20 -> 0 | F34: ='3_Balance_Sheet'!F20 -> 0 | G34: ='3_Balance_Sheet'!G20 -> 0 | H34: ='3_Balance_Sheet'!H20 -> 0 | I34: ='3_Balance_Sheet'!I20 -> 0 | J34: ='3_Balance_Sheet'!J20 -> 0 | ... N34: ='3_Balance_Sheet'!N20 -> 0

Sheet 6_Working_Capital
A1: =CONCATENATE("WORKING CAPITAL ASSESSMENT — MPBF II | ₹ Crores | ", BorrowerName) -> WORKING CAPITAL ASSESSMENT — MPBF II | ₹ Crores |
A2: Tandon II method. NWC must be ≥25% of TCA. ABF = WCG − NWC.
A3: Sr | B3: Particulars | C3: Yr 1 | D3: Yr 2 | E3: Yr 3 | F3: Yr 4 | G3: Yr 5 | H3: Yr 6 | I3: Yr 7 | J3: Yr 8 | K3: Yr 9 | L3: Yr 10 | M3: Yr 11 | N3: Yr 12 | O3: Δ Latest vs Prior Aud | P3: Auto-Comment
B4: Year → | C4: =INDEX('0_Setup'!$B$48:$B$59,1) -> 2022-23 | D4: =INDEX('0_Setup'!$B$48:$B$59,2) -> 2023-24 | E4: =INDEX('0_Setup'!$B$48:$B$59,3) -> 2024-25 | F4: =INDEX('0_Setup'!$B$48:$B$59,4) -> 2024-25 | G4: =INDEX('0_Setup'!$B$48:$B$59,5) -> 2025-26 | H4: =INDEX('0_Setup'!$B$48:$B$59,6) -> 2026-27 | I4: =INDEX('0_Setup'!$B$48:$B$59,7) -> 2027-28 | J4: =INDEX('0_Setup'!$B$48:$B$59,8) -> 2028-29 | K4: =INDEX('0_Setup'!$B$48:$B$59,9) -> 2029-30 | L4: =INDEX('0_Setup'!$B$48:$B$59,10) | M4: =INDEX('0_Setup'!$B$48:$B$59,11) | N4: =INDEX('0_Setup'!$B$48:$B$59,12)
B5: Type → | C5: =INDEX('0_Setup'!$C$48:$C$59,1) -> Audited | D5: =INDEX('0_Setup'!$C$48:$C$59,2) -> Audited | E5: =INDEX('0_Setup'!$C$48:$C$59,3) -> Estimated | F5: =INDEX('0_Setup'!$C$48:$C$59,4) -> Audited/Provisional | G5: =INDEX('0_Setup'!$C$48:$C$59,5) -> Estimated | H5: =INDEX('0_Setup'!$C$48:$C$59,6) -> Projected | I5: =INDEX('0_Setup'!$C$48:$C$59,7) -> Projected | J5: =INDEX('0_Setup'!$C$48:$C$59,8) -> Projected | K5: =INDEX('0_Setup'!$C$48:$C$59,9) -> Projected | L5: =INDEX('0_Setup'!$C$48:$C$59,10) | M5: =INDEX('0_Setup'!$C$48:$C$59,11) | N5: =INDEX('0_Setup'!$C$48:$C$59,12)
A6: MPBF CALCULATION
A7: 1 | B7: Total Current Assets (TCA) | C7: ='3_Balance_Sheet'!C82 -> 0 | D7: ='3_Balance_Sheet'!D82 -> 0 | E7: ='3_Balance_Sheet'!E82 -> 0 | F7: ='3_Balance_Sheet'!F82 -> 0 | G7: ='3_Balance_Sheet'!G82 -> 0 | H7: ='3_Balance_Sheet'!H82 -> 0 | I7: ='3_Balance_Sheet'!I82 -> 0 | J7: ='3_Balance_Sheet'!J82 -> 0 | ... N7: ='3_Balance_Sheet'!N82 -> 0
A8: 2 | B8: Total CL (other than Bank Borrowings) | C8: ='3_Balance_Sheet'!C26 -> 0 | D8: ='3_Balance_Sheet'!D26 -> 0 | E8: ='3_Balance_Sheet'!E26 -> 0 | F8: ='3_Balance_Sheet'!F26 -> 0 | G8: ='3_Balance_Sheet'!G26 -> 0 | H8: ='3_Balance_Sheet'!H26 -> 0 | I8: ='3_Balance_Sheet'!I26 -> 0 | J8: ='3_Balance_Sheet'!J26 -> 0 | ... N8: ='3_Balance_Sheet'!N26 -> 0
A9: 3 | B9: Other CL (excluding Sundry Creditors) | C9: ='3_Balance_Sheet'!C26-'3_Balance_Sheet'!C14-'3_Balance_Sheet'!C15 -> 0 | D9: ='3_Balance_Sheet'!D26-'3_Balance_Sheet'!D14-'3_Balance_Sheet'!D15 -> 0 | E9: ='3_Balance_Sheet'!E26-'3_Balance_Sheet'!E14-'3_Balance_Sheet'!E15 -> 0 | F9: ='3_Balance_Sheet'!F26-'3_Balance_Sheet'!F14-'3_Balance_Sheet'!F15 -> 0 | G9: ='3_Balance_Sheet'!G26-'3_Balance_Sheet'!G14-'3_Balance_Sheet'!G15 -> 0 | H9: ='3_Balance_Sheet'!H26-'3_Balance_Sheet'!H14-'3_Balance_Sheet'!H15 -> 0 | I9: ='3_Balance_Sheet'!I26-'3_Balance_Sheet'!I14-'3_Balance_Sheet'!I15 -> 0 | J9: ='3_Balance_Sheet'!J26-'3_Balance_Sheet'!J14-'3_Balance_Sheet'!J15 -> 0 | ... N9: ='3_Balance_Sheet'!N26-'3_Balance_Sheet'!N14-'3_Balance_Sheet'!N15 -> 0
A10: 4 | B10: Working Capital Gap (TCA − Other CL) | C10: =C7-C8 -> 0 | D10: =D7-D8 -> 0 | E10: =E7-E8 -> 0 | F10: =F7-F8 -> 0 | G10: =G7-G8 -> 0 | H10: =H7-H8 -> 0 | I10: =I7-I8 -> 0 | J10: =J7-J8 -> 0 | ... N10: =N7-N8 -> 0
A11: 5 | B11: Net Working Capital (NWC)
A12: 6 | B12: Assessed Bank Finance (ABF) = WCG − NWC | C12: =C10-C11 -> 0 | D12: =D10-D11 -> 0 | E12: =E10-E11 -> 0 | F12: =F10-F11 -> 0 | G12: =G10-G11 -> 0 | H12: =H10-H11 -> 0 | I12: =I10-I11 -> 0 | J12: =J10-J11 -> 0 | ... N12: =N10-N11 -> 0
A13: WC RATIOS
A14: 7 | B14: NWC / TCA (%) | C14: =IFERROR(C11/C7,0) -> 0 | D14: =IFERROR(D11/D7,0) -> 0 | E14: =IFERROR(E11/E7,0) -> 0 | F14: =IFERROR(F11/F7,0) -> 0 | G14: =IFERROR(G11/G7,0) -> 0 | H14: =IFERROR(H11/H7,0) -> 0 | I14: =IFERROR(I11/I7,0) -> 0 | J14: =IFERROR(J11/J7,0) -> 0 | ... N14: =IFERROR(N11/N7,0) -> 0
A15: 8 | B15: ABF / TCA (%) | C15: =IFERROR(C12/C7,0) -> 0 | D15: =IFERROR(D12/D7,0) -> 0 | E15: =IFERROR(E12/E7,0) -> 0 | F15: =IFERROR(F12/F7,0) -> 0 | G15: =IFERROR(G12/G7,0) -> 0 | H15: =IFERROR(H12/H7,0) -> 0 | I15: =IFERROR(I12/I7,0) -> 0 | J15: =IFERROR(J12/J7,0) -> 0 | ... N15: =IFERROR(N12/N7,0) -> 0
A16: 9 | B16: Sundry Creditors (linked) | C16: ='3_Balance_Sheet'!C14+'3_Balance_Sheet'!C15 -> 0 | D16: ='3_Balance_Sheet'!D14+'3_Balance_Sheet'!D15 -> 0 | E16: ='3_Balance_Sheet'!E14+'3_Balance_Sheet'!E15 -> 0 | F16: ='3_Balance_Sheet'!F14+'3_Balance_Sheet'!F15 -> 0 | G16: ='3_Balance_Sheet'!G14+'3_Balance_Sheet'!G15 -> 0 | H16: ='3_Balance_Sheet'!H14+'3_Balance_Sheet'!H15 -> 0 | I16: ='3_Balance_Sheet'!I14+'3_Balance_Sheet'!I15 -> 0 | J16: ='3_Balance_Sheet'!J14+'3_Balance_Sheet'!J15 -> 0 | ... N16: ='3_Balance_Sheet'!N14+'3_Balance_Sheet'!N15 -> 0
A17: 10 | B17: Sundry Creditors to TCA (%) | C17: =IFERROR(C16/C7,0) -> 0 | D17: =IFERROR(D16/D7,0) -> 0 | E17: =IFERROR(E16/E7,0) -> 0 | F17: =IFERROR(F16/F7,0) -> 0 | G17: =IFERROR(G16/G7,0) -> 0 | H17: =IFERROR(H16/H7,0) -> 0 | I17: =IFERROR(I16/I7,0) -> 0 | J17: =IFERROR(J16/J7,0) -> 0 | ... N17: =IFERROR(N16/N7,0) -> 0
A18: 11 | B18: Other CL to TCA (%) | C18: =IFERROR(C8/C7,0) -> 0 | D18: =IFERROR(D8/D7,0) -> 0 | E18: =IFERROR(E8/E7,0) -> 0 | F18: =IFERROR(F8/F7,0) -> 0 | G18: =IFERROR(G8/G7,0) -> 0 | H18: =IFERROR(H8/H7,0) -> 0 | I18: =IFERROR(I8/I7,0) -> 0 | J18: =IFERROR(J8/J7,0) -> 0 | ... N18: =IFERROR(N8/N7,0) -> 0
A19: HOLDING LEVELS (Days)
A20: 12 | B20: Inventory to Net Sales (days) | C20: =IFERROR('3_Balance_Sheet'!C73*365/'2_Operating_Statement'!C13,0) -> 0 | D20: =IFERROR('3_Balance_Sheet'!D73*365/'2_Operating_Statement'!D13,0) -> 0 | E20: =IFERROR('3_Balance_Sheet'!E73*365/'2_Operating_Statement'!E13,0) -> 0 | F20: =IFERROR('3_Balance_Sheet'!F73*365/'2_Operating_Statement'!F13,0) -> 0 | G20: =IFERROR('3_Balance_Sheet'!G73*365/'2_Operating_Statement'!G13,0) -> 0 | H20: =IFERROR('3_Balance_Sheet'!H73*365/'2_Operating_Statement'!H13,0) -> 0 | I20: =IFERROR('3_Balance_Sheet'!I73*365/'2_Operating_Statement'!I13,0) -> 0 | J20: =IFERROR('3_Balance_Sheet'!J73*365/'2_Operating_Statement'!J13,0) -> 0 | ... N20: =IFERROR('3_Balance_Sheet'!N73*365/'2_Operating_Statement'!N13,0) -> 0
A21: 13 | B21: Receivables to Gross Sales (days) | C21: =IFERROR(('3_Balance_Sheet'!C59+'3_Balance_Sheet'!C60)*365/'2_Operating_Statement'!C10,0) -> 0 | D21: =IFERROR(('3_Balance_Sheet'!D59+'3_Balance_Sheet'!D60)*365/'2_Operating_Statement'!D10,0) -> 0 | E21: =IFERROR(('3_Balance_Sheet'!E59+'3_Balance_Sheet'!E60)*365/'2_Operating_Statement'!E10,0) -> 0 | F21: =IFERROR(('3_Balance_Sheet'!F59+'3_Balance_Sheet'!F60)*365/'2_Operating_Statement'!F10,0) -> 0 | G21: =IFERROR(('3_Balance_Sheet'!G59+'3_Balance_Sheet'!G60)*365/'2_Operating_Statement'!G10,0) -> 0 | H21: =IFERROR(('3_Balance_Sheet'!H59+'3_Balance_Sheet'!H60)*365/'2_Operating_Statement'!H10,0) -> 0 | I21: =IFERROR(('3_Balance_Sheet'!I59+'3_Balance_Sheet'!I60)*365/'2_Operating_Statement'!I10,0) -> 0 | J21: =IFERROR(('3_Balance_Sheet'!J59+'3_Balance_Sheet'!J60)*365/'2_Operating_Statement'!J10,0) -> 0 | ... N21: =IFERROR(('3_Balance_Sheet'!N59+'3_Balance_Sheet'!N60)*365/'2_Operating_Statement'!N10,0) -> 0
A22: 14 | B22: Sundry Creditors to Purchases (days) | C22: =IFERROR(C16*365/('2_Operating_Statement'!C17+'2_Operating_Statement'!C20),0) -> 0 | D22: =IFERROR(D16*365/('2_Operating_Statement'!D17+'2_Operating_Statement'!D20),0) -> 0 | E22: =IFERROR(E16*365/('2_Operating_Statement'!E17+'2_Operating_Statement'!E20),0) -> 0 | F22: =IFERROR(F16*365/('2_Operating_Statement'!F17+'2_Operating_Statement'!F20),0) -> 0 | G22: =IFERROR(G16*365/('2_Operating_Statement'!G17+'2_Operating_Statement'!G20),0) -> 0 | H22: =IFERROR(H16*365/('2_Operating_Statement'!H17+'2_Operating_Statement'!H20),0) -> 0 | I22: =IFERROR(I16*365/('2_Operating_Statement'!I17+'2_Operating_Statement'!I20),0) -> 0 | J22: =IFERROR(J16*365/('2_Operating_Statement'!J17+'2_Operating_Statement'!J20),0) -> 0 | ... N22: =IFERROR(N16*365/('2_Operating_Statement'!N17+'2_Operating_Statement'!N20),0) -> 0
A23: WC ANALYSIS — RED FLAGS
B24: NWC Y-o-Y Movement (Latest Aud vs Prior Aud) | O24: =IFERROR((INDEX(C11:N11,1,LatestAudCol)-INDEX(C11:N11,1,PriorAudCol))/ABS(INDEX(C11:N11,1,PriorAudCol)),"") | P24: =IF(O24="","",IF(O24<MaxNWCErosion,"⚠ NWC eroded by "&TEXT(ABS(O24),"0.0%")&" — exceeds tolerance of "&TEXT(ABS(MaxNWCErosion),"0.0%"),"✓ NWC stable / improved"))

Sheet 7_Funds_Flow
A1: =CONCATENATE("FUNDS FLOW STATEMENT | ₹ Crores | ", BorrowerName) -> FUNDS FLOW STATEMENT | ₹ Crores |
A2: Sources & Uses. Net Surplus/Deficit = change in Bank Borrowings.
A3: Sr | B3: Particulars | C3: Yr 1 | D3: Yr 2 | E3: Yr 3 | F3: Yr 4 | G3: Yr 5 | H3: Yr 6 | I3: Yr 7 | J3: Yr 8 | K3: Yr 9 | L3: Yr 10 | M3: Yr 11 | N3: Yr 12 | O3: Δ Latest vs Prior Aud | P3: Auto-Comment
B4: Year → | C4: =INDEX('0_Setup'!$B$48:$B$59,1) -> 2022-23 | D4: =INDEX('0_Setup'!$B$48:$B$59,2) -> 2023-24 | E4: =INDEX('0_Setup'!$B$48:$B$59,3) -> 2024-25 | F4: =INDEX('0_Setup'!$B$48:$B$59,4) -> 2024-25 | G4: =INDEX('0_Setup'!$B$48:$B$59,5) -> 2025-26 | H4: =INDEX('0_Setup'!$B$48:$B$59,6) -> 2026-27 | I4: =INDEX('0_Setup'!$B$48:$B$59,7) -> 2027-28 | J4: =INDEX('0_Setup'!$B$48:$B$59,8) -> 2028-29 | K4: =INDEX('0_Setup'!$B$48:$B$59,9) -> 2029-30 | L4: =INDEX('0_Setup'!$B$48:$B$59,10) | M4: =INDEX('0_Setup'!$B$48:$B$59,11) | N4: =INDEX('0_Setup'!$B$48:$B$59,12)
B5: Type → | C5: =INDEX('0_Setup'!$C$48:$C$59,1) -> Audited | D5: =INDEX('0_Setup'!$C$48:$C$59,2) -> Audited | E5: =INDEX('0_Setup'!$C$48:$C$59,3) -> Estimated | F5: =INDEX('0_Setup'!$C$48:$C$59,4) -> Audited/Provisional | G5: =INDEX('0_Setup'!$C$48:$C$59,5) -> Estimated | H5: =INDEX('0_Setup'!$C$48:$C$59,6) -> Projected | I5: =INDEX('0_Setup'!$C$48:$C$59,7) -> Projected | J5: =INDEX('0_Setup'!$C$48:$C$59,8) -> Projected | K5: =INDEX('0_Setup'!$C$48:$C$59,9) -> Projected | L5: =INDEX('0_Setup'!$C$48:$C$59,10) | M5: =INDEX('0_Setup'!$C$48:$C$59,11) | N5: =INDEX('0_Setup'!$C$48:$C$59,12)
A6: SOURCES
A7: 1 | B7: Cash Accruals (PAT + Dep) | C7: ='4_DSCR'!C7 -> 0 | D7: ='4_DSCR'!D7 -> 0 | E7: ='4_DSCR'!E7 -> 0 | F7: ='4_DSCR'!F7 -> 0 | G7: ='4_DSCR'!G7 -> 0 | H7: ='4_DSCR'!H7 -> 0 | I7: ='4_DSCR'!I7 -> 0 | J7: ='4_DSCR'!J7 -> 0 | ... N7: ='4_DSCR'!N7 -> 0
A8: 2 | B8: Increase in Capital
A9: 3 | B9: Increase in Term Liabilities
A10: 4 | B10: Decrease in Fixed Assets
A11: 5 | B11: Decrease in Other Non-Current Assets
A12: 6 | B12: Other Sources
A13: 7 | B13: Total Sources | C13: =C7+SUM(C8:C12) -> 0 | D13: =D7+SUM(D8:D12) -> 0 | E13: =E7+SUM(E8:E12) -> 0 | F13: =F7+SUM(F8:F12) -> 0 | G13: =G7+SUM(G8:G12) -> 0 | H13: =H7+SUM(H8:H12) -> 0 | I13: =I7+SUM(I8:I12) -> 0 | J13: =J7+SUM(J8:J12) -> 0 | ... N13: =N7+SUM(N8:N12) -> 0
A14: USES
A15: 8 | B15: Cash Accruals (if negative) | C15: =IF(C7<0,-C7,0) -> 0 | D15: =IF(D7<0,-D7,0) -> 0 | E15: =IF(E7<0,-E7,0) -> 0 | F15: =IF(F7<0,-F7,0) -> 0 | G15: =IF(G7<0,-G7,0) -> 0 | H15: =IF(H7<0,-H7,0) -> 0 | I15: =IF(I7<0,-I7,0) -> 0 | J15: =IF(J7<0,-J7,0) -> 0 | ... N15: =IF(N7<0,-N7,0) -> 0
A16: 9 | B16: Decrease in Term Liabilities
A17: 10 | B17: Increase in Fixed Assets
A18: 11 | B18: Increase in Other Non-Current Assets
A19: 12 | B19: Dividend Payments
A20: 13 | B20: Other Uses
A21: 14 | B21: Total Uses | C21: =SUM(C15:C20) -> 0 | D21: =SUM(D15:D20) -> 0 | E21: =SUM(E15:E20) -> 0 | F21: =SUM(F15:F20) -> 0 | G21: =SUM(G15:G20) -> 0 | H21: =SUM(H15:H20) -> 0 | I21: =SUM(I15:I20) -> 0 | J21: =SUM(J15:J20) -> 0 | ... N21: =SUM(N15:N20) -> 0
A22: 15 | B22: Long Term Surplus / (Deficit) | C22: =C13-C21 -> 0 | D22: =D13-D21 -> 0 | E22: =E13-E21 -> 0 | F22: =F13-F21 -> 0 | G22: =G13-G21 -> 0 | H22: =H13-H21 -> 0 | I22: =I13-I21 -> 0 | J22: =J13-J21 -> 0 | ... N22: =N13-N21 -> 0
A23: WORKING CAPITAL CYCLE
A24: 16 | B24: Increase / (Decrease) in Current Assets
A25: 17 | B25: Increase / (Decrease) in Current Liabilities
A26: 18 | B26: Increase / (Decrease) in WCG | C26: =C24-C25 -> 0 | D26: =D24-D25 -> 0 | E26: =E24-E25 -> 0 | F26: =F24-F25 -> 0 | G26: =G24-G25 -> 0 | H26: =H24-H25 -> 0 | I26: =I24-I25 -> 0 | J26: =J24-J25 -> 0 | ... N26: =N24-N25 -> 0
A27: 19 | B27: Net Surplus / (Deficit) | C27: =C22-C26 -> 0 | D27: =D22-D26 -> 0 | E27: =E22-E26 -> 0 | F27: =F22-F26 -> 0 | G27: =G22-G26 -> 0 | H27: =H22-H26 -> 0 | I27: =I22-I26 -> 0 | J27: =J22-J26 -> 0 | ... N27: =N22-N26 -> 0
A28: 20 | B28: Increase / (Decrease) in Bank Borrowings | P28: =IF(ABS(INDEX(C27:N27,1,LatestAudCol)+INDEX(C28:N28,1,LatestAudCol))<0.5,"✓ Net Surplus tallies with Bank Borrowing change","⚠ Mismatch — investigate") -> ✓ Net Surplus tallies with Bank Borrowing change
A29: RED FLAG — CAPEX / LTF MATCHING
B30: FA addition / LT-Funds Available (>1 = funded by WC, dangerous) | C30: =IFERROR((INDEX('3_Balance_Sheet'!C84:N84,1,LatestAudCol)-INDEX('3_Balance_Sheet'!C84:N84,1,PriorAudCol))/IF(((INDEX('3_Balance_Sheet'!C52:N52,1,LatestAudCol)-INDEX('3_Balance_Sheet'!C52:N52,1,PriorAudCol))+(INDEX('3_Balance_Sheet'!C39:N39,1,LatestAudCol)-INDEX('3_Balance_Sheet'!C39:N39,1,PriorAudCol)))=0,1,((INDEX('3_Balance_Sheet'!C52:N52,1,LatestAudCol)-INDEX('3_Balance_Sheet'!C52:N52,1,PriorAudCol))+(INDEX('3_Balance_Sheet'!C39:N39,1,LatestAudCol)-INDEX('3_Balance_Sheet'!C39:N39,1,PriorAudCol)))),0) -> 0 | P30: =IF((INDEX('3_Balance_Sheet'!C84:N84,1,LatestAudCol)-INDEX('3_Balance_Sheet'!C84:N84,1,PriorAudCol))<0.05,"✓ No material capex in latest year",IF(C30>1.5,"⚠ DIVERSION RISK — capex exceeds long-term funds. Quantify gap, ensure no cross-subsidy from WC.",IF(C30>1,"⚠ Capex partly funded from working capital — review LTF source documentation.","✓ Capex matched with long-term sources"))) -> ✓ No material capex in latest year

Sheet 8_Performance_Indicators
A1: =CONCATENATE("PERFORMANCE INDICATORS | ", BorrowerName) -> PERFORMANCE INDICATORS |
A2: All ratios auto-computed from input sheets. Conditional formatting flags breaches in real time.
A3: Sr | B3: Particulars | C3: Yr 1 | D3: Yr 2 | E3: Yr 3 | F3: Yr 4 | G3: Yr 5 | H3: Yr 6 | I3: Yr 7 | J3: Yr 8 | K3: Yr 9 | L3: Yr 10 | M3: Yr 11 | N3: Yr 12 | O3: Threshold | P3: Auto-Comment
B4: Year → | C4: =INDEX('0_Setup'!$B$48:$B$59,1) -> 2022-23 | D4: =INDEX('0_Setup'!$B$48:$B$59,2) -> 2023-24 | E4: =INDEX('0_Setup'!$B$48:$B$59,3) -> 2024-25 | F4: =INDEX('0_Setup'!$B$48:$B$59,4) -> 2024-25 | G4: =INDEX('0_Setup'!$B$48:$B$59,5) -> 2025-26 | H4: =INDEX('0_Setup'!$B$48:$B$59,6) -> 2026-27 | I4: =INDEX('0_Setup'!$B$48:$B$59,7) -> 2027-28 | J4: =INDEX('0_Setup'!$B$48:$B$59,8) -> 2028-29 | K4: =INDEX('0_Setup'!$B$48:$B$59,9) -> 2029-30 | L4: =INDEX('0_Setup'!$B$48:$B$59,10) | M4: =INDEX('0_Setup'!$B$48:$B$59,11) | N4: =INDEX('0_Setup'!$B$48:$B$59,12)
B5: Type → | C5: =INDEX('0_Setup'!$C$48:$C$59,1) -> Audited | D5: =INDEX('0_Setup'!$C$48:$C$59,2) -> Audited | E5: =INDEX('0_Setup'!$C$48:$C$59,3) -> Estimated | F5: =INDEX('0_Setup'!$C$48:$C$59,4) -> Audited/Provisional | G5: =INDEX('0_Setup'!$C$48:$C$59,5) -> Estimated | H5: =INDEX('0_Setup'!$C$48:$C$59,6) -> Projected | I5: =INDEX('0_Setup'!$C$48:$C$59,7) -> Projected | J5: =INDEX('0_Setup'!$C$48:$C$59,8) -> Projected | K5: =INDEX('0_Setup'!$C$48:$C$59,9) -> Projected | L5: =INDEX('0_Setup'!$C$48:$C$59,10) | M5: =INDEX('0_Setup'!$C$48:$C$59,11) | N5: =INDEX('0_Setup'!$C$48:$C$59,12)
A6: PROFITABILITY
A7: 1 | B7: Net Sales (₹ Cr) | C7: ='2_Operating_Statement'!C13 -> 0 | D7: ='2_Operating_Statement'!D13 -> 0 | E7: ='2_Operating_Statement'!E13 -> 0 | F7: ='2_Operating_Statement'!F13 -> 0 | G7: ='2_Operating_Statement'!G13 -> 0 | H7: ='2_Operating_Statement'!H13 -> 0 | I7: ='2_Operating_Statement'!I13 -> 0 | J7: ='2_Operating_Statement'!J13 -> 0 | ... N7: ='2_Operating_Statement'!N13 -> 0 | P7: =IF(AND(INDEX('2_Operating_Statement'!C13:N13,1,PriorAudCol)>0,INDEX('2_Operating_Statement'!C13:N13,1,LatestAudCol)>0),"YoY: "&TEXT((INDEX('2_Operating_Statement'!C13:N13,1,LatestAudCol)-INDEX('2_Operating_Statement'!C13:N13,1,PriorAudCol))/INDEX('2_Operating_Statement'!C13:N13,1,PriorAudCol),"0.0%"),"")
A8: 2 | B8: Sales Growth Y-o-Y (Latest Aud vs Prior Aud) | C8: =IF(OR(1<>LatestAudCol,INDEX('2_Operating_Statement'!C13:N13,1,PriorAudCol)=0),"",IFERROR((INDEX('2_Operating_Statement'!C13:N13,1,LatestAudCol)-INDEX('2_Operating_Statement'!C13:N13,1,PriorAudCol))/INDEX('2_Operating_Statement'!C13:N13,1,PriorAudCol),"")) | D8: =IF(OR(2<>LatestAudCol,INDEX('2_Operating_Statement'!C13:N13,1,PriorAudCol)=0),"",IFERROR((INDEX('2_Operating_Statement'!C13:N13,1,LatestAudCol)-INDEX('2_Operating_Statement'!C13:N13,1,PriorAudCol))/INDEX('2_Operating_Statement'!C13:N13,1,PriorAudCol),"")) | E8: =IF(OR(3<>LatestAudCol,INDEX('2_Operating_Statement'!C13:N13,1,PriorAudCol)=0),"",IFERROR((INDEX('2_Operating_Statement'!C13:N13,1,LatestAudCol)-INDEX('2_Operating_Statement'!C13:N13,1,PriorAudCol))/INDEX('2_Operating_Statement'!C13:N13,1,PriorAudCol),"")) | F8: =IF(OR(4<>LatestAudCol,INDEX('2_Operating_Statement'!C13:N13,1,PriorAudCol)=0),"",IFERROR((INDEX('2_Operating_Statement'!C13:N13,1,LatestAudCol)-INDEX('2_Operating_Statement'!C13:N13,1,PriorAudCol))/INDEX('2_Operating_Statement'!C13:N13,1,PriorAudCol),"")) | G8: =IF(OR(5<>LatestAudCol,INDEX('2_Operating_Statement'!C13:N13,1,PriorAudCol)=0),"",IFERROR((INDEX('2_Operating_Statement'!C13:N13,1,LatestAudCol)-INDEX('2_Operating_Statement'!C13:N13,1,PriorAudCol))/INDEX('2_Operating_Statement'!C13:N13,1,PriorAudCol),"")) | H8: =IF(OR(6<>LatestAudCol,INDEX('2_Operating_Statement'!C13:N13,1,PriorAudCol)=0),"",IFERROR((INDEX('2_Operating_Statement'!C13:N13,1,LatestAudCol)-INDEX('2_Operating_Statement'!C13:N13,1,PriorAudCol))/INDEX('2_Operating_Statement'!C13:N13,1,PriorAudCol),"")) | I8: =IF(OR(7<>LatestAudCol,INDEX('2_Operating_Statement'!C13:N13,1,PriorAudCol)=0),"",IFERROR((INDEX('2_Operating_Statement'!C13:N13,1,LatestAudCol)-INDEX('2_Operating_Statement'!C13:N13,1,PriorAudCol))/INDEX('2_Operating_Statement'!C13:N13,1,PriorAudCol),"")) | J8: =IF(OR(8<>LatestAudCol,INDEX('2_Operating_Statement'!C13:N13,1,PriorAudCol)=0),"",IFERROR((INDEX('2_Operating_Statement'!C13:N13,1,LatestAudCol)-INDEX('2_Operating_Statement'!C13:N13,1,PriorAudCol))/INDEX('2_Operating_Statement'!C13:N13,1,PriorAudCol),"")) | K8: =IF(OR(9<>LatestAudCol,INDEX('2_Operating_Statement'!C13:N13,1,PriorAudCol)=0),"",IFERROR((INDEX('2_Operating_Statement'!C13:N13,1,LatestAudCol)-INDEX('2_Operating_Statement'!C13:N13,1,PriorAudCol))/INDEX('2_Operating_Statement'!C13:N13,1,PriorAudCol),"")) | L8: =IF(OR(10<>LatestAudCol,INDEX('2_Operating_Statement'!C13:N13,1,PriorAudCol)=0),"",IFERROR((INDEX('2_Operating_Statement'!C13:N13,1,LatestAudCol)-INDEX('2_Operating_Statement'!C13:N13,1,PriorAudCol))/INDEX('2_Operating_Statement'!C13:N13,1,PriorAudCol),"")) | M8: =IF(OR(11<>LatestAudCol,INDEX('2_Operating_Statement'!C13:N13,1,PriorAudCol)=0),"",IFERROR((INDEX('2_Operating_Statement'!C13:N13,1,LatestAudCol)-INDEX('2_Operating_Statement'!C13:N13,1,PriorAudCol))/INDEX('2_Operating_Statement'!C13:N13,1,PriorAudCol),"")) | N8: =IF(OR(12<>LatestAudCol,INDEX('2_Operating_Statement'!C13:N13,1,PriorAudCol)=0),"",IFERROR((INDEX('2_Operating_Statement'!C13:N13,1,LatestAudCol)-INDEX('2_Operating_Statement'!C13:N13,1,PriorAudCol))/INDEX('2_Operating_Statement'!C13:N13,1,PriorAudCol),"")) | O8: >= -5% | P8: =IF(INDEX('2_Operating_Statement'!C13:N13,1,LatestAudCol)=0,"",IF((INDEX('2_Operating_Statement'!C13:N13,1,LatestAudCol)-INDEX('2_Operating_Statement'!C13:N13,1,PriorAudCol))/INDEX('2_Operating_Statement'!C13:N13,1,PriorAudCol)<MinSalesGrowth,"⚠ Sales declined materially; investigate volume/realisation breakup",IF((INDEX('2_Operating_Statement'!C13:N13,1,LatestAudCol)-INDEX('2_Operating_Statement'!C13:N13,1,PriorAudCol))/INDEX('2_Operating_Statement'!C13:N13,1,PriorAudCol)>0.5,"⚠ Sales growth >50% — verify with sales register, GST returns, customer concentration","✓ Sales trajectory within reasonable range")))
A9: 3 | B9: Operating Profit Margin (OPBI / Net Sales) | C9: =IFERROR('2_Operating_Statement'!C33/'2_Operating_Statement'!C13,0) -> 0 | D9: =IFERROR('2_Operating_Statement'!D33/'2_Operating_Statement'!D13,0) -> 0 | E9: =IFERROR('2_Operating_Statement'!E33/'2_Operating_Statement'!E13,0) -> 0 | F9: =IFERROR('2_Operating_Statement'!F33/'2_Operating_Statement'!F13,0) -> 0 | G9: =IFERROR('2_Operating_Statement'!G33/'2_Operating_Statement'!G13,0) -> 0 | H9: =IFERROR('2_Operating_Statement'!H33/'2_Operating_Statement'!H13,0) -> 0 | I9: =IFERROR('2_Operating_Statement'!I33/'2_Operating_Statement'!I13,0) -> 0 | J9: =IFERROR('2_Operating_Statement'!J33/'2_Operating_Statement'!J13,0) -> 0 | ... N9: =IFERROR('2_Operating_Statement'!N33/'2_Operating_Statement'!N13,0) -> 0 | O9: >= 5%
A10: 4 | B10: PAT Margin (PAT / Net Sales) | C10: =IFERROR('2_Operating_Statement'!C58/'2_Operating_Statement'!C13,0) -> 0 | D10: =IFERROR('2_Operating_Statement'!D58/'2_Operating_Statement'!D13,0) -> 0 | E10: =IFERROR('2_Operating_Statement'!E58/'2_Operating_Statement'!E13,0) -> 0 | F10: =IFERROR('2_Operating_Statement'!F58/'2_Operating_Statement'!F13,0) -> 0 | G10: =IFERROR('2_Operating_Statement'!G58/'2_Operating_Statement'!G13,0) -> 0 | H10: =IFERROR('2_Operating_Statement'!H58/'2_Operating_Statement'!H13,0) -> 0 | I10: =IFERROR('2_Operating_Statement'!I58/'2_Operating_Statement'!I13,0) -> 0 | J10: =IFERROR('2_Operating_Statement'!J58/'2_Operating_Statement'!J13,0) -> 0 | ... N10: =IFERROR('2_Operating_Statement'!N58/'2_Operating_Statement'!N13,0) -> 0 | O10: >= 2%
A11: 5 | B11: Cash Profit (PAT + Dep) | C11: ='2_Operating_Statement'!C58+'2_Operating_Statement'!C24 -> 0 | D11: ='2_Operating_Statement'!D58+'2_Operating_Statement'!D24 -> 0 | E11: ='2_Operating_Statement'!E58+'2_Operating_Statement'!E24 -> 0 | F11: ='2_Operating_Statement'!F58+'2_Operating_Statement'!F24 -> 0 | G11: ='2_Operating_Statement'!G58+'2_Operating_Statement'!G24 -> 0 | H11: ='2_Operating_Statement'!H58+'2_Operating_Statement'!H24 -> 0 | I11: ='2_Operating_Statement'!I58+'2_Operating_Statement'!I24 -> 0 | J11: ='2_Operating_Statement'!J58+'2_Operating_Statement'!J24 -> 0 | ... N11: ='2_Operating_Statement'!N58+'2_Operating_Statement'!N24 -> 0
A12: 6 | B12: Cash Profit Margin | C12: =IFERROR(('2_Operating_Statement'!C58+'2_Operating_Statement'!C24)/'2_Operating_Statement'!C13,0) -> 0 | D12: =IFERROR(('2_Operating_Statement'!D58+'2_Operating_Statement'!D24)/'2_Operating_Statement'!D13,0) -> 0 | E12: =IFERROR(('2_Operating_Statement'!E58+'2_Operating_Statement'!E24)/'2_Operating_Statement'!E13,0) -> 0 | F12: =IFERROR(('2_Operating_Statement'!F58+'2_Operating_Statement'!F24)/'2_Operating_Statement'!F13,0) -> 0 | G12: =IFERROR(('2_Operating_Statement'!G58+'2_Operating_Statement'!G24)/'2_Operating_Statement'!G13,0) -> 0 | H12: =IFERROR(('2_Operating_Statement'!H58+'2_Operating_Statement'!H24)/'2_Operating_Statement'!H13,0) -> 0 | I12: =IFERROR(('2_Operating_Statement'!I58+'2_Operating_Statement'!I24)/'2_Operating_Statement'!I13,0) -> 0 | J12: =IFERROR(('2_Operating_Statement'!J58+'2_Operating_Statement'!J24)/'2_Operating_Statement'!J13,0) -> 0 | ... N12: =IFERROR(('2_Operating_Statement'!N58+'2_Operating_Statement'!N24)/'2_Operating_Statement'!N13,0) -> 0 | O12: >= 5%
A13: LIQUIDITY
A14: 7 | B14: Current Ratio (TCA / TCL) | C14: =IFERROR('3_Balance_Sheet'!C82/'3_Balance_Sheet'!C27,0) -> 0 | D14: =IFERROR('3_Balance_Sheet'!D82/'3_Balance_Sheet'!D27,0) -> 0 | E14: =IFERROR('3_Balance_Sheet'!E82/'3_Balance_Sheet'!E27,0) -> 0 | F14: =IFERROR('3_Balance_Sheet'!F82/'3_Balance_Sheet'!F27,0) -> 0 | G14: =IFERROR('3_Balance_Sheet'!G82/'3_Balance_Sheet'!G27,0) -> 0 | H14: =IFERROR('3_Balance_Sheet'!H82/'3_Balance_Sheet'!H27,0) -> 0 | I14: =IFERROR('3_Balance_Sheet'!I82/'3_Balance_Sheet'!I27,0) -> 0 | J14: =IFERROR('3_Balance_Sheet'!J82/'3_Balance_Sheet'!J27,0) -> 0 | ... N14: =IFERROR('3_Balance_Sheet'!N82/'3_Balance_Sheet'!N27,0) -> 0 | O14: >= MinCR | P14: =IF(INDEX('3_Balance_Sheet'!C82:N82,1,LatestAudCol)=0,"",IF(IFERROR(INDEX('3_Balance_Sheet'!C82:N82,1,LatestAudCol)/INDEX('3_Balance_Sheet'!C27:N27,1,LatestAudCol),0)<MinCR,"⚠ Current Ratio below "&TEXT(MinCR,"0.00")&" — liquidity stress","✓ Current Ratio acceptable"))
A15: 8 | B15: Quick Ratio ((TCA − Inventory) / TCL) | C15: =IFERROR(('3_Balance_Sheet'!C82-'3_Balance_Sheet'!C73)/'3_Balance_Sheet'!C27,0) -> 0 | D15: =IFERROR(('3_Balance_Sheet'!D82-'3_Balance_Sheet'!D73)/'3_Balance_Sheet'!D27,0) -> 0 | E15: =IFERROR(('3_Balance_Sheet'!E82-'3_Balance_Sheet'!E73)/'3_Balance_Sheet'!E27,0) -> 0 | F15: =IFERROR(('3_Balance_Sheet'!F82-'3_Balance_Sheet'!F73)/'3_Balance_Sheet'!F27,0) -> 0 | G15: =IFERROR(('3_Balance_Sheet'!G82-'3_Balance_Sheet'!G73)/'3_Balance_Sheet'!G27,0) -> 0 | H15: =IFERROR(('3_Balance_Sheet'!H82-'3_Balance_Sheet'!H73)/'3_Balance_Sheet'!H27,0) -> 0 | I15: =IFERROR(('3_Balance_Sheet'!I82-'3_Balance_Sheet'!I73)/'3_Balance_Sheet'!I27,0) -> 0 | J15: =IFERROR(('3_Balance_Sheet'!J82-'3_Balance_Sheet'!J73)/'3_Balance_Sheet'!J27,0) -> 0 | ... N15: =IFERROR(('3_Balance_Sheet'!N82-'3_Balance_Sheet'!N73)/'3_Balance_Sheet'!N27,0) -> 0 | O15: >= 1.0
A16: 9 | B16: Net Working Capital (₹ Cr) | C16: ='3_Balance_Sheet'!C82-'3_Balance_Sheet'!C27 -> 0 | D16: ='3_Balance_Sheet'!D82-'3_Balance_Sheet'!D27 -> 0 | E16: ='3_Balance_Sheet'!E82-'3_Balance_Sheet'!E27 -> 0 | F16: ='3_Balance_Sheet'!F82-'3_Balance_Sheet'!F27 -> 0 | G16: ='3_Balance_Sheet'!G82-'3_Balance_Sheet'!G27 -> 0 | H16: ='3_Balance_Sheet'!H82-'3_Balance_Sheet'!H27 -> 0 | I16: ='3_Balance_Sheet'!I82-'3_Balance_Sheet'!I27 -> 0 | J16: ='3_Balance_Sheet'!J82-'3_Balance_Sheet'!J27 -> 0 | ... N16: ='3_Balance_Sheet'!N82-'3_Balance_Sheet'!N27 -> 0
A17: SOLVENCY & LEVERAGE
A18: 10 | B18: Total Net Worth (TNW) | C18: ='3_Balance_Sheet'!C52 -> 0 | D18: ='3_Balance_Sheet'!D52 -> 0 | E18: ='3_Balance_Sheet'!E52 -> 0 | F18: ='3_Balance_Sheet'!F52 -> 0 | G18: ='3_Balance_Sheet'!G52 -> 0 | H18: ='3_Balance_Sheet'!H52 -> 0 | I18: ='3_Balance_Sheet'!I52 -> 0 | J18: ='3_Balance_Sheet'!J52 -> 0 | ... N18: ='3_Balance_Sheet'!N52 -> 0
A19: 11 | B19: TOL / TNW | C19: =IFERROR('3_Balance_Sheet'!C40/'3_Balance_Sheet'!C52,0) -> 0 | D19: =IFERROR('3_Balance_Sheet'!D40/'3_Balance_Sheet'!D52,0) -> 0 | E19: =IFERROR('3_Balance_Sheet'!E40/'3_Balance_Sheet'!E52,0) -> 0 | F19: =IFERROR('3_Balance_Sheet'!F40/'3_Balance_Sheet'!F52,0) -> 0 | G19: =IFERROR('3_Balance_Sheet'!G40/'3_Balance_Sheet'!G52,0) -> 0 | H19: =IFERROR('3_Balance_Sheet'!H40/'3_Balance_Sheet'!H52,0) -> 0 | I19: =IFERROR('3_Balance_Sheet'!I40/'3_Balance_Sheet'!I52,0) -> 0 | J19: =IFERROR('3_Balance_Sheet'!J40/'3_Balance_Sheet'!J52,0) -> 0 | ... N19: =IFERROR('3_Balance_Sheet'!N40/'3_Balance_Sheet'!N52,0) -> 0 | O19: <= MaxTOLTNW | P19: =IF(INDEX('3_Balance_Sheet'!C52:N52,1,LatestAudCol)<=0,"⚠ Negative/Nil TNW — critical",IF(IFERROR(INDEX('3_Balance_Sheet'!C40:N40,1,LatestAudCol)/INDEX('3_Balance_Sheet'!C52:N52,1,LatestAudCol),0)>MaxTOLTNW,"⚠ TOL/TNW breach: "&TEXT(IFERROR(INDEX('3_Balance_Sheet'!C40:N40,1,LatestAudCol)/INDEX('3_Balance_Sheet'!C52:N52,1,LatestAudCol),0),"0.00x")&" exceeds "&TEXT(MaxTOLTNW,"0.00x")&" cap","✓ Leverage within tolerance")) -> ⚠ Negative/Nil TNW — critical
A20: 12 | B20: TTL / TNW (Long-term Debt / Equity) | C20: =IFERROR('3_Balance_Sheet'!C39/'3_Balance_Sheet'!C52,0) -> 0 | D20: =IFERROR('3_Balance_Sheet'!D39/'3_Balance_Sheet'!D52,0) -> 0 | E20: =IFERROR('3_Balance_Sheet'!E39/'3_Balance_Sheet'!E52,0) -> 0 | F20: =IFERROR('3_Balance_Sheet'!F39/'3_Balance_Sheet'!F52,0) -> 0 | G20: =IFERROR('3_Balance_Sheet'!G39/'3_Balance_Sheet'!G52,0) -> 0 | H20: =IFERROR('3_Balance_Sheet'!H39/'3_Balance_Sheet'!H52,0) -> 0 | I20: =IFERROR('3_Balance_Sheet'!I39/'3_Balance_Sheet'!I52,0) -> 0 | J20: =IFERROR('3_Balance_Sheet'!J39/'3_Balance_Sheet'!J52,0) -> 0 | ... N20: =IFERROR('3_Balance_Sheet'!N39/'3_Balance_Sheet'!N52,0) -> 0 | O20: <= 2.5x
A21: 13 | B21: Debt / EBITDA | C21: =IFERROR('3_Balance_Sheet'!C39/('2_Operating_Statement'!C33+'2_Operating_Statement'!C24),0) -> 0 | D21: =IFERROR('3_Balance_Sheet'!D39/('2_Operating_Statement'!D33+'2_Operating_Statement'!D24),0) -> 0 | E21: =IFERROR('3_Balance_Sheet'!E39/('2_Operating_Statement'!E33+'2_Operating_Statement'!E24),0) -> 0 | F21: =IFERROR('3_Balance_Sheet'!F39/('2_Operating_Statement'!F33+'2_Operating_Statement'!F24),0) -> 0 | G21: =IFERROR('3_Balance_Sheet'!G39/('2_Operating_Statement'!G33+'2_Operating_Statement'!G24),0) -> 0 | H21: =IFERROR('3_Balance_Sheet'!H39/('2_Operating_Statement'!H33+'2_Operating_Statement'!H24),0) -> 0 | I21: =IFERROR('3_Balance_Sheet'!I39/('2_Operating_Statement'!I33+'2_Operating_Statement'!I24),0) -> 0 | J21: =IFERROR('3_Balance_Sheet'!J39/('2_Operating_Statement'!J33+'2_Operating_Statement'!J24),0) -> 0 | ... N21: =IFERROR('3_Balance_Sheet'!N39/('2_Operating_Statement'!N33+'2_Operating_Statement'!N24),0) -> 0 | O21: <= MaxLeverage | P21: =IF((INDEX('2_Operating_Statement'!C33:N33,1,LatestAudCol)+INDEX('2_Operating_Statement'!C24:N24,1,LatestAudCol))<=0,"⚠ EBITDA negative or zero — leverage ratio undefined",IF(IFERROR(INDEX('3_Balance_Sheet'!C39:N39,1,LatestAudCol)/(INDEX('2_Operating_Statement'!C33:N33,1,LatestAudCol)+INDEX('2_Operating_Statement'!C24:N24,1,LatestAudCol)),0)>MaxLeverage,"⚠ Leverage breach: Debt/EBITDA exceeds "&TEXT(MaxLeverage,"0.00x"),"✓ Debt/EBITDA within ceiling")) -> ⚠ EBITDA negative or zero — leverage ratio undefined
A22: COVERAGE
A23: 14 | B23: Interest Coverage Ratio (EBIT / Interest) | C23: =IFERROR('2_Operating_Statement'!C33/'2_Operating_Statement'!C37,0) -> 0 | D23: =IFERROR('2_Operating_Statement'!D33/'2_Operating_Statement'!D37,0) -> 0 | E23: =IFERROR('2_Operating_Statement'!E33/'2_Operating_Statement'!E37,0) -> 0 | F23: =IFERROR('2_Operating_Statement'!F33/'2_Operating_Statement'!F37,0) -> 0 | G23: =IFERROR('2_Operating_Statement'!G33/'2_Operating_Statement'!G37,0) -> 0 | H23: =IFERROR('2_Operating_Statement'!H33/'2_Operating_Statement'!H37,0) -> 0 | I23: =IFERROR('2_Operating_Statement'!I33/'2_Operating_Statement'!I37,0) -> 0 | J23: =IFERROR('2_Operating_Statement'!J33/'2_Operating_Statement'!J37,0) -> 0 | ... N23: =IFERROR('2_Operating_Statement'!N33/'2_Operating_Statement'!N37,0) -> 0 | O23: >= MinICR | P23: =IF(INDEX('2_Operating_Statement'!C37:N37,1,LatestAudCol)<=0,"No interest in latest year",IF(IFERROR(INDEX('2_Operating_Statement'!C33:N33,1,LatestAudCol)/INDEX('2_Operating_Statement'!C37:N37,1,LatestAudCol),0)<MinICR,"⚠ ICR breach: "&TEXT(IFERROR(INDEX('2_Operating_Statement'!C33:N33,1,LatestAudCol)/INDEX('2_Operating_Statement'!C37:N37,1,LatestAudCol),0),"0.00x")&" below "&TEXT(MinICR,"0.00x"),"✓ ICR satisfactory")) -> No interest in latest year
A24: 15 | B24: DSCR (Gross — from DSCR sheet) | C24: ='4_DSCR'!C17 -> 0 | D24: ='4_DSCR'!D17 -> 0 | E24: ='4_DSCR'!E17 -> 0 | F24: ='4_DSCR'!F17 -> 0 | G24: ='4_DSCR'!G17 -> 0 | H24: ='4_DSCR'!H17 -> 0 | I24: ='4_DSCR'!I17 -> 0 | J24: ='4_DSCR'!J17 -> 0 | ... N24: ='4_DSCR'!N17 -> 0 | O24: >= MinDSCR_Any
A25: 16 | B25: Average Gross DSCR (from DSCR sheet) | C25: =IF(1=LatestAudCol,'4_DSCR'!C19,"") | D25: =IF(2=LatestAudCol,'4_DSCR'!C19,"") | E25: =IF(3=LatestAudCol,'4_DSCR'!C19,"") | F25: =IF(4=LatestAudCol,'4_DSCR'!C19,"") -> 0 | G25: =IF(5=LatestAudCol,'4_DSCR'!C19,"") | H25: =IF(6=LatestAudCol,'4_DSCR'!C19,"") | I25: =IF(7=LatestAudCol,'4_DSCR'!C19,"") | J25: =IF(8=LatestAudCol,'4_DSCR'!C19,"") | K25: =IF(9=LatestAudCol,'4_DSCR'!C19,"") | L25: =IF(10=LatestAudCol,'4_DSCR'!C19,"") | M25: =IF(11=LatestAudCol,'4_DSCR'!C19,"") | N25: =IF(12=LatestAudCol,'4_DSCR'!C19,"") | O25: >= MinDSCR_Avg
A26: EFFICIENCY / OPERATING CYCLE
A27: 17 | B27: Inventory Days (Inv / Net Sales × 365) | C27: =IFERROR('3_Balance_Sheet'!C73*365/'2_Operating_Statement'!C13,0) -> 0 | D27: =IFERROR('3_Balance_Sheet'!D73*365/'2_Operating_Statement'!D13,0) -> 0 | E27: =IFERROR('3_Balance_Sheet'!E73*365/'2_Operating_Statement'!E13,0) -> 0 | F27: =IFERROR('3_Balance_Sheet'!F73*365/'2_Operating_Statement'!F13,0) -> 0 | G27: =IFERROR('3_Balance_Sheet'!G73*365/'2_Operating_Statement'!G13,0) -> 0 | H27: =IFERROR('3_Balance_Sheet'!H73*365/'2_Operating_Statement'!H13,0) -> 0 | I27: =IFERROR('3_Balance_Sheet'!I73*365/'2_Operating_Statement'!I13,0) -> 0 | J27: =IFERROR('3_Balance_Sheet'!J73*365/'2_Operating_Statement'!J13,0) -> 0 | ... N27: =IFERROR('3_Balance_Sheet'!N73*365/'2_Operating_Statement'!N13,0) -> 0 | O27: Watch trend
A28: 18 | B28: DSO (Days Sales Outstanding) | C28: =IFERROR(('3_Balance_Sheet'!C59+'3_Balance_Sheet'!C60)*365/'2_Operating_Statement'!C10,0) -> 0 | D28: =IFERROR(('3_Balance_Sheet'!D59+'3_Balance_Sheet'!D60)*365/'2_Operating_Statement'!D10,0) -> 0 | E28: =IFERROR(('3_Balance_Sheet'!E59+'3_Balance_Sheet'!E60)*365/'2_Operating_Statement'!E10,0) -> 0 | F28: =IFERROR(('3_Balance_Sheet'!F59+'3_Balance_Sheet'!F60)*365/'2_Operating_Statement'!F10,0) -> 0 | G28: =IFERROR(('3_Balance_Sheet'!G59+'3_Balance_Sheet'!G60)*365/'2_Operating_Statement'!G10,0) -> 0 | H28: =IFERROR(('3_Balance_Sheet'!H59+'3_Balance_Sheet'!H60)*365/'2_Operating_Statement'!H10,0) -> 0 | I28: =IFERROR(('3_Balance_Sheet'!I59+'3_Balance_Sheet'!I60)*365/'2_Operating_Statement'!I10,0) -> 0 | J28: =IFERROR(('3_Balance_Sheet'!J59+'3_Balance_Sheet'!J60)*365/'2_Operating_Statement'!J10,0) -> 0 | ... N28: =IFERROR(('3_Balance_Sheet'!N59+'3_Balance_Sheet'!N60)*365/'2_Operating_Statement'!N10,0) -> 0 | O28: Watch trend | P28: =IF(INDEX('2_Operating_Statement'!C10:N10,1,LatestAudCol)<=0,"",IF(IFERROR(((INDEX('3_Balance_Sheet'!C59:N59,1,LatestAudCol)+INDEX('3_Balance_Sheet'!C60:N60,1,LatestAudCol))/(INDEX('3_Balance_Sheet'!C59:N59,1,PriorAudCol)+INDEX('3_Balance_Sheet'!C60:N60,1,PriorAudCol))-1),0)>MaxDSOIncrease,"⚠ DSO stretched materially — investigate ageing & overdue receivables","✓ DSO within tolerance"))
A29: 19 | B29: DPO (Days Payable Outstanding) | C29: =IFERROR(('3_Balance_Sheet'!C14+'3_Balance_Sheet'!C15)*365/('2_Operating_Statement'!C17+'2_Operating_Statement'!C20),0) -> 0 | D29: =IFERROR(('3_Balance_Sheet'!D14+'3_Balance_Sheet'!D15)*365/('2_Operating_Statement'!D17+'2_Operating_Statement'!D20),0) -> 0 | E29: =IFERROR(('3_Balance_Sheet'!E14+'3_Balance_Sheet'!E15)*365/('2_Operating_Statement'!E17+'2_Operating_Statement'!E20),0) -> 0 | F29: =IFERROR(('3_Balance_Sheet'!F14+'3_Balance_Sheet'!F15)*365/('2_Operating_Statement'!F17+'2_Operating_Statement'!F20),0) -> 0 | G29: =IFERROR(('3_Balance_Sheet'!G14+'3_Balance_Sheet'!G15)*365/('2_Operating_Statement'!G17+'2_Operating_Statement'!G20),0) -> 0 | H29: =IFERROR(('3_Balance_Sheet'!H14+'3_Balance_Sheet'!H15)*365/('2_Operating_Statement'!H17+'2_Operating_Statement'!H20),0) -> 0 | I29: =IFERROR(('3_Balance_Sheet'!I14+'3_Balance_Sheet'!I15)*365/('2_Operating_Statement'!I17+'2_Operating_Statement'!I20),0) -> 0 | J29: =IFERROR(('3_Balance_Sheet'!J14+'3_Balance_Sheet'!J15)*365/('2_Operating_Statement'!J17+'2_Operating_Statement'!J20),0) -> 0 | ... N29: =IFERROR(('3_Balance_Sheet'!N14+'3_Balance_Sheet'!N15)*365/('2_Operating_Statement'!N17+'2_Operating_Statement'!N20),0) -> 0 | O29: Watch trend
A30: 20 | B30: Cash Conversion Cycle (days) | C30: =IFERROR('3_Balance_Sheet'!C73*365/'2_Operating_Statement'!C13,0)+IFERROR(('3_Balance_Sheet'!C59+'3_Balance_Sheet'!C60)*365/'2_Operating_Statement'!C10,0)-IFERROR(('3_Balance_Sheet'!C14+'3_Balance_Sheet'!C15)*365/('2_Operating_Statement'!C17+'2_Operating_Statement'!C20),0) -> 0 | D30: =IFERROR('3_Balance_Sheet'!D73*365/'2_Operating_Statement'!D13,0)+IFERROR(('3_Balance_Sheet'!D59+'3_Balance_Sheet'!D60)*365/'2_Operating_Statement'!D10,0)-IFERROR(('3_Balance_Sheet'!D14+'3_Balance_Sheet'!D15)*365/('2_Operating_Statement'!D17+'2_Operating_Statement'!D20),0) -> 0 | E30: =IFERROR('3_Balance_Sheet'!E73*365/'2_Operating_Statement'!E13,0)+IFERROR(('3_Balance_Sheet'!E59+'3_Balance_Sheet'!E60)*365/'2_Operating_Statement'!E10,0)-IFERROR(('3_Balance_Sheet'!E14+'3_Balance_Sheet'!E15)*365/('2_Operating_Statement'!E17+'2_Operating_Statement'!E20),0) -> 0 | F30: =IFERROR('3_Balance_Sheet'!F73*365/'2_Operating_Statement'!F13,0)+IFERROR(('3_Balance_Sheet'!F59+'3_Balance_Sheet'!F60)*365/'2_Operating_Statement'!F10,0)-IFERROR(('3_Balance_Sheet'!F14+'3_Balance_Sheet'!F15)*365/('2_Operating_Statement'!F17+'2_Operating_Statement'!F20),0) -> 0 | G30: =IFERROR('3_Balance_Sheet'!G73*365/'2_Operating_Statement'!G13,0)+IFERROR(('3_Balance_Sheet'!G59+'3_Balance_Sheet'!G60)*365/'2_Operating_Statement'!G10,0)-IFERROR(('3_Balance_Sheet'!G14+'3_Balance_Sheet'!G15)*365/('2_Operating_Statement'!G17+'2_Operating_Statement'!G20),0) -> 0 | H30: =IFERROR('3_Balance_Sheet'!H73*365/'2_Operating_Statement'!H13,0)+IFERROR(('3_Balance_Sheet'!H59+'3_Balance_Sheet'!H60)*365/'2_Operating_Statement'!H10,0)-IFERROR(('3_Balance_Sheet'!H14+'3_Balance_Sheet'!H15)*365/('2_Operating_Statement'!H17+'2_Operating_Statement'!H20),0) -> 0 | I30: =IFERROR('3_Balance_Sheet'!I73*365/'2_Operating_Statement'!I13,0)+IFERROR(('3_Balance_Sheet'!I59+'3_Balance_Sheet'!I60)*365/'2_Operating_Statement'!I10,0)-IFERROR(('3_Balance_Sheet'!I14+'3_Balance_Sheet'!I15)*365/('2_Operating_Statement'!I17+'2_Operating_Statement'!I20),0) -> 0 | J30: =IFERROR('3_Balance_Sheet'!J73*365/'2_Operating_Statement'!J13,0)+IFERROR(('3_Balance_Sheet'!J59+'3_Balance_Sheet'!J60)*365/'2_Operating_Statement'!J10,0)-IFERROR(('3_Balance_Sheet'!J14+'3_Balance_Sheet'!J15)*365/('2_Operating_Statement'!J17+'2_Operating_Statement'!J20),0) -> 0 | ... N30: =IFERROR('3_Balance_Sheet'!N73*365/'2_Operating_Statement'!N13,0)+IFERROR(('3_Balance_Sheet'!N59+'3_Balance_Sheet'!N60)*365/'2_Operating_Statement'!N10,0)-IFERROR(('3_Balance_Sheet'!N14+'3_Balance_Sheet'!N15)*365/('2_Operating_Statement'!N17+'2_Operating_Statement'!N20),0) -> 0 | O30: Watch trend
A31: RETURNS
A32: 21 | B32: RoCE (PBIT / (TNW + TTL)) | C32: =IFERROR(('2_Operating_Statement'!C33)/('3_Balance_Sheet'!C52+'3_Balance_Sheet'!C39),0) -> 0 | D32: =IFERROR(('2_Operating_Statement'!D33)/('3_Balance_Sheet'!D52+'3_Balance_Sheet'!D39),0) -> 0 | E32: =IFERROR(('2_Operating_Statement'!E33)/('3_Balance_Sheet'!E52+'3_Balance_Sheet'!E39),0) -> 0 | F32: =IFERROR(('2_Operating_Statement'!F33)/('3_Balance_Sheet'!F52+'3_Balance_Sheet'!F39),0) -> 0 | G32: =IFERROR(('2_Operating_Statement'!G33)/('3_Balance_Sheet'!G52+'3_Balance_Sheet'!G39),0) -> 0 | H32: =IFERROR(('2_Operating_Statement'!H33)/('3_Balance_Sheet'!H52+'3_Balance_Sheet'!H39),0) -> 0 | I32: =IFERROR(('2_Operating_Statement'!I33)/('3_Balance_Sheet'!I52+'3_Balance_Sheet'!I39),0) -> 0 | J32: =IFERROR(('2_Operating_Statement'!J33)/('3_Balance_Sheet'!J52+'3_Balance_Sheet'!J39),0) -> 0 | ... N32: =IFERROR(('2_Operating_Statement'!N33)/('3_Balance_Sheet'!N52+'3_Balance_Sheet'!N39),0) -> 0 | O32: >= 12%
A33: 22 | B33: RoE (PAT / TNW) | C33: =IFERROR('2_Operating_Statement'!C58/'3_Balance_Sheet'!C52,0) -> 0 | D33: =IFERROR('2_Operating_Statement'!D58/'3_Balance_Sheet'!D52,0) -> 0 | E33: =IFERROR('2_Operating_Statement'!E58/'3_Balance_Sheet'!E52,0) -> 0 | F33: =IFERROR('2_Operating_Statement'!F58/'3_Balance_Sheet'!F52,0) -> 0 | G33: =IFERROR('2_Operating_Statement'!G58/'3_Balance_Sheet'!G52,0) -> 0 | H33: =IFERROR('2_Operating_Statement'!H58/'3_Balance_Sheet'!H52,0) -> 0 | I33: =IFERROR('2_Operating_Statement'!I58/'3_Balance_Sheet'!I52,0) -> 0 | J33: =IFERROR('2_Operating_Statement'!J58/'3_Balance_Sheet'!J52,0) -> 0 | ... N33: =IFERROR('2_Operating_Statement'!N58/'3_Balance_Sheet'!N52,0) -> 0 | O33: >= 10%

Sheet 9_Cross_Checks
A1: =CONCATENATE("CROSS CHECKS | ", BorrowerName) -> CROSS CHECKS |
A2: Internal consistency tests across input sheets. Should all show ✓ at zero.
A3: Sr | B3: Cross Check | C3: Yr 1 | D3: Yr 2 | E3: Yr 3 | F3: Yr 4 | G3: Yr 5 | H3: Yr 6 | I3: Yr 7 | J3: Yr 8 | K3: Yr 9 | L3: Yr 10 | M3: Yr 11 | N3: Yr 12 | O3: Status | P3: Note
B4: Year → | C4: =INDEX('0_Setup'!$B$48:$B$59,1) -> 2022-23 | D4: =INDEX('0_Setup'!$B$48:$B$59,2) -> 2023-24 | E4: =INDEX('0_Setup'!$B$48:$B$59,3) -> 2024-25 | F4: =INDEX('0_Setup'!$B$48:$B$59,4) -> 2024-25 | G4: =INDEX('0_Setup'!$B$48:$B$59,5) -> 2025-26 | H4: =INDEX('0_Setup'!$B$48:$B$59,6) -> 2026-27 | I4: =INDEX('0_Setup'!$B$48:$B$59,7) -> 2027-28 | J4: =INDEX('0_Setup'!$B$48:$B$59,8) -> 2028-29 | K4: =INDEX('0_Setup'!$B$48:$B$59,9) -> 2029-30 | L4: =INDEX('0_Setup'!$B$48:$B$59,10) | M4: =INDEX('0_Setup'!$B$48:$B$59,11) | N4: =INDEX('0_Setup'!$B$48:$B$59,12)
A6: 1 | B6: Balance Sheet Check (Total Liab − Total Assets) | C6: ='3_Balance_Sheet'!C53-'3_Balance_Sheet'!C108 -> 0 | D6: ='3_Balance_Sheet'!D53-'3_Balance_Sheet'!D108 -> 0 | E6: ='3_Balance_Sheet'!E53-'3_Balance_Sheet'!E108 -> 0 | F6: ='3_Balance_Sheet'!F53-'3_Balance_Sheet'!F108 -> 0 | G6: ='3_Balance_Sheet'!G53-'3_Balance_Sheet'!G108 -> 0 | H6: ='3_Balance_Sheet'!H53-'3_Balance_Sheet'!H108 -> 0 | I6: ='3_Balance_Sheet'!I53-'3_Balance_Sheet'!I108 -> 0 | J6: ='3_Balance_Sheet'!J53-'3_Balance_Sheet'!J108 -> 0 | ... N6: ='3_Balance_Sheet'!N53-'3_Balance_Sheet'!N108 -> 0 | O6: =IF(SUMPRODUCT(--(ABS(C6:N6)>0.5))=0,"✓ All Match","⚠ Discrepancy") -> ✓ All Match | P6: Must = 0
A7: 2 | B7: TCA from BS = Sum of components | C7: ='3_Balance_Sheet'!C82-('3_Balance_Sheet'!C58+'3_Balance_Sheet'!C63+'3_Balance_Sheet'!C73+'3_Balance_Sheet'!C74+'3_Balance_Sheet'!C75+'3_Balance_Sheet'!C81) -> 0 | D7: ='3_Balance_Sheet'!D82-('3_Balance_Sheet'!D58+'3_Balance_Sheet'!D63+'3_Balance_Sheet'!D73+'3_Balance_Sheet'!D74+'3_Balance_Sheet'!D75+'3_Balance_Sheet'!D81) -> 0 | E7: ='3_Balance_Sheet'!E82-('3_Balance_Sheet'!E58+'3_Balance_Sheet'!E63+'3_Balance_Sheet'!E73+'3_Balance_Sheet'!E74+'3_Balance_Sheet'!E75+'3_Balance_Sheet'!E81) -> 0 | F7: ='3_Balance_Sheet'!F82-('3_Balance_Sheet'!F58+'3_Balance_Sheet'!F63+'3_Balance_Sheet'!F73+'3_Balance_Sheet'!F74+'3_Balance_Sheet'!F75+'3_Balance_Sheet'!F81) -> 0 | G7: ='3_Balance_Sheet'!G82-('3_Balance_Sheet'!G58+'3_Balance_Sheet'!G63+'3_Balance_Sheet'!G73+'3_Balance_Sheet'!G74+'3_Balance_Sheet'!G75+'3_Balance_Sheet'!G81) -> 0 | H7: ='3_Balance_Sheet'!H82-('3_Balance_Sheet'!H58+'3_Balance_Sheet'!H63+'3_Balance_Sheet'!H73+'3_Balance_Sheet'!H74+'3_Balance_Sheet'!H75+'3_Balance_Sheet'!H81) -> 0 | I7: ='3_Balance_Sheet'!I82-('3_Balance_Sheet'!I58+'3_Balance_Sheet'!I63+'3_Balance_Sheet'!I73+'3_Balance_Sheet'!I74+'3_Balance_Sheet'!I75+'3_Balance_Sheet'!I81) -> 0 | J7: ='3_Balance_Sheet'!J82-('3_Balance_Sheet'!J58+'3_Balance_Sheet'!J63+'3_Balance_Sheet'!J73+'3_Balance_Sheet'!J74+'3_Balance_Sheet'!J75+'3_Balance_Sheet'!J81) -> 0 | ... N7: ='3_Balance_Sheet'!N82-('3_Balance_Sheet'!N58+'3_Balance_Sheet'!N63+'3_Balance_Sheet'!N73+'3_Balance_Sheet'!N74+'3_Balance_Sheet'!N75+'3_Balance_Sheet'!N81) -> 0 | O7: =IF(SUMPRODUCT(--(ABS(C7:N7)>0.5))=0,"✓ All Match","⚠ Discrepancy") -> ✓ All Match | P7: Must = 0
A8: 3 | B8: TCL from BS = STBB + Other CL | C8: ='3_Balance_Sheet'!C27-('3_Balance_Sheet'!C11+'3_Balance_Sheet'!C26) -> 0 | D8: ='3_Balance_Sheet'!D27-('3_Balance_Sheet'!D11+'3_Balance_Sheet'!D26) -> 0 | E8: ='3_Balance_Sheet'!E27-('3_Balance_Sheet'!E11+'3_Balance_Sheet'!E26) -> 0 | F8: ='3_Balance_Sheet'!F27-('3_Balance_Sheet'!F11+'3_Balance_Sheet'!F26) -> 0 | G8: ='3_Balance_Sheet'!G27-('3_Balance_Sheet'!G11+'3_Balance_Sheet'!G26) -> 0 | H8: ='3_Balance_Sheet'!H27-('3_Balance_Sheet'!H11+'3_Balance_Sheet'!H26) -> 0 | I8: ='3_Balance_Sheet'!I27-('3_Balance_Sheet'!I11+'3_Balance_Sheet'!I26) -> 0 | J8: ='3_Balance_Sheet'!J27-('3_Balance_Sheet'!J11+'3_Balance_Sheet'!J26) -> 0 | ... N8: ='3_Balance_Sheet'!N27-('3_Balance_Sheet'!N11+'3_Balance_Sheet'!N26) -> 0 | O8: =IF(SUMPRODUCT(--(ABS(C8:N8)>0.5))=0,"✓ All Match","⚠ Discrepancy") -> ✓ All Match | P8: Must = 0
A9: 4 | B9: Net Sales = Gross Sales − Excise/Other | C9: ='2_Operating_Statement'!C13-('2_Operating_Statement'!C10-'2_Operating_Statement'!C11-'2_Operating_Statement'!C12) -> 0 | D9: ='2_Operating_Statement'!D13-('2_Operating_Statement'!D10-'2_Operating_Statement'!D11-'2_Operating_Statement'!D12) -> 0 | E9: ='2_Operating_Statement'!E13-('2_Operating_Statement'!E10-'2_Operating_Statement'!E11-'2_Operating_Statement'!E12) -> 0 | F9: ='2_Operating_Statement'!F13-('2_Operating_Statement'!F10-'2_Operating_Statement'!F11-'2_Operating_Statement'!F12) -> 0 | G9: ='2_Operating_Statement'!G13-('2_Operating_Statement'!G10-'2_Operating_Statement'!G11-'2_Operating_Statement'!G12) -> 0 | H9: ='2_Operating_Statement'!H13-('2_Operating_Statement'!H10-'2_Operating_Statement'!H11-'2_Operating_Statement'!H12) -> 0 | I9: ='2_Operating_Statement'!I13-('2_Operating_Statement'!I10-'2_Operating_Statement'!I11-'2_Operating_Statement'!I12) -> 0 | J9: ='2_Operating_Statement'!J13-('2_Operating_Statement'!J10-'2_Operating_Statement'!J11-'2_Operating_Statement'!J12) -> 0 | ... N9: ='2_Operating_Statement'!N13-('2_Operating_Statement'!N10-'2_Operating_Statement'!N11-'2_Operating_Statement'!N12) -> 0 | O9: =IF(SUMPRODUCT(--(ABS(C9:N9)>0.5))=0,"✓ All Match","⚠ Discrepancy") -> ✓ All Match | P9: Must = 0
A10: 5 | B10: PAT correct (PBT − Tax − Prior + MAT) | C10: ='2_Operating_Statement'!C58-('2_Operating_Statement'!C54-'2_Operating_Statement'!C56-'2_Operating_Statement'!C57+'2_Operating_Statement'!C55) -> 0 | D10: ='2_Operating_Statement'!D58-('2_Operating_Statement'!D54-'2_Operating_Statement'!D56-'2_Operating_Statement'!D57+'2_Operating_Statement'!D55) -> 0 | E10: ='2_Operating_Statement'!E58-('2_Operating_Statement'!E54-'2_Operating_Statement'!E56-'2_Operating_Statement'!E57+'2_Operating_Statement'!E55) -> 0 | F10: ='2_Operating_Statement'!F58-('2_Operating_Statement'!F54-'2_Operating_Statement'!F56-'2_Operating_Statement'!F57+'2_Operating_Statement'!F55) -> 0 | G10: ='2_Operating_Statement'!G58-('2_Operating_Statement'!G54-'2_Operating_Statement'!G56-'2_Operating_Statement'!G57+'2_Operating_Statement'!G55) -> 0 | H10: ='2_Operating_Statement'!H58-('2_Operating_Statement'!H54-'2_Operating_Statement'!H56-'2_Operating_Statement'!H57+'2_Operating_Statement'!H55) -> 0 | I10: ='2_Operating_Statement'!I58-('2_Operating_Statement'!I54-'2_Operating_Statement'!I56-'2_Operating_Statement'!I57+'2_Operating_Statement'!I55) -> 0 | J10: ='2_Operating_Statement'!J58-('2_Operating_Statement'!J54-'2_Operating_Statement'!J56-'2_Operating_Statement'!J57+'2_Operating_Statement'!J55) -> 0 | ... N10: ='2_Operating_Statement'!N58-('2_Operating_Statement'!N54-'2_Operating_Statement'!N56-'2_Operating_Statement'!N57+'2_Operating_Statement'!N55) -> 0 | O10: =IF(SUMPRODUCT(--(ABS(C10:N10)>0.5))=0,"✓ All Match","⚠ Discrepancy") -> ✓ All Match | P10: Must = 0

Sheet 10_Credit_Limits
A1: =CONCATENATE("CREDIT LIMITS | ", BorrowerName) -> CREDIT LIMITS |
A2: Facility-wise existing limits, proposed limits (where applicable), pricing, and tenor.
A4: Sr | B4: Facility Type | C4: Sub-Facility | D4: Existing Limit (₹ Cr) | E4: Proposed Limit (₹ Cr) | F4: Tenor / Repayment | G4: Interest Rate / Pricing | H4: Notes
A6: FUND-BASED — WORKING CAPITAL
A7: 1 | B7: FB - Working Capital | C7: Cash Credit | F7: On Demand
A8: 2 | B8: FB - Working Capital | C8: Working Capital Demand Loan | F8: On Demand
A9: 3 | B9: FB - Working Capital | C9: Bills Discounting | F9: 60-180 days
A10: 4 | B10: FB - Working Capital | C10: Buyer's Credit (FCNR) | F10: 6-12 months
B11: Sub-Total FB - WC | D11: =SUM(D7:D10) -> 0 | E11: =SUM(E7:E10) -> 0
A13: FUND-BASED — TERM LOANS
A14: 1 | B14: FB - Term Loan | C14: Term Loan I
A15: 2 | B15: FB - Term Loan | C15: Term Loan II
A16: 3 | B16: FB - Term Loan | C16: Term Loan III
A17: 4 | B17: FB - Term Loan | C17: Equipment Finance / Vehicle Loan
B18: Sub-Total FB - TL | D18: =SUM(D14:D17) -> 0 | E18: =SUM(E14:E17) -> 0
A20: NON-FUND BASED LIMITS
A21: 1 | B21: Non-Fund Based | C21: Letter of Credit (Inland) | F21: 180 days
A22: 2 | B22: Non-Fund Based | C22: Letter of Credit (Foreign) | F22: 180 days
A23: 3 | B23: Non-Fund Based | C23: Bank Guarantee — Performance | F23: Up to 5 yrs
A24: 4 | B24: Non-Fund Based | C24: Bank Guarantee — Financial | F24: Up to 1 yr
B25: Sub-Total NFB | D25: =SUM(D21:D24) -> 0 | E25: =SUM(E21:E24) -> 0
B27: GRAND TOTAL (FB + NFB) | D27: =D11+D18+D25 -> 0 | E27: =E11+E18+E25 -> 0
A29: Check vs Setup: | B29: =IF(AND(D11=ExistingFB_WC,D18=ExistingFB_TL,D25=ExistingNFB),"✓ Limits tally with Setup totals","⚠ Limits don't tally with Setup — recheck either Setup or sub-facility lines") -> ✓ Limits tally with Setup totals
A30: SYSTEM EXPOSURE & CHAPTER XIA COMPLIANCE | RBI Amendment Directions Apr 2026
A31: Chapter XIA enforces strict current/OD account discipline. For aggregate banking exposure ≥ ₹10 Cr, applicant bank must hold ≥10% share of total banking exposure to maintain standard Current/OD accounts; otherwise only Collection Accounts (T+2 sweep) are permitted. Source: CRILC / CIBIL Commercial.
B33: Chapter XIA Input Field | D33: Existing (₹ Cr) | E33: Proposed (₹ Cr) | F33: Source
B34: Total Limits Sanctioned by Other Banks | D34: 0 | E34: 0 | F34: Source: CRILC / CIBIL Commercial Report
B35: Applicant Bank Proposed Limits (FB+NFB) | D35: =D26 -> 0 | E35: =E26 -> 0 | F35: Auto: Grand Total above
B36: Aggregate Banking System Exposure | D36: =D34+D35 -> 0 | E36: =E34+E35 -> 0 | F36: Total (this bank + all others)
B37: Applicant Bank Share of Total Exposure | D37: =IFERROR(D35/D36,0) -> 0 | E37: =IFERROR(E35/E36,0) -> 0 | F37: Bank share of aggregate exposure
B39: CHAPTER XIA COMPLIANCE STATUS | D39: Existing | E39: Proposed | F39: Implication
B40: Account Operation Permission | D40: =IF(D37<10,"🟢 NO RESTRICTION",IF(D39>=0.1,"🟢 COMPLIANT","🔴 RESTRICTED")) -> 🟢 NO RESTRICTION | E40: =IF(E37<10,"🟢 NO RESTRICTION",IF(E39>=0.1,"🟢 COMPLIANT","🔴 RESTRICTED")) -> 🟢 NO RESTRICTION | F40: =IF(E37<10,"Aggregate exposure < ₹10 Cr — bank may operate Current/OD accounts freely.",IF(E39>=0.1,"Bank share ≥10% of aggregate. Authorised to operate full standard Current/OD accounts.","Bank share <10% of aggregate. Only restricted Collection Accounts permitted. Mandatory escrow + T+2 sweep to compliant primary bank. Outward business debits prohibited.")) -> Aggregate exposure < ₹10 Cr — bank may operate Current/OD accounts freely.

Sheet 11_Security
A1: =CONCATENATE("SECURITY | ", BorrowerName) -> SECURITY |
A2: Primary security on stocks/receivables for WC; FA charge for TL. Collateral coverage % auto-computed.
A4: Sr | B4: Security Description | C4: Type (Primary/Collateral) | D4: Value (₹ Cr) | E4: Charge Type (1st pari-passu / Exclusive) | F4: Notes
A6: PRIMARY SECURITY
A7: 1 | B7: Hypothecation of stocks (RM, WIP, FG) | C7: Primary
A8: 2 | B8: Hypothecation of book debts / receivables | C8: Primary
A9: 3 | B9: Equitable mortgage of factory premises | C9: Primary
A10: 4 | B10: Hypothecation of plant & machinery | C10: Primary
A11: 5 | B11: Other primary security | C11: Primary
B12: Sub-Total Primary | D12: =SUM(D7:D11) -> 0
A14: COLLATERAL SECURITY
A15: 1 | B15: Equitable mortgage — Land/property (3rd party) | C15: Collateral
A16: 2 | B16: Lien on Fixed Deposits | C16: Collateral
A17: 3 | B17: Pledge of shares / securities | C17: Collateral
A18: 4 | B18: Personal Guarantee — Promoter(s) | C18: Collateral
A19: 5 | B19: Corporate Guarantee — Group company | C19: Collateral
A20: 6 | B20: Other collateral | C20: Collateral
B21: Sub-Total Collateral | D21: =SUM(D15:D20) -> 0
A23: COVERAGE ANALYSIS
A24: Total Sanctioned Limits (FB Existing + Proposed) | D24: =ExistingFB_WC+ExistingFB_TL+ProposedFB_WC+ProposedFB_TL -> 0
A25: Total Security Value (Primary + Collateral) | D25: =D12+D21 -> 0
A26: Security Coverage (Total Security / Total Sanctioned FB) | D26: =IFERROR(D25/D24,0) -> 0 | E26: =IF(D24=0,"Awaiting limit data",IF(D26<1,"⚠ Coverage <100%",IF(D26<1.5,"✓ Coverage adequate (100-150%)","✓ Coverage strong (>150%)"))) -> Awaiting limit data

Sheet 12_Red_Flags
A1: =CONCATENATE("RED FLAGS DASHBOARD | ", BorrowerName) -> RED FLAGS DASHBOARD |
A2: Each red flag shows the test, current value, threshold, status, AND a citation of the source rows/columns driving the conclusion.
A4: # | B4: Red Flag Test | C4: Source Reference | D4: Current Value | E4: Threshold | F4: Status | G4: Detail / Action Required
A5: SECTION I — PROFITABILITY
A6: 1 | B6: Loss in any latest year (PAT) | C6: Op Stmt row 58 (PAT) — Latest Aud col | D6: =INDEX('2_Operating_Statement'!C58:N58,1,LatestAudCol) -> 0 | E6: ≥ 0 | F6: =IF(INDEX('2_Operating_Statement'!C58:N58,1,LatestAudCol)<0,"⚠ BREACH","✓ OK") -> ✓ OK | G6: =IF(INDEX('2_Operating_Statement'!C58:N58,1,LatestAudCol)<0,"PAT was negative in latest audited year. Investigate root cause — one-off vs structural. Test sustainability.","No loss in latest year.") -> No loss in latest year.
A7: 2 | B7: OPM declining trend (Latest Aud vs Prior Aud) | C7: Op Stmt row 33 (OPBI) ÷ row 13 (Net Sales) | D7: =IFERROR(INDEX('2_Operating_Statement'!C33:N33,1,LatestAudCol)/INDEX('2_Operating_Statement'!C13:N13,1,LatestAudCol),0)-IFERROR(INDEX('2_Operating_Statement'!C33:N33,1,PriorAudCol)/INDEX('2_Operating_Statement'!C13:N13,1,PriorAudCol),0) -> 0 | E7: Δ ≥ -2pp | F7: =IF(IFERROR(INDEX('2_Operating_Statement'!C33:N33,1,LatestAudCol)/INDEX('2_Operating_Statement'!C13:N13,1,LatestAudCol),0)-IFERROR(INDEX('2_Operating_Statement'!C33:N33,1,PriorAudCol)/INDEX('2_Operating_Statement'!C13:N13,1,PriorAudCol),0)<-0.02,"⚠ BREACH","✓ OK") -> ✓ OK | G7: =IF(IFERROR(INDEX('2_Operating_Statement'!C33:N33,1,LatestAudCol)/INDEX('2_Operating_Statement'!C13:N13,1,LatestAudCol),0)-IFERROR(INDEX('2_Operating_Statement'!C33:N33,1,PriorAudCol)/INDEX('2_Operating_Statement'!C13:N13,1,PriorAudCol),0)<-0.02,"OPM compressed >2pp YoY. Quantify cost element driving compression (RM/power/labour) and check pass-through ability.","OPM stable / improved YoY.") -> OPM stable / improved YoY.
A8: 3 | B8: Sales jump > 50% (verification needed) | C8: Op Stmt row 13 (Net Sales) Latest vs Prior Aud | D8: =IFERROR((INDEX('2_Operating_Statement'!C13:N13,1,LatestAudCol)-INDEX('2_Operating_Statement'!C13:N13,1,PriorAudCol))/INDEX('2_Operating_Statement'!C13:N13,1,PriorAudCol),0) -> 0 | E8: ≤ 50% | F8: =IF(IFERROR((INDEX('2_Operating_Statement'!C13:N13,1,LatestAudCol)-INDEX('2_Operating_Statement'!C13:N13,1,PriorAudCol))/INDEX('2_Operating_Statement'!C13:N13,1,PriorAudCol),0)>0.5,"⚠ VERIFY","✓ OK") -> ✓ OK | G8: =IF(IFERROR((INDEX('2_Operating_Statement'!C13:N13,1,LatestAudCol)-INDEX('2_Operating_Statement'!C13:N13,1,PriorAudCol))/INDEX('2_Operating_Statement'!C13:N13,1,PriorAudCol),0)>0.5,"Sales jumped >50% YoY. Verify with GST 3B/9 returns, sales register, customer concentration. Check for one-off contracts / order book stretch.","Sales growth within reasonable range.") -> Sales growth within reasonable range.
A9: 4 | B9: Sales decline (Latest Aud vs Prior Aud) | C9: Op Stmt row 13 | D9: =IFERROR((INDEX('2_Operating_Statement'!C13:N13,1,LatestAudCol)-INDEX('2_Operating_Statement'!C13:N13,1,PriorAudCol))/INDEX('2_Operating_Statement'!C13:N13,1,PriorAudCol),0) -> 0 | E9: ≥ MinSalesGrowth | F9: =IF(IFERROR((INDEX('2_Operating_Statement'!C13:N13,1,LatestAudCol)-INDEX('2_Operating_Statement'!C13:N13,1,PriorAudCol))/INDEX('2_Operating_Statement'!C13:N13,1,PriorAudCol),0)<MinSalesGrowth,"⚠ BREACH","✓ OK") -> ✓ OK | G9: =IF(IFERROR((INDEX('2_Operating_Statement'!C13:N13,1,LatestAudCol)-INDEX('2_Operating_Statement'!C13:N13,1,PriorAudCol))/INDEX('2_Operating_Statement'!C13:N13,1,PriorAudCol),0)<MinSalesGrowth,"Net Sales declined materially. Investigate volume vs realisation; check competitive position; assess sustainability of WC limit.","Sales trajectory within tolerance.") -> Sales trajectory within tolerance.
A10: SECTION II — LIQUIDITY
A11: 5 | B11: Current Ratio breach (Latest Aud) | C11: BS row 82 (TCA) ÷ row 27 (TCL) | D11: =IFERROR(INDEX('3_Balance_Sheet'!C82:N82,1,LatestAudCol)/INDEX('3_Balance_Sheet'!C27:N27,1,LatestAudCol),0) -> 0 | E11: ≥ MinCR | F11: =IF(IFERROR(INDEX('3_Balance_Sheet'!C82:N82,1,LatestAudCol)/INDEX('3_Balance_Sheet'!C27:N27,1,LatestAudCol),0)<MinCR,"⚠ BREACH","✓ OK") -> ⚠ BREACH | G11: =IF(IFERROR(INDEX('3_Balance_Sheet'!C82:N82,1,LatestAudCol)/INDEX('3_Balance_Sheet'!C27:N27,1,LatestAudCol),0)<MinCR,"CR below threshold. Liquidity stretched. Examine inventory build, receivable ageing, and STBB concentration.","CR meets minimum acceptable level.") -> CR below threshold. Liquidity stretched. Examine inventory build, receivable ageing, and STBB concentration.
A12: 6 | B12: Negative or eroded NWC | C12: BS row 82 (TCA) − row 27 (TCL) | D12: =INDEX('3_Balance_Sheet'!C82:N82,1,LatestAudCol)-INDEX('3_Balance_Sheet'!C27:N27,1,LatestAudCol) -> 0 | E12: > 0 | F12: =IF(INDEX('3_Balance_Sheet'!C82:N82,1,LatestAudCol)-INDEX('3_Balance_Sheet'!C27:N27,1,LatestAudCol)<=0,"⚠ BREACH","✓ OK") -> ⚠ BREACH | G12: =IF(INDEX('3_Balance_Sheet'!C82:N82,1,LatestAudCol)-INDEX('3_Balance_Sheet'!C27:N27,1,LatestAudCol)<=0,"NWC is negative — TCA insufficient to cover TCL. Borrower cannot self-fund operating cycle. Critical for WC limit decision.","NWC positive.") -> NWC is negative — TCA insufficient to cover TCL. Borrower cannot self-fund operating cycle. Critical for WC limit decision.
A13: 7 | B13: NWC erosion YoY > tolerance | C13: BS row 82 − row 27 (Latest vs Prior Aud) | D13: =IFERROR(((INDEX('3_Balance_Sheet'!C82:N82,1,LatestAudCol)-INDEX('3_Balance_Sheet'!C27:N27,1,LatestAudCol))-(INDEX('3_Balance_Sheet'!C82:N82,1,PriorAudCol)-INDEX('3_Balance_Sheet'!C27:N27,1,PriorAudCol)))/ABS(INDEX('3_Balance_Sheet'!C82:N82,1,PriorAudCol)-INDEX('3_Balance_Sheet'!C27:N27,1,PriorAudCol)),0) -> 0 | E13: ≥ MaxNWCErosion | F13: =IF(IFERROR(((INDEX('3_Balance_Sheet'!C82:N82,1,LatestAudCol)-INDEX('3_Balance_Sheet'!C27:N27,1,LatestAudCol))-(INDEX('3_Balance_Sheet'!C82:N82,1,PriorAudCol)-INDEX('3_Balance_Sheet'!C27:N27,1,PriorAudCol)))/ABS(INDEX('3_Balance_Sheet'!C82:N82,1,PriorAudCol)-INDEX('3_Balance_Sheet'!C27:N27,1,PriorAudCol)),0)<MaxNWCErosion,"⚠ BREACH","✓ OK") -> ✓ OK | G13: =IF(IFERROR(((INDEX('3_Balance_Sheet'!C82:N82,1,LatestAudCol)-INDEX('3_Balance_Sheet'!C27:N27,1,LatestAudCol))-(INDEX('3_Balance_Sheet'!C82:N82,1,PriorAudCol)-INDEX('3_Balance_Sheet'!C27:N27,1,PriorAudCol)))/ABS(INDEX('3_Balance_Sheet'!C82:N82,1,PriorAudCol)-INDEX('3_Balance_Sheet'!C27:N27,1,PriorAudCol)),0)<MaxNWCErosion,"NWC eroded sharply YoY — typically signals capex from internal accruals, cash payouts, or losses. Reconcile with Funds Flow.","NWC stable / improved.") -> NWC stable / improved.
A14: SECTION III — LEVERAGE
A15: 8 | B15: TOL/TNW exceeds threshold | C15: BS row 40 (TOL) ÷ row 52 (TNW) | D15: =IFERROR(INDEX('3_Balance_Sheet'!C40:N40,1,LatestAudCol)/INDEX('3_Balance_Sheet'!C52:N52,1,LatestAudCol),0) -> 0 | E15: ≤ MaxTOLTNW | F15: =IF(IFERROR(INDEX('3_Balance_Sheet'!C40:N40,1,LatestAudCol)/INDEX('3_Balance_Sheet'!C52:N52,1,LatestAudCol),0)>MaxTOLTNW,"⚠ BREACH","✓ OK") -> ✓ OK | G15: =IF(INDEX('3_Balance_Sheet'!C52:N52,1,LatestAudCol)<=0,"TNW negative or zero. Critical — solvency at risk.",IF(IFERROR(INDEX('3_Balance_Sheet'!C40:N40,1,LatestAudCol)/INDEX('3_Balance_Sheet'!C52:N52,1,LatestAudCol),0)>MaxTOLTNW,"Leverage breach. Quantify gap; check fresh equity infusion plan or debt repayment schedule; tighten covenants.","Leverage within tolerance.")) -> TNW negative or zero. Critical — solvency at risk.
A16: 9 | B16: Negative or zero TNW | C16: BS row 52 (TNW) Latest Aud | D16: =INDEX('3_Balance_Sheet'!C52:N52,1,LatestAudCol) -> 0 | E16: > 0 | F16: =IF(INDEX('3_Balance_Sheet'!C52:N52,1,LatestAudCol)<=0,"⚠ CRITICAL","✓ OK") -> ⚠ CRITICAL | G16: =IF(INDEX('3_Balance_Sheet'!C52:N52,1,LatestAudCol)<=0,"TNW eroded — indicates accumulated losses exceed paid-up capital + reserves. Restructuring or fresh equity is essential.","TNW positive.") -> TNW eroded — indicates accumulated losses exceed paid-up capital + reserves. Restructuring or fresh equity is essential.
A17: 10 | B17: Debt/EBITDA breach | C17: BS row 39 (TTL) ÷ (Op Stmt row 33 + row 24) | D17: =IFERROR(INDEX('3_Balance_Sheet'!C39:N39,1,LatestAudCol)/(INDEX('2_Operating_Statement'!C33:N33,1,LatestAudCol)+INDEX('2_Operating_Statement'!C24:N24,1,LatestAudCol)),0) -> 0 | E17: ≤ MaxLeverage | F17: =IF((INDEX('2_Operating_Statement'!C33:N33,1,LatestAudCol)+INDEX('2_Operating_Statement'!C24:N24,1,LatestAudCol))<=0,"⚠ EBITDA NIL",IF(IFERROR(INDEX('3_Balance_Sheet'!C39:N39,1,LatestAudCol)/(INDEX('2_Operating_Statement'!C33:N33,1,LatestAudCol)+INDEX('2_Operating_Statement'!C24:N24,1,LatestAudCol)),0)>MaxLeverage,"⚠ BREACH","✓ OK")) -> ⚠ EBITDA NIL | G17: =IF((INDEX('2_Operating_Statement'!C33:N33,1,LatestAudCol)+INDEX('2_Operating_Statement'!C24:N24,1,LatestAudCol))<=0,"EBITDA negative or zero — Debt/EBITDA undefined. Operations not generating cash to service debt.",IF(IFERROR(INDEX('3_Balance_Sheet'!C39:N39,1,LatestAudCol)/(INDEX('2_Operating_Statement'!C33:N33,1,LatestAudCol)+INDEX('2_Operating_Statement'!C24:N24,1,LatestAudCol)),0)>MaxLeverage,"Debt/EBITDA exceeds ceiling. Test covenant compliance; project deleveraging path and FCF coverage.","Leverage manageable.")) -> EBITDA negative or zero — Debt/EBITDA undefined. Operations not generating cash to service debt.
A18: SECTION IV — COVERAGE
A19: 11 | B19: ICR below threshold (Latest Aud) | C19: Op Stmt row 33 (OPBI) ÷ row 37 (Total Interest) | D19: =IFERROR(INDEX('2_Operating_Statement'!C33:N33,1,LatestAudCol)/INDEX('2_Operating_Statement'!C37:N37,1,LatestAudCol),0) -> 0 | E19: ≥ MinICR | F19: =IF(INDEX('2_Operating_Statement'!C37:N37,1,LatestAudCol)<=0,"✓ NO INT",IF(IFERROR(INDEX('2_Operating_Statement'!C33:N33,1,LatestAudCol)/INDEX('2_Operating_Statement'!C37:N37,1,LatestAudCol),0)<MinICR,"⚠ BREACH","✓ OK")) -> ✓ NO INT | G19: =IF(INDEX('2_Operating_Statement'!C37:N37,1,LatestAudCol)<=0,"No interest outgo in latest year — review",IF(IFERROR(INDEX('2_Operating_Statement'!C33:N33,1,LatestAudCol)/INDEX('2_Operating_Statement'!C37:N37,1,LatestAudCol),0)<MinICR,"ICR below minimum — operating profit insufficient to cover interest. Check pricing, debt mix, refinancing options.","ICR acceptable.")) -> No interest outgo in latest year — review
A20: 12 | B20: DSCR breach in any year | C20: DSCR sheet row 17 across all years | D20: =MIN(IF('4_DSCR'!C13:N13>0,'4_DSCR'!C17:N17,99)) -> 99 | E20: ≥ MinDSCR_Any | F20: =IF(MIN(IF('4_DSCR'!C13:N13>0,'4_DSCR'!C17:N17,99))<MinDSCR_Any,"⚠ BREACH","✓ OK") -> ✓ OK | G20: =IF(MIN(IF('4_DSCR'!C13:N13>0,'4_DSCR'!C17:N17,99))<MinDSCR_Any,"DSCR below minimum in at least one year. Identify the year, root cause, and request comfort (sponsor support / DSRA / structured cash flows).","DSCR meets minimum in all years.") -> DSCR meets minimum in all years.
A21: 13 | B21: Average DSCR below threshold | C21: DSCR sheet row 19 | D21: ='4_DSCR'!C19 -> 0 | E21: ≥ MinDSCR_Avg | F21: =IF('4_DSCR'!C19<MinDSCR_Avg,"⚠ BREACH","✓ OK") -> ⚠ BREACH | G21: =IF('4_DSCR'!C19<MinDSCR_Avg,"Average DSCR weak — lifecycle servicing capacity inadequate. Re-examine TL repayment structure and tenor.","Average DSCR meets benchmark.") -> Average DSCR weak — lifecycle servicing capacity inadequate. Re-examine TL repayment structure and tenor.
A22: SECTION V — WORKING CAPITAL & EFFICIENCY
A23: 14 | B23: Inventory days stretching | C23: BS row 73 ÷ Op Stmt row 13 × 365 (Latest vs Prior Aud) | D23: =IFERROR((INDEX('3_Balance_Sheet'!C73:N73,1,LatestAudCol)*365/INDEX('2_Operating_Statement'!C13:N13,1,LatestAudCol))-(INDEX('3_Balance_Sheet'!C73:N73,1,PriorAudCol)*365/INDEX('2_Operating_Statement'!C13:N13,1,PriorAudCol)),0) -> 0 | E23: Δ ≤ 20% rise | F23: =IF(IFERROR(((INDEX('3_Balance_Sheet'!C73:N73,1,LatestAudCol)*365/INDEX('2_Operating_Statement'!C13:N13,1,LatestAudCol))/(INDEX('3_Balance_Sheet'!C73:N73,1,PriorAudCol)*365/INDEX('2_Operating_Statement'!C13:N13,1,PriorAudCol))-1),0)>MaxInvDays,"⚠ BREACH","✓ OK") -> ✓ OK | G23: =IF(IFERROR(((INDEX('3_Balance_Sheet'!C73:N73,1,LatestAudCol)*365/INDEX('2_Operating_Statement'!C13:N13,1,LatestAudCol))/(INDEX('3_Balance_Sheet'!C73:N73,1,PriorAudCol)*365/INDEX('2_Operating_Statement'!C13:N13,1,PriorAudCol))-1),0)>MaxInvDays,"Inventory days stretched materially — could indicate slow-moving stock, obsolescence, or window-dressing of FG. Get age-wise breakup.","Inventory days within tolerance.") -> Inventory days within tolerance.
A24: 15 | B24: DSO stretching | C24: BS rows 59+60 ÷ Op Stmt row 10 × 365 | D24: =IFERROR(((INDEX('3_Balance_Sheet'!C59:N59,1,LatestAudCol)+INDEX('3_Balance_Sheet'!C60:N60,1,LatestAudCol))/(INDEX('3_Balance_Sheet'!C59:N59,1,PriorAudCol)+INDEX('3_Balance_Sheet'!C60:N60,1,PriorAudCol))*INDEX('2_Operating_Statement'!C10:N10,1,PriorAudCol)/INDEX('2_Operating_Statement'!C10:N10,1,LatestAudCol))-1,0) -> 0 | E24: Δ ≤ MaxDSOIncrease | F24: =IF(IFERROR(((INDEX('3_Balance_Sheet'!C59:N59,1,LatestAudCol)+INDEX('3_Balance_Sheet'!C60:N60,1,LatestAudCol))/(INDEX('3_Balance_Sheet'!C59:N59,1,PriorAudCol)+INDEX('3_Balance_Sheet'!C60:N60,1,PriorAudCol))*INDEX('2_Operating_Statement'!C10:N10,1,PriorAudCol)/INDEX('2_Operating_Statement'!C10:N10,1,LatestAudCol))-1,0)>MaxDSOIncrease,"⚠ BREACH","✓ OK") -> ✓ OK | G24: =IF(IFERROR(((INDEX('3_Balance_Sheet'!C59:N59,1,LatestAudCol)+INDEX('3_Balance_Sheet'!C60:N60,1,LatestAudCol))/(INDEX('3_Balance_Sheet'!C59:N59,1,PriorAudCol)+INDEX('3_Balance_Sheet'!C60:N60,1,PriorAudCol))*INDEX('2_Operating_Statement'!C10:N10,1,PriorAudCol)/INDEX('2_Operating_Statement'!C10:N10,1,LatestAudCol))-1,0)>MaxDSOIncrease,"Debtors stretched — request ageing analysis (>90 days, >180 days). Check for related-party concentration and customer credit policy change.","Receivables management healthy.") -> Receivables management healthy.
A25: 16 | B25: DPO stretching (creditor squeeze) | C25: BS rows 14+15 ÷ Purchases × 365 | D25: =IFERROR(((INDEX('3_Balance_Sheet'!C14:N14,1,LatestAudCol)+INDEX('3_Balance_Sheet'!C15:N15,1,LatestAudCol))/(INDEX('3_Balance_Sheet'!C14:N14,1,PriorAudCol)+INDEX('3_Balance_Sheet'!C15:N15,1,PriorAudCol))*(INDEX('2_Operating_Statement'!C17:N17,1,PriorAudCol)+INDEX('2_Operating_Statement'!C20:N20,1,PriorAudCol))/(INDEX('2_Operating_Statement'!C17:N17,1,LatestAudCol)+INDEX('2_Operating_Statement'!C20:N20,1,LatestAudCol)))-1,0) -> 0 | E25: Δ ≤ MaxDPOStretch | F25: =IF(IFERROR(((INDEX('3_Balance_Sheet'!C14:N14,1,LatestAudCol)+INDEX('3_Balance_Sheet'!C15:N15,1,LatestAudCol))/(INDEX('3_Balance_Sheet'!C14:N14,1,PriorAudCol)+INDEX('3_Balance_Sheet'!C15:N15,1,PriorAudCol))*(INDEX('2_Operating_Statement'!C17:N17,1,PriorAudCol)+INDEX('2_Operating_Statement'!C20:N20,1,PriorAudCol))/(INDEX('2_Operating_Statement'!C17:N17,1,LatestAudCol)+INDEX('2_Operating_Statement'!C20:N20,1,LatestAudCol)))-1,0)>MaxDPOStretch,"⚠ BREACH","✓ OK") -> ✓ OK | G25: =IF(IFERROR(((INDEX('3_Balance_Sheet'!C14:N14,1,LatestAudCol)+INDEX('3_Balance_Sheet'!C15:N15,1,LatestAudCol))/(INDEX('3_Balance_Sheet'!C14:N14,1,PriorAudCol)+INDEX('3_Balance_Sheet'!C15:N15,1,PriorAudCol))*(INDEX('2_Operating_Statement'!C17:N17,1,PriorAudCol)+INDEX('2_Operating_Statement'!C20:N20,1,PriorAudCol))/(INDEX('2_Operating_Statement'!C17:N17,1,LatestAudCol)+INDEX('2_Operating_Statement'!C20:N20,1,LatestAudCol)))-1,0)>MaxDPOStretch,"DPO stretched — indicates supplier credit being relied on. Verify supplier dispute / ageing payables / withholding from disputed creditors.","Payables behaviour stable.") -> Payables behaviour stable.
A26: 17 | B26: STBB > 70% of TCL (over-reliance on bank borrowing) | C26: BS row 11 (STBB) ÷ row 27 (TCL) | D26: =IFERROR(INDEX('3_Balance_Sheet'!C11:N11,1,LatestAudCol)/INDEX('3_Balance_Sheet'!C27:N27,1,LatestAudCol),0) -> 0 | E26: ≤ 70% | F26: =IF(IFERROR(INDEX('3_Balance_Sheet'!C11:N11,1,LatestAudCol)/INDEX('3_Balance_Sheet'!C27:N27,1,LatestAudCol),0)>0.7,"⚠ BREACH","✓ OK") -> ✓ OK | G26: =IF(IFERROR(INDEX('3_Balance_Sheet'!C11:N11,1,LatestAudCol)/INDEX('3_Balance_Sheet'!C27:N27,1,LatestAudCol),0)>0.7,"Borrower over-reliant on bank credit for current liabilities. Check trade credit terms / efforts to extend supplier credit.","Mix of CL is balanced.") -> Mix of CL is balanced.
A27: SECTION VI — CAPEX & FUNDS FLOW DIVERSION
A28: 18 | B28: Capex funded from working capital (CRITICAL) | C28: BS row 84 (Gross Block) Δ vs (TNW Δ + TTL Δ) | D28: =IFERROR((INDEX('3_Balance_Sheet'!C84:N84,1,LatestAudCol)-INDEX('3_Balance_Sheet'!C84:N84,1,PriorAudCol))/MAX(0.01,(INDEX('3_Balance_Sheet'!C52:N52,1,LatestAudCol)-INDEX('3_Balance_Sheet'!C52:N52,1,PriorAudCol))+(INDEX('3_Balance_Sheet'!C39:N39,1,LatestAudCol)-INDEX('3_Balance_Sheet'!C39:N39,1,PriorAudCol))),0) -> 0 | E28: ≤ 1.0x | F28: =IF((INDEX('3_Balance_Sheet'!C84:N84,1,LatestAudCol)-INDEX('3_Balance_Sheet'!C84:N84,1,PriorAudCol))<0.5,"✓ NO CAPEX",IF(IFERROR((INDEX('3_Balance_Sheet'!C84:N84,1,LatestAudCol)-INDEX('3_Balance_Sheet'!C84:N84,1,PriorAudCol))/MAX(0.01,(INDEX('3_Balance_Sheet'!C52:N52,1,LatestAudCol)-INDEX('3_Balance_Sheet'!C52:N52,1,PriorAudCol))+(INDEX('3_Balance_Sheet'!C39:N39,1,LatestAudCol)-INDEX('3_Balance_Sheet'!C39:N39,1,PriorAudCol))),0)>1,"⚠ DIVERSION","✓ OK")) -> ✓ NO CAPEX | G28: =IF((INDEX('3_Balance_Sheet'!C84:N84,1,LatestAudCol)-INDEX('3_Balance_Sheet'!C84:N84,1,PriorAudCol))<0.5,"No material capex in latest year.",IF(IFERROR((INDEX('3_Balance_Sheet'!C84:N84,1,LatestAudCol)-INDEX('3_Balance_Sheet'!C84:N84,1,PriorAudCol))/MAX(0.01,(INDEX('3_Balance_Sheet'!C52:N52,1,LatestAudCol)-INDEX('3_Balance_Sheet'!C52:N52,1,PriorAudCol))+(INDEX('3_Balance_Sheet'!C39:N39,1,LatestAudCol)-INDEX('3_Balance_Sheet'!C39:N39,1,PriorAudCol))),0)>1,"Gross Block addition exceeds long-term-funds raised — capex appears funded from working capital. CRITICAL: quantify diversion, examine end-use compliance, freeze further drawals if confirmed.","Capex matches with LT funds.")) -> No material capex in latest year.
A29: 19 | B29: Capital withdrawal (TNW reduction without losses) | C29: BS row 52 (TNW) Δ vs Op Stmt row 60 (Retained Profit) | D29: =(INDEX('3_Balance_Sheet'!C52:N52,1,LatestAudCol)-INDEX('3_Balance_Sheet'!C52:N52,1,PriorAudCol))-INDEX('2_Operating_Statement'!C60:N60,1,LatestAudCol) -> 0 | E29: ≥ -1.0 | F29: =IF((INDEX('3_Balance_Sheet'!C52:N52,1,LatestAudCol)-INDEX('3_Balance_Sheet'!C52:N52,1,PriorAudCol))-INDEX('2_Operating_Statement'!C60:N60,1,LatestAudCol)<-1,"⚠ WITHDRAWAL","✓ OK") -> ✓ OK | G29: =IF((INDEX('3_Balance_Sheet'!C52:N52,1,LatestAudCol)-INDEX('3_Balance_Sheet'!C52:N52,1,PriorAudCol))-INDEX('2_Operating_Statement'!C60:N60,1,LatestAudCol)<-1,"TNW change ≠ Retained Profit. Possible capital withdrawal or buyback. Quantify and seek explanation. RBI / bank policy may require this to be disallowed.","No anomalous TNW reduction.") -> No anomalous TNW reduction.
A30: 20 | B30: Surge in unsecured loans (related-party diversion?) | C30: BS rows 34+35 (Unsecured Loans) Δ | D30: =IFERROR(((INDEX('3_Balance_Sheet'!C34:N34,1,LatestAudCol)+INDEX('3_Balance_Sheet'!C35:N35,1,LatestAudCol))/(INDEX('3_Balance_Sheet'!C34:N34,1,PriorAudCol)+INDEX('3_Balance_Sheet'!C35:N35,1,PriorAudCol)))-1,0) -> 0 | E30: Δ ≤ 100% | F30: =IF((INDEX('3_Balance_Sheet'!C34:N34,1,PriorAudCol)+INDEX('3_Balance_Sheet'!C35:N35,1,PriorAudCol))<0.5,"✓ NEGLIGIBLE",IF(IFERROR(((INDEX('3_Balance_Sheet'!C34:N34,1,LatestAudCol)+INDEX('3_Balance_Sheet'!C35:N35,1,LatestAudCol))/(INDEX('3_Balance_Sheet'!C34:N34,1,PriorAudCol)+INDEX('3_Balance_Sheet'!C35:N35,1,PriorAudCol)))-1,0)>1,"⚠ SURGE","✓ OK")) -> ✓ NEGLIGIBLE | G30: =IF((INDEX('3_Balance_Sheet'!C34:N34,1,PriorAudCol)+INDEX('3_Balance_Sheet'!C35:N35,1,PriorAudCol))<0.5,"Negligible USL outstanding in prior year.",IF(IFERROR(((INDEX('3_Balance_Sheet'!C34:N34,1,LatestAudCol)+INDEX('3_Balance_Sheet'!C35:N35,1,LatestAudCol))/(INDEX('3_Balance_Sheet'!C34:N34,1,PriorAudCol)+INDEX('3_Balance_Sheet'!C35:N35,1,PriorAudCol)))-1,0)>1,"USLs (esp. from promoters/group cos) doubled or more YoY. Could indicate (a) propping up TNW for ratios, (b) related-party fund routing, or (c) genuine equity-like infusion. Probe and convert to subordinated debt if continuing.","USL movement within tolerance.")) -> Negligible USL outstanding in prior year.
A31: SECTION VII — CONTINGENT & OFF-BS EXPOSURES
A32: 21 | B32: Corporate Guarantees > 50% of TNW | C32: BS row 41 ÷ row 52 | D32: =IFERROR(INDEX('3_Balance_Sheet'!C41:N41,1,LatestAudCol)/INDEX('3_Balance_Sheet'!C52:N52,1,LatestAudCol),0) -> 0 | E32: ≤ 50% | F32: =IF(IFERROR(INDEX('3_Balance_Sheet'!C41:N41,1,LatestAudCol)/INDEX('3_Balance_Sheet'!C52:N52,1,LatestAudCol),0)>0.5,"⚠ HIGH","✓ OK") -> ✓ OK | G32: =IF(INDEX('3_Balance_Sheet'!C41:N41,1,LatestAudCol)<=0,"No corporate guarantees disclosed.",IF(IFERROR(INDEX('3_Balance_Sheet'!C41:N41,1,LatestAudCol)/INDEX('3_Balance_Sheet'!C52:N52,1,LatestAudCol),0)>0.5,"Off-BS exposure via group CGs is significant. Map to specific group entities and assess their standalone credit quality. Risk of devolvement.","Corporate guarantee exposure manageable.")) -> No corporate guarantees disclosed.
A33: 22 | B33: Investments in Group Cos > 25% of TNW | C33: BS row 89 ÷ row 52 | D33: =IFERROR(INDEX('3_Balance_Sheet'!C89:N89,1,LatestAudCol)/INDEX('3_Balance_Sheet'!C52:N52,1,LatestAudCol),0) -> 0 | E33: ≤ 25% | F33: =IF(IFERROR(INDEX('3_Balance_Sheet'!C89:N89,1,LatestAudCol)/INDEX('3_Balance_Sheet'!C52:N52,1,LatestAudCol),0)>0.25,"⚠ HIGH","✓ OK") -> ✓ OK | G33: =IF(INDEX('3_Balance_Sheet'!C89:N89,1,LatestAudCol)<=0,"No group company investments.",IF(IFERROR(INDEX('3_Balance_Sheet'!C89:N89,1,LatestAudCol)/INDEX('3_Balance_Sheet'!C52:N52,1,LatestAudCol),0)>0.25,"Material capital tied up in group co investments. Examine purpose, dividend yield, and exit option. Could be implicit support to weaker group companies.","Group investments within tolerance.")) -> No group company investments.
A34: 23 | B34: Loans/Advances to group/directors > 10% of TNW | C34: BS rows 95+97+98 ÷ row 52 | D34: =IFERROR((INDEX('3_Balance_Sheet'!C95:N95,1,LatestAudCol)+INDEX('3_Balance_Sheet'!C97:N97,1,LatestAudCol)+INDEX('3_Balance_Sheet'!C98:N98,1,LatestAudCol))/INDEX('3_Balance_Sheet'!C52:N52,1,LatestAudCol),0) -> 0 | E34: ≤ 10% | F34: =IF(IFERROR((INDEX('3_Balance_Sheet'!C95:N95,1,LatestAudCol)+INDEX('3_Balance_Sheet'!C97:N97,1,LatestAudCol)+INDEX('3_Balance_Sheet'!C98:N98,1,LatestAudCol))/INDEX('3_Balance_Sheet'!C52:N52,1,LatestAudCol),0)>0.1,"⚠ HIGH","✓ OK") -> ✓ OK | G34: =IF((INDEX('3_Balance_Sheet'!C95:N95,1,LatestAudCol)+INDEX('3_Balance_Sheet'!C97:N97,1,LatestAudCol)+INDEX('3_Balance_Sheet'!C98:N98,1,LatestAudCol))<=0,"No related-party loans/advances.",IF(IFERROR((INDEX('3_Balance_Sheet'!C95:N95,1,LatestAudCol)+INDEX('3_Balance_Sheet'!C97:N97,1,LatestAudCol)+INDEX('3_Balance_Sheet'!C98:N98,1,LatestAudCol))/INDEX('3_Balance_Sheet'!C52:N52,1,LatestAudCol),0)>0.1,"Sizeable related-party advances. Possible diversion. Get specific list, interest rate, and recoverability assessment.","Related-party advances minimal.")) -> No related-party loans/advances.
A35: SECTION VIII — TANDON-II NORMS
A36: 24 | B36: ABF > 75% of TCA (over-banked) | C36: WC sheet row 12 ÷ row 7 | D36: =IFERROR(INDEX('6_Working_Capital'!C12:N12,1,LatestAudCol)/INDEX('6_Working_Capital'!C7:N7,1,LatestAudCol),0) -> 0 | E36: ≤ 75% | F36: =IF(IFERROR(INDEX('6_Working_Capital'!C12:N12,1,LatestAudCol)/INDEX('6_Working_Capital'!C7:N7,1,LatestAudCol),0)>0.75,"⚠ HIGH","✓ OK") -> ✓ OK | G36: =IF(IFERROR(INDEX('6_Working_Capital'!C12:N12,1,LatestAudCol)/INDEX('6_Working_Capital'!C7:N7,1,LatestAudCol),0)>0.75,"ABF as % of TCA suggests over-reliance on bank finance for WC. Test if borrower can sustain operating cycle with reduced bank dependence.","WC funding mix balanced.") -> WC funding mix balanced.
A37: 25 | B37: NWC < 25% of TCA (Tandon norm breach) | C37: WC sheet row 11 ÷ row 7 | D37: =IFERROR(INDEX('6_Working_Capital'!C11:N11,1,LatestAudCol)/INDEX('6_Working_Capital'!C7:N7,1,LatestAudCol),0) -> 0 | E37: ≥ 25% | F37: =IF(IFERROR(INDEX('6_Working_Capital'!C11:N11,1,LatestAudCol)/INDEX('6_Working_Capital'!C7:N7,1,LatestAudCol),0)<0.25,"⚠ BREACH","✓ OK") -> ⚠ BREACH | G37: =IF(IFERROR(INDEX('6_Working_Capital'!C11:N11,1,LatestAudCol)/INDEX('6_Working_Capital'!C7:N7,1,LatestAudCol),0)<0.25,"NWC below 25% of TCA — Tandon II norm breach. Borrower has insufficient margin contribution to WC. Require fresh equity / promoter contribution.","NWC margin meets Tandon norm.") -> NWC below 25% of TCA — Tandon II norm breach. Borrower has insufficient margin contribution to WC. Require fresh equity / promoter contribution.
A38: SECTION IX — DIRECTIONAL TESTS
A39: 26 | B39: Receivables > 6 months age (BS row 96) | C39: BS row 96 ÷ row 82 (TCA) | D39: =IFERROR(INDEX('3_Balance_Sheet'!C96:N96,1,LatestAudCol)/INDEX('3_Balance_Sheet'!C82:N82,1,LatestAudCol),0) -> 0 | E39: ≤ 5% | F39: =IF(IFERROR(INDEX('3_Balance_Sheet'!C96:N96,1,LatestAudCol)/INDEX('3_Balance_Sheet'!C82:N82,1,LatestAudCol),0)>0.05,"⚠ HIGH","✓ OK") -> ✓ OK | G39: =IF(INDEX('3_Balance_Sheet'!C96:N96,1,LatestAudCol)<=0,"No receivables aged >6 months.",IF(IFERROR(INDEX('3_Balance_Sheet'!C96:N96,1,LatestAudCol)/INDEX('3_Balance_Sheet'!C82:N82,1,LatestAudCol),0)>0.05,"Material receivables aged over 6 months. Likely needs provisioning. Get age-wise receivable list and recovery action plan.","Aged receivables within tolerance.")) -> No receivables aged >6 months.
A40: 27 | B40: Provision for taxation negative or zero in profitable year | C40: BS row 17 (Provision) vs Op Stmt row 54 (PBT) | D40: =INDEX('3_Balance_Sheet'!C17:N17,1,LatestAudCol) -> 0 | E40: Should be > 0 if PBT > 0 | F40: =IF(AND(INDEX('2_Operating_Statement'!C54:N54,1,LatestAudCol)>1,INDEX('3_Balance_Sheet'!C17:N17,1,LatestAudCol)<=0),"⚠ ANOMALY","✓ OK") -> ✓ OK | G40: =IF(AND(INDEX('2_Operating_Statement'!C54:N54,1,LatestAudCol)>1,INDEX('3_Balance_Sheet'!C17:N17,1,LatestAudCol)<=0),"Profitable year but no tax provision shown. Check if MAT/AMT applicable, b/f losses, or under-provisioning.","Tax provisioning consistent with PBT.") -> Tax provisioning consistent with PBT.
A41: 28 | B41: Cash & equivalents very low (< 1% of net sales) | C41: BS rows 55+57 ÷ Op Stmt row 13 | D41: =IFERROR((INDEX('3_Balance_Sheet'!C55:N55,1,LatestAudCol)+INDEX('3_Balance_Sheet'!C57:N57,1,LatestAudCol))/INDEX('2_Operating_Statement'!C13:N13,1,LatestAudCol),0) -> 0 | E41: ≥ 1% | F41: =IF(IFERROR((INDEX('3_Balance_Sheet'!C55:N55,1,LatestAudCol)+INDEX('3_Balance_Sheet'!C57:N57,1,LatestAudCol))/INDEX('2_Operating_Statement'!C13:N13,1,LatestAudCol),0)<0.01,"⚠ LOW","✓ OK") -> ⚠ LOW | G41: =IF(IFERROR((INDEX('3_Balance_Sheet'!C55:N55,1,LatestAudCol)+INDEX('3_Balance_Sheet'!C57:N57,1,LatestAudCol))/INDEX('2_Operating_Statement'!C13:N13,1,LatestAudCol),0)<0.01,"Cash buffer is very thin (<1% of revenue). Borrower may rely heavily on rolling drawdowns. Stress-test for any liquidity disruption.","Cash buffer adequate.") -> Cash buffer is very thin (<1% of revenue). Borrower may rely heavily on rolling drawdowns. Stress-test for any liquidity disruption.
A42: SECTION X — ASSET QUALITY & TL COVERAGE
A43: 29 | B43: Net Block / Gross Block < 30% (asset over-aged) | C43: BS row 87 (Net Block) ÷ row 84 (Gross Block) | D43: =IFERROR(INDEX('3_Balance_Sheet'!C87:N87,1,LatestAudCol)/INDEX('3_Balance_Sheet'!C84:N84,1,LatestAudCol),0) -> 0 | E43: ≥ 30% | F43: =IF(INDEX('3_Balance_Sheet'!C84:N84,1,LatestAudCol)<=0,"✓ N/A",IF(IFERROR(INDEX('3_Balance_Sheet'!C87:N87,1,LatestAudCol)/INDEX('3_Balance_Sheet'!C84:N84,1,LatestAudCol),0)<0.3,"⚠ AGED","✓ OK")) -> ✓ N/A | G43: =IF(INDEX('3_Balance_Sheet'!C84:N84,1,LatestAudCol)<=0,"No fixed assets.",IF(IFERROR(INDEX('3_Balance_Sheet'!C87:N87,1,LatestAudCol)/INDEX('3_Balance_Sheet'!C84:N84,1,LatestAudCol),0)<0.3,"Net Block to Gross Block ratio low — assets are heavily depreciated. Anticipate near-term replacement capex; confirm sinking fund / TL plan.","Asset base reasonably young.")) -> No fixed assets.
A44: 30 | B44: FACR (Asset coverage) for Term Loans | C44: BS row 87 ÷ row 39 (TTL) | D44: =IFERROR(INDEX('3_Balance_Sheet'!C87:N87,1,LatestAudCol)/INDEX('3_Balance_Sheet'!C39:N39,1,LatestAudCol),0) -> 0 | E44: ≥ MinFACR | F44: =IF(INDEX('3_Balance_Sheet'!C39:N39,1,LatestAudCol)<=0,"✓ NO TL",IF(IFERROR(INDEX('3_Balance_Sheet'!C87:N87,1,LatestAudCol)/INDEX('3_Balance_Sheet'!C39:N39,1,LatestAudCol),0)<MinFACR,"⚠ BREACH","✓ OK")) -> ✓ NO TL | G44: =IF(INDEX('3_Balance_Sheet'!C39:N39,1,LatestAudCol)<=0,"No long-term debt outstanding.",IF(IFERROR(INDEX('3_Balance_Sheet'!C87:N87,1,LatestAudCol)/INDEX('3_Balance_Sheet'!C39:N39,1,LatestAudCol),0)<MinFACR,"FACR below threshold. Asset coverage for term loans inadequate. Either accelerate repayment or seek additional collateral.","Asset cover for TL adequate.")) -> No long-term debt outstanding.
A46: SECTION XI — REGULATORY OVERLAYS
A47: 31 | B47: Project Finance Capital & Provisioning Strain | C47: Setup Section 7 (PF Type, Phase, Sector) | D47: =IF(ProjectFinance="Yes",IF(ProjectPhase="Under-Construction",IF(ProjectSector="Commercial Real Estate",1.25,1),0),0) -> 0 | E47: 0.40% (standard) | F47: =IF(AND(ProjectFinance="Yes",ProjectPhase="Under-Construction",OR(ProjectSector="Infrastructure",ProjectSector="Commercial Real Estate")),"⚠ REG REQUIREMENT","✓ N/A") -> ✓ N/A | G47: =IF(AND(ProjectFinance="Yes",ProjectPhase="Under-Construction",ProjectSector="Commercial Real Estate"),"Standard asset provisioning at elevated 1.25% for under-construction CRE (RBI Project Finance Directions 2025). Ensure pricing fully incorporates increased capital consumption + step-ups for DCCO delays.",IF(AND(ProjectFinance="Yes",ProjectPhase="Under-Construction",ProjectSector="Infrastructure"),"Standard asset provisioning at elevated 1.00% for under-construction infrastructure projects. Provisioning steps up if DCCO is delayed. Verify pricing matrix incorporates increased capital cost.","Not a project finance facility OR project is operational. Standard 0.40% provisioning applies.")) -> Not a project finance facility OR project is operational. Standard 0.40% provisioning applies.
A48: 32 | B48: DSCR Suppression — Project Finance Construction Phase | C48: DCCO_Year vs Year Index (suppress alerts pre-DCCO) | D48: =IF(AND(ProjectFinance="Yes",ProjectPhase="Under-Construction"),IF(DCCO_Year="","DCCO Not Set",DCCO_Year-FirstFY),"N/A") -> N/A | E48: Active post-DCCO only | F48: =IF(AND(ProjectFinance="Yes",ProjectPhase="Under-Construction"),"⚠ INFO","✓ N/A") -> ✓ N/A | G48: =IF(AND(ProjectFinance="Yes",ProjectPhase="Under-Construction"),"Greenfield projects have zero cash flows during construction. DSCR breach alerts (Test 12, 13) are advisory only during construction phase. Activate covenant from DCCO year onwards. Validate via Construction Period Interest moratorium / DSRA arrangement.","Project is operational or not a project finance facility — standard DSCR covenants apply.") -> Project is operational or not a project finance facility — standard DSCR covenants apply.
A50: OVERALL RED FLAG SUMMARY
B51: Total Red Flags Triggered: | D51: =COUNTIF(F6:F48,"⚠*") -> 7
B52: Total Tests Passed: | D52: =COUNTIF(F6:F48,"✓*") -> 25
B53: Overall Risk Score (out of 32): | D53: =32-COUNTIF(F6:F48,"⚠*") -> 25
B54: Verdict: | D54: =IF(COUNTIF(F6:F48,"⚠*")=0,"NO MATERIAL RED FLAGS",IF(COUNTIF(F6:F48,"⚠*")<=3,"MINOR CONCERNS — ADDRESS IN COVENANTS",IF(COUNTIF(F6:F48,"⚠*")<=7,"MULTIPLE CONCERNS — DEEP DIVE NEEDED","MATERIAL CREDIT CONCERNS — RECONSIDER PROPOSAL"))) -> MULTIPLE CONCERNS — DEEP DIVE NEEDED

Sheet 12B_Exception_Engine
A1: ADVANCED EXCEPTION ENGINE | 13 Deep-Diagnostic Risk Tests (Supplement to 12_Red_Flags)
A2: =IF(BorrowerName="","Borrower: [Not Set]","Borrower: "&BorrowerName)&" | Each test includes: risk explanation, probable cause, banker action" -> Borrower: [Not Set] | Each test includes: risk explanation, probable cause, banker action
B3: Exception Test | C3: Computed Value | D3: Threshold | E3: Status | F3: Risk Explanation & Probable Cause | G3: Banker Action / Verification
B4: 1. Sudden Receivable Spike | C4: =IFERROR(IF((INDEX('3_Balance_Sheet'!C59:N59,1,PriorAudCol)+INDEX('3_Balance_Sheet'!C60:N60,1,PriorAudCol))>0,((INDEX('3_Balance_Sheet'!C59:N59,1,LatestAudCol)+INDEX('3_Balance_Sheet'!C60:N60,1,LatestAudCol))/(INDEX('3_Balance_Sheet'!C59:N59,1,PriorAudCol)+INDEX('3_Balance_Sheet'!C60:N60,1,PriorAudCol)))-1,0),0) -> 0 | D4: > 50% with sales < 20% | E4: — | F4: "Receivables grew >50% while sales grew <20%. Possible channel stuffing, inflated debtors, or collection failure. Classic NPA precursor." | G4: "Verify debtor ageing schedule. Cross-check with GST sales register. Request top-10 debtor list + overdue status."
B6: 2. Inventory vs Sales Mismatch | C6: =IFERROR(IF(INDEX('2_Operating_Statement'!C13:N13,1,PriorAudCol)>0,(INDEX('3_Balance_Sheet'!C73:N73,1,LatestAudCol)/INDEX('3_Balance_Sheet'!C73:N73,1,PriorAudCol)-1)/(INDEX('2_Operating_Statement'!C13:N13,1,LatestAudCol)/INDEX('2_Operating_Statement'!C13:N13,1,PriorAudCol)-1+0.001),0),0) -> 0 | D6: < 2x (Inv growth : Sales growth) | E6: =IFERROR(IF(AND(INDEX('3_Balance_Sheet'!C73:N73,1,PriorAudCol)>0,INDEX('2_Operating_Statement'!C13:N13,1,PriorAudCol)>0,(INDEX('3_Balance_Sheet'!C73:N73,1,LatestAudCol)/INDEX('3_Balance_Sheet'!C73:N73,1,PriorAudCol)-1)>2*(INDEX('2_Operating_Statement'!C13:N13,1,LatestAudCol)/INDEX('2_Operating_Statement'!C13:N13,1,PriorAudCol)-1+0.001)),"⚠ MISMATCH","✓ OK"),"—") -> — | F6: "Inventory growing faster than 2× sales — suggests slow-moving stock, demand fall, or inventory inflation for drawing power manipulation." | G6: "Inspect stock statements, movement registers, stock audit report. Check if valuation basis has changed."
B8: 3. Earnings Quality — PAT+ve but NWC Eroding | C8: =IFERROR(INDEX('2_Operating_Statement'!C58:N58,1,LatestAudCol),0) -> 0 | D8: PAT > 0 requires NWC stable | E8: ✓ OK | F8: "PAT is positive but NWC is severely negative — profits are not cash-backed. May indicate accrual-based income, delayed receivable collection, or rising short-term obligations." | G8: "Request cash flow statement. Reconcile PAT to operating cash flows. Check for large creditor increases or deferred payments."
B10: 4. EBITDA Growth Without Sales Growth | C10: =IFERROR(IF((INDEX('2_Operating_Statement'!C33:N33,1,PriorAudCol)+INDEX('2_Operating_Statement'!C24:N24,1,PriorAudCol))>0,(INDEX('2_Operating_Statement'!C33:N33,1,LatestAudCol)+INDEX('2_Operating_Statement'!C24:N24,1,LatestAudCol))/(INDEX('2_Operating_Statement'!C33:N33,1,PriorAudCol)+INDEX('2_Operating_Statement'!C24:N24,1,PriorAudCol))-1,0),0) -> 0 | D10: Not > +10% when sales growth < 0% | E10: — | F10: "EBITDA improved >10% while revenue fell — could indicate cost-cutting (positive) OR one-time income, accounting reclassification, or capitalization of costs (negative)." | G10: "Analyse cost structure changes YoY. Check for cost deferrals, depreciation policy changes, or extraordinary items inflating EBITDA."
B12: 5. Aggressive Leverage Jump | C12: =IFERROR(IF(INDEX('3_Balance_Sheet'!C39:N39,1,PriorAudCol)>0,INDEX('3_Balance_Sheet'!C39:N39,1,LatestAudCol)/INDEX('3_Balance_Sheet'!C39:N39,1,PriorAudCol)-1,IF(INDEX('3_Balance_Sheet'!C39:N39,1,LatestAudCol)>0,1,0)),0) -> 0 | D12: ≤ 50% single-year increase | E12: =IFERROR(IF(AND(INDEX('3_Balance_Sheet'!C39:N39,1,PriorAudCol)>0,INDEX('3_Balance_Sheet'!C39:N39,1,LatestAudCol)/INDEX('3_Balance_Sheet'!C39:N39,1,PriorAudCol)-1>0.5),"⚠ LEVERAGE SURGE","✓ OK"),"—") -> — | F12: "Term debt grew >50% in one year. Rapid leverage build-up strains future DSCR, especially if EBITDA growth doesn't match." | G12: "Verify purpose of new TL — capex plan, refinancing, or group diversion. Ensure DSCR projections remain adequate with new debt level."
B14: 6. STBB Funding Long-Term Assets (Diversion) | C14: =IFERROR(INDEX('3_Balance_Sheet'!C11:N11,1,LatestAudCol)/IF(INDEX('3_Balance_Sheet'!C82:N82,1,LatestAudCol)=0,1,INDEX('3_Balance_Sheet'!C82:N82,1,LatestAudCol)),0) -> 0 | D14: STBB ≤ 60% of TCA (not funding FA) | E14: =IFERROR(IF(INDEX('3_Balance_Sheet'!C11:N11,1,LatestAudCol)>0.6*INDEX('3_Balance_Sheet'!C82:N82,1,LatestAudCol),"⚠ POSSIBLE DIVERSION","✓ OK"),"—") -> ✓ OK | F14: "Short-term bank borrowings are disproportionately high relative to current assets — suggests WC limits funding capex or long-term assets (diversion from intended purpose)." | G14: "Cross-check fixed asset additions vs long-term funds raised. Request purpose-wise utilisation certificate. Fund-flow analysis."
B16: 7. Old Receivable Concentration (>6 Months) | C16: =IFERROR(IF((INDEX('3_Balance_Sheet'!C59:N59,1,LatestAudCol)+INDEX('3_Balance_Sheet'!C60:N60,1,LatestAudCol))>0,INDEX('3_Balance_Sheet'!C96:N96,1,LatestAudCol)/(INDEX('3_Balance_Sheet'!C59:N59,1,LatestAudCol)+INDEX('3_Balance_Sheet'!C60:N60,1,LatestAudCol)),0),0) -> 0 | D16: ≤ 15% of total debtors | E16: =IFERROR(IF(AND((INDEX('3_Balance_Sheet'!C59:N59,1,LatestAudCol)+INDEX('3_Balance_Sheet'!C60:N60,1,LatestAudCol))>0,INDEX('3_Balance_Sheet'!C96:N96,1,LatestAudCol)/(INDEX('3_Balance_Sheet'!C59:N59,1,LatestAudCol)+INDEX('3_Balance_Sheet'!C60:N60,1,LatestAudCol))>0.15),"⚠ STALE DEBTORS","✓ OK"),"—") -> — | F16: "More than 15% of trade receivables are aged beyond 6 months — signals chronic collection weakness or NPA-grade debtors on books." | G16: "Obtain debtor ageing report. Identify top overdue accounts. Verify provisions adequacy. Examine if these are related-party transactions."
B18: 8. Rapid Unsecured Loan Movement | C18: =IFERROR(IF(INDEX('2_Operating_Statement'!C13:N13,1,LatestAudCol)>0,((INDEX('3_Balance_Sheet'!C34:N34,1,LatestAudCol)+INDEX('3_Balance_Sheet'!C35:N35,1,LatestAudCol))-(INDEX('3_Balance_Sheet'!C34:N34,1,PriorAudCol)+INDEX('3_Balance_Sheet'!C35:N35,1,PriorAudCol)))/INDEX('2_Operating_Statement'!C13:N13,1,LatestAudCol),0),0) -> 0 | D18: Δ USL ≤ 10% of Net Sales | E18: — | F18: "Unsecured loans increased by >10% of Net Sales in latest year — signals related-party fund infusion/diversion or promoter siphoning disguised as inter-company loans." | G18: "Demand loan-wise USL schedule with lender/borrower names. Check if USL outflows exceed inflows. Examine for group exposure concentration."
B20: 9. GST/Revenue-Inventory Disconnect | C20: =IFERROR(IF(INDEX('2_Operating_Statement'!C13:N13,1,PriorAudCol)>0,(INDEX('2_Operating_Statement'!C13:N13,1,LatestAudCol)/INDEX('2_Operating_Statement'!C13:N13,1,PriorAudCol))-1,0),0) -> 0 | D20: Sales jump > 30% needs inventory/debtor support | E20: — | F20: "Revenue jumped >30% but inventory+debtors grew <5% — inconsistent for manufacturing/trading businesses. May indicate inflated revenue or under-reporting of debtors." | G20: "Cross-verify revenue with GSTR-3B/GSTR-1 data. Reconcile with Form 26AS TDS receipts. Inspect bank credits vs reported turnover."
B22: 10. Projection CAGR vs Historical CAGR | C22: =IFERROR(INDEX('2_Operating_Statement'!C13:N13,1,LastProjCol)/INDEX('2_Operating_Statement'!C13:N13,1,LatestAudCol),1)^(1/MAX(1,LastProjCol-LatestAudCol))-1 -> 0 | D22: Projected CAGR ≤ 2× historical CAGR | E22: =IFERROR(IF(AND(INDEX('2_Operating_Statement'!C13:N13,1,LastProjCol)>0,INDEX('2_Operating_Statement'!C13:N13,1,LatestAudCol)>0,INDEX('2_Operating_Statement'!C13:N13,1,1)>0,(INDEX('2_Operating_Statement'!C13:N13,1,LastProjCol)/INDEX('2_Operating_Statement'!C13:N13,1,LatestAudCol))^(1/MAX(1,LastProjCol-LatestAudCol))-1>2*((INDEX('2_Operating_Statement'!C13:N13,1,LatestAudCol)/INDEX('2_Operating_Statement'!C13:N13,1,1))^(1/MAX(1,LatestAudCol-1))-1)),"⚠ AGGRESSIVE PROJECTION","✓ REALISTIC"),"—") -> — | F22: "Projected revenue CAGR exceeds 2× the historically achieved CAGR — projections appear optimistic relative to demonstrated growth capacity." | G22: "Challenge assumptions underlying sales projections. Verify order book, capacity utilisation headroom. Request management note on growth drivers."
B24: 11. STBB Replacing Term Debt (Maturity Mismatch) | C24: =IFERROR((INDEX('3_Balance_Sheet'!C11:N11,1,LatestAudCol)-INDEX('3_Balance_Sheet'!C11:N11,1,PriorAudCol))/IF(INDEX('3_Balance_Sheet'!C39:N39,1,PriorAudCol)=0,1,INDEX('3_Balance_Sheet'!C39:N39,1,PriorAudCol)),0) -> 0 | D24: STBB rise should not > TTL fall | E24: =IFERROR(IF(AND(INDEX('3_Balance_Sheet'!C39:N39,1,PriorAudCol)>INDEX('3_Balance_Sheet'!C39:N39,1,LatestAudCol),INDEX('3_Balance_Sheet'!C11:N11,1,LatestAudCol)>INDEX('3_Balance_Sheet'!C11:N11,1,PriorAudCol),(INDEX('3_Balance_Sheet'!C11:N11,1,LatestAudCol)-INDEX('3_Balance_Sheet'!C11:N11,1,PriorAudCol))>(INDEX('3_Balance_Sheet'!C39:N39,1,PriorAudCol)-INDEX('3_Balance_Sheet'!C39:N39,1,LatestAudCol))),"⚠ MATURITY MISMATCH","✓ OK"),"—") -> ✓ OK | F24: "Short-term borrowings increased while term loans declined — borrower may be rolling long-term debt through WC lines (prohibited). Maturity mismatch creates liquidity risk." | G24: "Examine end-use of TL repayments — were proceeds absorbed or recycled? Cross-check WC limit utilisation pattern. Review sanction conditions."
B26: 12. Interest Capitalization Risk | C26: =IFERROR(IF(INDEX('4_DSCR'!C13:N13,1,LatestAudCol)>0,INDEX('2_Operating_Statement'!C35:N35,1,LatestAudCol)/INDEX('4_DSCR'!C13:N13,1,LatestAudCol),0),0) -> 0 | D26: TL Interest / Instalments ≤ 1.5× | E26: =IFERROR(IF(AND(INDEX('4_DSCR'!C13:N13,1,LatestAudCol)>0,INDEX('2_Operating_Statement'!C35:N35,1,LatestAudCol)/INDEX('4_DSCR'!C13:N13,1,LatestAudCol)>1.5),"⚠ INTEREST HEAVY","✓ OK"),"—") -> — | F26: "Interest on term loans far exceeds principal instalments — loan is interest-heavy in current structure. Risk of evergreening: interest kept current while principal is rolled." | G26: "Verify TL amortisation schedule. Check if principal payments are being funded from fresh drawdowns. Review DSCR vs actual repayment record."
B28: 13. Related-Party USL Dependency | C28: =IFERROR(IF(INDEX('3_Balance_Sheet'!C52:N52,1,LatestAudCol)>0,(INDEX('3_Balance_Sheet'!C34:N34,1,LatestAudCol)+INDEX('3_Balance_Sheet'!C35:N35,1,LatestAudCol))/INDEX('3_Balance_Sheet'!C52:N52,1,LatestAudCol),0),0) -> 0 | D28: USL / TNW ≤ 30% | E28: — | F28: "Unsecured loans exceed 30% of Net Worth — high related-party dependency. USL can be called any time, creating sudden liquidity stress, or may represent disguised promoter withdrawal." | G28: "Identify USL lenders — promoters, group companies, or third parties. Confirm subordination to bank debt. Restrict USL repayment via covenant."
B31: EXCEPTION SUMMARY | D31: Tests Flagged | E31: Tests Passed
D32: =COUNTIF(E4:E30,"⚠*") -> 0 | E32: =COUNTIF(E4:E30,"✓*") -> 3

Sheet 13_Auto_Analysis
A1: =CONCATENATE("AUTO-ANALYSIS | For / Against / Mitigants | ", BorrowerName) -> AUTO-ANALYSIS | For / Against / Mitigants |
A2: Themed analysis. Each row tightens to 2-3 lines per cell. Industry context auto-pulled from selected sector outlook.
A4: =CONCATENATE("PROPOSAL: ",ProposalType," | Existing FB: ₹",TEXT(ExistingFB_WC+ExistingFB_TL,"0.00")," Cr | Proposed FB: ₹",TEXT(ProposedFB_WC+ProposedFB_TL,"0.00")," Cr | Industry: ",IndustryName) -> PROPOSAL: | Existing FB: ₹0.00 Cr | Proposed FB: ₹0.00 Cr | Industry:
A6: Theme | B6: Status / Key Metric | C6: FOR (supporting the proposal) | D6: AGAINST (concerns to address) | E6: MITIGANTS (proposed safeguards)
A7: Sales / Revenue Trajectory | B7: =CONCATENATE("Net Sales: ₹",TEXT(INDEX('2_Operating_Statement'!C13:N13,1,LatestAudCol),"0.00")," Cr (Latest Aud); YoY: ",TEXT(IFERROR((INDEX('2_Operating_Statement'!C13:N13,1,LatestAudCol)-INDEX('2_Operating_Statement'!C13:N13,1,PriorAudCol))/INDEX('2_Operating_Statement'!C13:N13,1,PriorAudCol),0),"0.0%")) -> Net Sales: ₹0.00 Cr (Latest Aud); YoY: 0.0% | C7: =IF(IFERROR((INDEX('2_Operating_Statement'!C13:N13,1,LatestAudCol)-INDEX('2_Operating_Statement'!C13:N13,1,PriorAudCol))/INDEX('2_Operating_Statement'!C13:N13,1,PriorAudCol),0)>=0.1,"Healthy double-digit revenue expansion supports debt-servicing capacity and justifies the WC limit. Order book / industry tailwinds are visible.",IF(IFERROR((INDEX('2_Operating_Statement'!C13:N13,1,LatestAudCol)-INDEX('2_Operating_Statement'!C13:N13,1,PriorAudCol))/INDEX('2_Operating_Statement'!C13:N13,1,PriorAudCol),0)>=0,"Modest topline growth indicates business stability. The borrower has weathered macro headwinds without contraction.","No supportive narrative — see Against.")) -> Modest topline growth indicates business stability. The borrower has weathered macro headwinds without contraction. | D7: =IF(IFERROR((INDEX('2_Operating_Statement'!C13:N13,1,LatestAudCol)-INDEX('2_Operating_Statement'!C13:N13,1,PriorAudCol))/INDEX('2_Operating_Statement'!C13:N13,1,PriorAudCol),0)>0.5,"Sales spike >50% YoY is unusual. Verify with GST 3B/9, sales register, e-way bills, and customer concentration. Risk of one-off contracts inflating base.",IF(IFERROR((INDEX('2_Operating_Statement'!C13:N13,1,LatestAudCol)-INDEX('2_Operating_Statement'!C13:N13,1,PriorAudCol))/INDEX('2_Operating_Statement'!C13:N13,1,PriorAudCol),0)<MinSalesGrowth,"Material sales decline signals competitive pressure or volume loss. Examine market share, capacity utilisation, and downside scenarios.","No material concerns on growth trajectory.")) -> No material concerns on growth trajectory. | E7: =IF(IFERROR((INDEX('2_Operating_Statement'!C13:N13,1,LatestAudCol)-INDEX('2_Operating_Statement'!C13:N13,1,PriorAudCol))/INDEX('2_Operating_Statement'!C13:N13,1,PriorAudCol),0)>0.5,"Trigger: 6-monthly sales-vs-projection covenant. Sub-limit on customer concentration. Quarterly stock & receivables statement.",IF(IFERROR((INDEX('2_Operating_Statement'!C13:N13,1,LatestAudCol)-INDEX('2_Operating_Statement'!C13:N13,1,PriorAudCol))/INDEX('2_Operating_Statement'!C13:N13,1,PriorAudCol),0)<MinSalesGrowth,"Sub-limit at 80% of MPBF until trajectory reverses. Half-yearly review. Restrict NFB issuance till H2 of next FY.","Standard quarterly stock & book-debt statements.")) -> Standard quarterly stock & book-debt statements.
A8: Profitability & Margins | B8: =CONCATENATE("OPM: ",TEXT(IFERROR(INDEX('2_Operating_Statement'!C33:N33,1,LatestAudCol)/INDEX('2_Operating_Statement'!C13:N13,1,LatestAudCol),0),"0.0%")," | PAT: ₹",TEXT(INDEX('2_Operating_Statement'!C58:N58,1,LatestAudCol),"0.00")," Cr") -> OPM: 0.0% | PAT: ₹0.00 Cr | C8: =IF(INDEX('2_Operating_Statement'!C58:N58,1,LatestAudCol)>0,CONCATENATE("Profitable in latest year (PAT ₹",TEXT(INDEX('2_Operating_Statement'!C58:N58,1,LatestAudCol),"0.00")," Cr). Operating margin of ",TEXT(IFERROR(INDEX('2_Operating_Statement'!C33:N33,1,LatestAudCol)/INDEX('2_Operating_Statement'!C13:N13,1,LatestAudCol),0),"0.0%")," demonstrates pricing power and cost discipline."),"No supportive narrative — operations are loss-making.") -> No supportive narrative — operations are loss-making. | D8: =IF(INDEX('2_Operating_Statement'!C58:N58,1,LatestAudCol)<=0,"PAT negative in latest audited year. Sustainability of operations questionable. Examine root cause — input costs, demand-supply, capacity utilisation.",IF(IFERROR(INDEX('2_Operating_Statement'!C33:N33,1,LatestAudCol)/INDEX('2_Operating_Statement'!C13:N13,1,LatestAudCol),0)-IFERROR(INDEX('2_Operating_Statement'!C33:N33,1,PriorAudCol)/INDEX('2_Operating_Statement'!C13:N13,1,PriorAudCol),0)<-0.02,"OPM compressed >200 bps YoY. Pressure points likely RM cost / power / labour. Test pass-through ability.","No material profitability concerns.")) -> PAT negative in latest audited year. Sustainability of operations questionable. Examine root cause — input costs, demand-supply, capacity utilisation. | E8: =IF(INDEX('2_Operating_Statement'!C58:N58,1,LatestAudCol)<=0,"Mandatory: monthly MIS (P&L + bank statement); restrict any related-party transactions; freeze further drawals beyond drawing power; consider stress-test pricing.",IF(IFERROR(INDEX('2_Operating_Statement'!C33:N33,1,LatestAudCol)/INDEX('2_Operating_Statement'!C13:N13,1,LatestAudCol),0)-IFERROR(INDEX('2_Operating_Statement'!C33:N33,1,PriorAudCol)/INDEX('2_Operating_Statement'!C13:N13,1,PriorAudCol),0)<-0.02,"Quarterly margin review covenant. Trigger for limit reduction if margin slips further by 100 bps.","Standard monitoring.")) -> Mandatory: monthly MIS (P&L + bank statement); restrict any related-party transactions; freeze further drawals beyond drawing power; consider stress-test pricing.
A9: Leverage / Solvency | B9: =CONCATENATE("TOL/TNW: ",TEXT(IFERROR(INDEX('3_Balance_Sheet'!C40:N40,1,LatestAudCol)/INDEX('3_Balance_Sheet'!C52:N52,1,LatestAudCol),0),"0.00x")," | Debt/EBITDA: ",TEXT(IFERROR(INDEX('3_Balance_Sheet'!C39:N39,1,LatestAudCol)/(INDEX('2_Operating_Statement'!C33:N33,1,LatestAudCol)+INDEX('2_Operating_Statement'!C24:N24,1,LatestAudCol)),0),"0.00x")) -> TOL/TNW: 0.00x | Debt/EBITDA: 0.00x | C9: =IF(AND(IFERROR(INDEX('3_Balance_Sheet'!C40:N40,1,LatestAudCol)/INDEX('3_Balance_Sheet'!C52:N52,1,LatestAudCol),0)<=MaxTOLTNW*0.7,IFERROR(INDEX('3_Balance_Sheet'!C39:N39,1,LatestAudCol)/(INDEX('2_Operating_Statement'!C33:N33,1,LatestAudCol)+INDEX('2_Operating_Statement'!C24:N24,1,LatestAudCol)),0)<=MaxLeverage*0.6),CONCATENATE("Comfortable leverage profile. TOL/TNW at ",TEXT(IFERROR(INDEX('3_Balance_Sheet'!C40:N40,1,LatestAudCol)/INDEX('3_Balance_Sheet'!C52:N52,1,LatestAudCol),0),"0.00x")," provides headroom for the proposed exposure. Borrower has demonstrated capacity to deleverage."),IF(IFERROR(INDEX('3_Balance_Sheet'!C40:N40,1,LatestAudCol)/INDEX('3_Balance_Sheet'!C52:N52,1,LatestAudCol),0)<=MaxTOLTNW,"Leverage within tolerance band. No fresh equity infusion currently required.","No supportive narrative — see Against.")) -> Comfortable leverage profile. TOL/TNW at 0.00x provides headroom for the proposed exposure. Borrower has demonstrated capacity to deleverage. | D9: =IF(INDEX('3_Balance_Sheet'!C52:N52,1,LatestAudCol)<=0,"TNW eroded — solvency at critical level. Cannot absorb the proposed exposure without fresh equity infusion. Material reservation.",IF(IFERROR(INDEX('3_Balance_Sheet'!C40:N40,1,LatestAudCol)/INDEX('3_Balance_Sheet'!C52:N52,1,LatestAudCol),0)>MaxTOLTNW,CONCATENATE("TOL/TNW at ",TEXT(IFERROR(INDEX('3_Balance_Sheet'!C40:N40,1,LatestAudCol)/INDEX('3_Balance_Sheet'!C52:N52,1,LatestAudCol),0),"0.00x")," exceeds policy ceiling of ",TEXT(MaxTOLTNW,"0.00x"),". Quantify deleveraging path. Fresh equity / sub-debt may be needed."),"No leverage concerns.")) -> TNW eroded — solvency at critical level. Cannot absorb the proposed exposure without fresh equity infusion. Material reservation. | E9: =IF(INDEX('3_Balance_Sheet'!C52:N52,1,LatestAudCol)<=0,"Pre-condition: fresh equity infusion of at least the gap. Subordination of all USLs. Half-yearly TNW covenant.",IF(IFERROR(INDEX('3_Balance_Sheet'!C40:N40,1,LatestAudCol)/INDEX('3_Balance_Sheet'!C52:N52,1,LatestAudCol),0)>MaxTOLTNW,"TOL/TNW covenant tightened: must converge to MaxTOLTNW within 18 months. Subordinate all promoter loans. Restrict dividend till compliance.","Standard half-yearly leverage covenant.")) -> Pre-condition: fresh equity infusion of at least the gap. Subordination of all USLs. Half-yearly TNW covenant.
A10: Liquidity & Working Capital | B10: =CONCATENATE("CR: ",TEXT(IFERROR(INDEX('3_Balance_Sheet'!C82:N82,1,LatestAudCol)/INDEX('3_Balance_Sheet'!C27:N27,1,LatestAudCol),0),"0.00")," | NWC: ₹",TEXT(INDEX('3_Balance_Sheet'!C82:N82,1,LatestAudCol)-INDEX('3_Balance_Sheet'!C27:N27,1,LatestAudCol),"0.00")," Cr | ABF: ₹",TEXT(INDEX('6_Working_Capital'!C12:N12,1,LatestAudCol),"0.00")," Cr") -> CR: 0.00 | NWC: ₹0.00 Cr | ABF: ₹0.00 Cr | C10: =IF(AND(IFERROR(INDEX('3_Balance_Sheet'!C82:N82,1,LatestAudCol)/INDEX('3_Balance_Sheet'!C27:N27,1,LatestAudCol),0)>=MinCR,(INDEX('3_Balance_Sheet'!C82:N82,1,LatestAudCol)-INDEX('3_Balance_Sheet'!C27:N27,1,LatestAudCol))>0),"Liquidity profile is sound. CR meets benchmark and NWC is positive — borrower can fund operating cycle without distress.","No supportive narrative — see Against.") -> No supportive narrative — see Against. | D10: =IF(IFERROR(INDEX('3_Balance_Sheet'!C82:N82,1,LatestAudCol)/INDEX('3_Balance_Sheet'!C27:N27,1,LatestAudCol),0)<MinCR,CONCATENATE("CR at ",TEXT(IFERROR(INDEX('3_Balance_Sheet'!C82:N82,1,LatestAudCol)/INDEX('3_Balance_Sheet'!C27:N27,1,LatestAudCol),0),"0.00")," below ",TEXT(MinCR,"0.00"),". Operating cycle stretched. STBB likely funding non-current uses — diversion risk."),IF(INDEX('6_Working_Capital'!C11:N11,1,LatestAudCol)/INDEX('6_Working_Capital'!C7:N7,1,LatestAudCol)<0.25,"NWC margin below Tandon-II 25% norm. Borrower has insufficient long-term contribution to operating cycle.","No liquidity concerns.")) -> CR at 0.00 below 1.17. Operating cycle stretched. STBB likely funding non-current uses — diversion risk. | E10: =IF(IFERROR(INDEX('3_Balance_Sheet'!C82:N82,1,LatestAudCol)/INDEX('3_Balance_Sheet'!C27:N27,1,LatestAudCol),0)<MinCR,"Quarterly stock-statement sub-limit enforcement. DP calculation strict (no relaxation in margins). Restrict adhoc beyond drawing power.",IF(INDEX('6_Working_Capital'!C11:N11,1,LatestAudCol)/INDEX('6_Working_Capital'!C7:N7,1,LatestAudCol)<0.25,"Promoter contribution undertaking before further drawal. Reduce ABF until NWC norm met. Half-yearly compliance.","Standard MSOD / QIS submission.")) -> Quarterly stock-statement sub-limit enforcement. DP calculation strict (no relaxation in margins). Restrict adhoc beyond drawing power.
A11: Coverage / Debt Service | B11: =CONCATENATE("ICR: ",TEXT(IFERROR(INDEX('2_Operating_Statement'!C33:N33,1,LatestAudCol)/INDEX('2_Operating_Statement'!C37:N37,1,LatestAudCol),0),"0.00x")," | Avg DSCR: ",TEXT('4_DSCR'!C19,"0.00x")) -> ICR: 0.00x | Avg DSCR: 0.00x | C11: =IF(AND(IFERROR(INDEX('2_Operating_Statement'!C33:N33,1,LatestAudCol)/INDEX('2_Operating_Statement'!C37:N37,1,LatestAudCol),0)>=MinICR,'4_DSCR'!C19>=MinDSCR_Avg),CONCATENATE("Healthy coverage. ICR at ",TEXT(IFERROR(INDEX('2_Operating_Statement'!C33:N33,1,LatestAudCol)/INDEX('2_Operating_Statement'!C37:N37,1,LatestAudCol),0),"0.00x")," and Avg DSCR at ",TEXT('4_DSCR'!C19,"0.00x")," indicate operations are generating ample cash to service total debt obligations."),"No supportive narrative — see Against.") -> No supportive narrative — see Against. | D11: =IF(INDEX('2_Operating_Statement'!C37:N37,1,LatestAudCol)<=0,"No interest in latest year — review debt mix and tenor.",IF(IFERROR(INDEX('2_Operating_Statement'!C33:N33,1,LatestAudCol)/INDEX('2_Operating_Statement'!C37:N37,1,LatestAudCol),0)<MinICR,"ICR below benchmark — operations not generating sufficient cushion over interest. Risk of default rises in stress scenarios.",IF('4_DSCR'!C19<MinDSCR_Avg,"Average DSCR weak — lifecycle servicing of TL inadequate. Rework repayment structure.","No coverage concerns."))) -> No interest in latest year — review debt mix and tenor. | E11: =IF('4_DSCR'!C19<MinDSCR_Avg,"DSRA equal to 1 quarterly TL instalment. Cash sweep on excess flows. Trigger for review at any DSCR breach.","Standard DSCR covenant in sanction.") -> DSRA equal to 1 quarterly TL instalment. Cash sweep on excess flows. Trigger for review at any DSCR breach.
A12: Capex & Funds Flow Discipline | B12: =CONCATENATE("Capex: ₹",TEXT(INDEX('3_Balance_Sheet'!C84:N84,1,LatestAudCol)-INDEX('3_Balance_Sheet'!C84:N84,1,PriorAudCol),"0.00")," Cr | LT funds raised: ₹",TEXT((INDEX('3_Balance_Sheet'!C52:N52,1,LatestAudCol)-INDEX('3_Balance_Sheet'!C52:N52,1,PriorAudCol))+(INDEX('3_Balance_Sheet'!C39:N39,1,LatestAudCol)-INDEX('3_Balance_Sheet'!C39:N39,1,PriorAudCol)),"0.00")," Cr") -> Capex: ₹0.00 Cr | LT funds raised: ₹0.00 Cr | C12: =IF((INDEX('3_Balance_Sheet'!C84:N84,1,LatestAudCol)-INDEX('3_Balance_Sheet'!C84:N84,1,PriorAudCol))<0.5,"No material capex in latest year. Funds Flow is clean — operations and WC funding aligned.",IF((INDEX('3_Balance_Sheet'!C84:N84,1,LatestAudCol)-INDEX('3_Balance_Sheet'!C84:N84,1,PriorAudCol))<=(INDEX('3_Balance_Sheet'!C52:N52,1,LatestAudCol)-INDEX('3_Balance_Sheet'!C52:N52,1,PriorAudCol))+(INDEX('3_Balance_Sheet'!C39:N39,1,LatestAudCol)-INDEX('3_Balance_Sheet'!C39:N39,1,PriorAudCol)),"Capex matched with long-term sources (TNW + TTL). End-use compliance holds — no diversion of WC.","No supportive narrative — see Against.")) -> No material capex in latest year. Funds Flow is clean — operations and WC funding aligned. | D12: =IF((INDEX('3_Balance_Sheet'!C84:N84,1,LatestAudCol)-INDEX('3_Balance_Sheet'!C84:N84,1,PriorAudCol))<0.5,"No capex concerns.",IF((INDEX('3_Balance_Sheet'!C84:N84,1,LatestAudCol)-INDEX('3_Balance_Sheet'!C84:N84,1,PriorAudCol))>(INDEX('3_Balance_Sheet'!C52:N52,1,LatestAudCol)-INDEX('3_Balance_Sheet'!C52:N52,1,PriorAudCol))+(INDEX('3_Balance_Sheet'!C39:N39,1,LatestAudCol)-INDEX('3_Balance_Sheet'!C39:N39,1,PriorAudCol)),"CRITICAL: Capex appears partly funded from working capital. Quantify diversion. End-use compliance breached.","No funds-flow concerns.")) -> No capex concerns. | E12: =IF((INDEX('3_Balance_Sheet'!C84:N84,1,LatestAudCol)-INDEX('3_Balance_Sheet'!C84:N84,1,PriorAudCol))>(INDEX('3_Balance_Sheet'!C52:N52,1,LatestAudCol)-INDEX('3_Balance_Sheet'!C52:N52,1,PriorAudCol))+(INDEX('3_Balance_Sheet'!C39:N39,1,LatestAudCol)-INDEX('3_Balance_Sheet'!C39:N39,1,PriorAudCol)),"Specific TL or promoter contribution to plug the gap. Stop-payment on WC limit until compliance restored. Half-yearly stock audit.","Standard end-use undertaking.") -> Standard end-use undertaking.
A13: Industry / Macro Context | B13: =IFERROR(CONCATENATE("Outlook: ",VLOOKUP(IndustryName,Industry_Outlook!$A:$H,2,FALSE())),"Awaiting industry selection on Setup") -> Awaiting industry selection on Setup | C13: =IFERROR(IF(OR(VLOOKUP(IndustryName,Industry_Outlook!$A:$H,2,FALSE())="Positive",VLOOKUP(IndustryName,Industry_Outlook!$A:$H,2,FALSE())="Stable to Positive"),VLOOKUP(IndustryName,Industry_Outlook!$A:$H,4,FALSE()),VLOOKUP(IndustryName,Industry_Outlook!$A:$H,3,FALSE())),"") | D13: =IFERROR(VLOOKUP(IndustryName,Industry_Outlook!$A:$H,7,FALSE()),"") | E13: =IFERROR(IF(OR(VLOOKUP(IndustryName,Industry_Outlook!$A:$H,2,FALSE())="Negative",VLOOKUP(IndustryName,Industry_Outlook!$A:$H,2,FALSE())="Cautious",LEFT(VLOOKUP(IndustryName,Industry_Outlook!$A:$H,2,FALSE()),7)="Adverse"),"Industry-specific covenants: monthly cash flow MIS; sub-limit on commodity exposure if applicable; quarterly Industry Risk Score review.","Standard industry monitoring under SBI MDS framework."),"")
A14: Pricing & Repayment Structure | B14: =CONCATENATE("Existing FB: ₹",TEXT(ExistingFB_WC+ExistingFB_TL,"0.00")," Cr | Proposed FB: ₹",TEXT(ProposedFB_WC+ProposedFB_TL,"0.00")," Cr") -> Existing FB: ₹0.00 Cr | Proposed FB: ₹0.00 Cr | C14: =IF(ProposalType="Renewal at Existing Level","Renewal at existing levels — no incremental risk taken. Borrower has serviced limits over the prior year.",IF(ProposalType="Renewal with Reduction","Renewal with reduction signals risk-aware stance. Reduced exposure better aligned with current operating size.",IF(ProposalType="Enhancement","Enhancement justified by sales/asset growth (subject to underlying drivers reviewed in Theme 1).",IF(ProposalType="Greenfield Unit","Greenfield financing — risk-priced; tied to phased disbursement against milestones.",IF(ProposalType="Fresh Sanction","Fresh sanction — borrower onboarding; rating-based pricing applies.",""))))) | D14: =IF(ProposalType="Enhancement","Quantum of enhancement must align with MPBF computation; avoid gold-plating. Validate against assessed need.",IF(ProposalType="Greenfield Unit","Project execution risk; cost overruns; commissioning delay risk; off-take dependency.",IF(ProposalType="Fresh Sanction","First-time exposure — limited track record with bank. Higher spread justifiable.","No pricing concerns."))) -> No pricing concerns. | E14: =IF(ProposalType="Greenfield Unit","Disbursement linked to milestones (civil, equipment, commissioning). Pre-COD interest in moratorium. DSRA + cash sweep post-COD. Sponsor undertaking.",IF(ProposalType="Fresh Sanction","Risk-based pricing; rating-linked spread reset annually; quarterly review for first 12 months.","Standard pricing tied to internal rating; reset at next renewal.")) -> Standard pricing tied to internal rating; reset at next renewal.
A15: Short-Term Liquidity Visibility (13-Week) | B15: =CONCATENATE("Min closing: ₹",TEXT(MIN('18_13W_Cash_Flow'!C29:O29),"0.00")," Cr | Max funding need: ₹",TEXT(MAX('18_13W_Cash_Flow'!C30:O30),"0.00")," Cr") -> Min closing: ₹0.00 Cr | Max funding need: ₹0.00 Cr | C15: =IF(MIN('18_13W_Cash_Flow'!C29:O29)>=0,"13-week rolling cash flow projection demonstrates positive liquidity throughout the horizon. Borrower can self-fund operating cycle without dependence on additional bank drawdowns.","No supportive narrative — see Against.") -> 13-week rolling cash flow projection demonstrates positive liquidity throughout the horizon. Borrower can self-fund operating cycle without dependence on additional bank drawdowns. | D15: =IF(MIN('18_13W_Cash_Flow'!C29:O29)<0,"AGAINST: Acute short-term liquidity deficit projected. Borrower relies heavily on rolling drawdowns. Existing working capital limits may be mathematically insufficient to bridge the projected cash conversion cycle. Material concern for sanction committee.","No 13-week liquidity concerns identified.") -> No 13-week liquidity concerns identified. | E15: =IF(MIN('18_13W_Cash_Flow'!C29:O29)<0,"Weekly cash flow MIS submission. DSRA equal to 4 weeks of operating outflows. Cash sweep arrangement on excess flows. Sub-limit for ad-hoc enhancements requires committee approval.","Standard monthly MSOD; quarterly cash flow review.") -> Standard monthly MSOD; quarterly cash flow review.

Sheet 14_Justification
A1: =CONCATENATE("CREDIT JUSTIFICATION | ", BorrowerName, " | ", ProposalType) -> CREDIT JUSTIFICATION | |
A2: Conversational, paste-ready justification narrative. Auto-tunes by proposal type and observed metrics.
A4: 1. Borrower & Proposal | B4: =CONCATENATE("M/s ",BorrowerName," (Customer ID: ",CustomerID,") is engaged in the ",IndustryName," segment, internally rated ",InternalRating," and externally rated ",ExternalRating,". The present proposal is for ",ProposalType,IF(ProposalType="Renewal at Existing Level"," at the existing aggregate FB sanction of ₹"&TEXT(ExistingFB_WC+ExistingFB_TL,"0.00")&" Cr.",IF(ProposalType="Renewal with Reduction"," with a reduction from ₹"&TEXT(ExistingFB_WC+ExistingFB_TL,"0.00")&" Cr to ₹"&TEXT(ProposedFB_WC+ProposedFB_TL,"0.00")&" Cr.",IF(ProposalType="Enhancement"," from ₹"&TEXT(ExistingFB_WC+ExistingFB_TL,"0.00")&" Cr to ₹"&TEXT(ProposedFB_WC+ProposedFB_TL,"0.00")&" Cr.",IF(ProposalType="Greenfield Unit"," for a greenfield unit with proposed FB exposure of ₹"&TEXT(ProposedFB_WC+ProposedFB_TL,"0.00")&" Cr.",IF(ProposalType="Fresh Sanction"," with proposed FB exposure of ₹"&TEXT(ProposedFB_WC+ProposedFB_TL,"0.00")&" Cr.","")))))) -> M/s (Customer ID: ) is engaged in the segment, internally rated and externally rated . The present proposal is for
A5: 2. Operations & Sales Trajectory | B5: =CONCATENATE("Net sales for the latest audited year stood at ₹",TEXT(INDEX('2_Operating_Statement'!C13:N13,1,LatestAudCol),"0.00")," Cr, representing a YoY ",IF(IFERROR((INDEX('2_Operating_Statement'!C13:N13,1,LatestAudCol)-INDEX('2_Operating_Statement'!C13:N13,1,PriorAudCol))/INDEX('2_Operating_Statement'!C13:N13,1,PriorAudCol),0)>=0,"growth","decline")," of ",TEXT(ABS(IFERROR((INDEX('2_Operating_Statement'!C13:N13,1,LatestAudCol)-INDEX('2_Operating_Statement'!C13:N13,1,PriorAudCol))/INDEX('2_Operating_Statement'!C13:N13,1,PriorAudCol),0)),"0.0%"),IF(IFERROR((INDEX('2_Operating_Statement'!C13:N13,1,LatestAudCol)-INDEX('2_Operating_Statement'!C13:N13,1,PriorAudCol))/INDEX('2_Operating_Statement'!C13:N13,1,PriorAudCol),0)>0.5,". This sharp jump warrants verification against GST returns, sales register, and customer concentration.",IF(IFERROR((INDEX('2_Operating_Statement'!C13:N13,1,LatestAudCol)-INDEX('2_Operating_Statement'!C13:N13,1,PriorAudCol))/INDEX('2_Operating_Statement'!C13:N13,1,PriorAudCol),0)<MinSalesGrowth,". The decline reflects challenging market conditions; sustainability of revenue base needs to be reviewed.",". Trajectory is consistent with industry benchmarks."))," Operating margin held at ",TEXT(IFERROR(INDEX('2_Operating_Statement'!C33:N33,1,LatestAudCol)/INDEX('2_Operating_Statement'!C13:N13,1,LatestAudCol),0),"0.0%")," and PAT closed at ₹",TEXT(INDEX('2_Operating_Statement'!C58:N58,1,LatestAudCol),"0.00")," Cr.") -> Net sales for the latest audited year stood at ₹0.00 Cr, representing a YoY growth of 0.0%. Trajectory is consistent with industry benchmarks. Operating margin held at 0.0% and PAT closed at ₹0.00 Cr.
A6: 3. Liquidity & Working Capital | B6: =CONCATENATE("Liquidity is ",IF(IFERROR(INDEX('3_Balance_Sheet'!C82:N82,1,LatestAudCol)/INDEX('3_Balance_Sheet'!C27:N27,1,LatestAudCol),0)>=MinCR,"adequate","stretched"),", with Current Ratio at ",TEXT(IFERROR(INDEX('3_Balance_Sheet'!C82:N82,1,LatestAudCol)/INDEX('3_Balance_Sheet'!C27:N27,1,LatestAudCol),0),"0.00")," against the policy minimum of ",TEXT(MinCR,"0.00"),". Net Working Capital stood at ₹",TEXT(INDEX('3_Balance_Sheet'!C82:N82,1,LatestAudCol)-INDEX('3_Balance_Sheet'!C27:N27,1,LatestAudCol),"0.00")," Cr",IF((INDEX('3_Balance_Sheet'!C82:N82,1,LatestAudCol)-INDEX('3_Balance_Sheet'!C27:N27,1,LatestAudCol))<=0," — negative; the borrower currently does not have a positive operating cycle margin.",""),". Operating cycle days: Inventory ",TEXT(IFERROR(INDEX('3_Balance_Sheet'!C73:N73,1,LatestAudCol)*365/INDEX('2_Operating_Statement'!C13:N13,1,LatestAudCol),0),"0")," days; Receivables ",TEXT(IFERROR((INDEX('3_Balance_Sheet'!C59:N59,1,LatestAudCol)+INDEX('3_Balance_Sheet'!C60:N60,1,LatestAudCol))*365/INDEX('2_Operating_Statement'!C10:N10,1,LatestAudCol),0),"0")," days; Payables ",TEXT(IFERROR((INDEX('3_Balance_Sheet'!C14:N14,1,LatestAudCol)+INDEX('3_Balance_Sheet'!C15:N15,1,LatestAudCol))*365/(INDEX('2_Operating_Statement'!C17:N17,1,LatestAudCol)+INDEX('2_Operating_Statement'!C20:N20,1,LatestAudCol)),0),"0")," days.") -> Liquidity is stretched, with Current Ratio at 0.00 against the policy minimum of 1.17. Net Working Capital stood at ₹0.00 Cr — negative; the borrower currently does not have a positive operating cycle margin.. Operating cycle days: Inventory 0 days; Receivables 0 days; Payables 0 days.
A7: 4. Solvency & Leverage | B7: =CONCATENATE("TNW closed at ₹",TEXT(INDEX('3_Balance_Sheet'!C52:N52,1,LatestAudCol),"0.00")," Cr",IF(INDEX('3_Balance_Sheet'!C52:N52,1,LatestAudCol)<=0," (eroded — critical concern requiring fresh equity)",""),". TOL/TNW at ",TEXT(IFERROR(INDEX('3_Balance_Sheet'!C40:N40,1,LatestAudCol)/INDEX('3_Balance_Sheet'!C52:N52,1,LatestAudCol),0),"0.00x"),IF(IFERROR(INDEX('3_Balance_Sheet'!C40:N40,1,LatestAudCol)/INDEX('3_Balance_Sheet'!C52:N52,1,LatestAudCol),0)<=MaxTOLTNW," remains within the policy ceiling of "&TEXT(MaxTOLTNW,"0.00x")&"."," exceeds the policy ceiling of "&TEXT(MaxTOLTNW,"0.00x")&"; deleveraging plan needs articulation.")," Debt/EBITDA stands at ",TEXT(IFERROR(INDEX('3_Balance_Sheet'!C39:N39,1,LatestAudCol)/(INDEX('2_Operating_Statement'!C33:N33,1,LatestAudCol)+INDEX('2_Operating_Statement'!C24:N24,1,LatestAudCol)),0),"0.00x"),IF(IFERROR(INDEX('3_Balance_Sheet'!C39:N39,1,LatestAudCol)/(INDEX('2_Operating_Statement'!C33:N33,1,LatestAudCol)+INDEX('2_Operating_Statement'!C24:N24,1,LatestAudCol)),0)<=MaxLeverage," — within tolerance."," — exceeds the "&TEXT(MaxLeverage,"0.00x")&" benchmark.")) -> TNW closed at ₹0.00 Cr (eroded — critical concern requiring fresh equity). TOL/TNW at 0.00x remains within the policy ceiling of 4.00x. Debt/EBITDA stands at 0.00x — within tolerance.
A8: 5. Coverage & Debt Service | B8: =CONCATENATE("Interest coverage stood at ",TEXT(IFERROR(INDEX('2_Operating_Statement'!C33:N33,1,LatestAudCol)/INDEX('2_Operating_Statement'!C37:N37,1,LatestAudCol),0),"0.00x"),IF(IFERROR(INDEX('2_Operating_Statement'!C33:N33,1,LatestAudCol)/INDEX('2_Operating_Statement'!C37:N37,1,LatestAudCol),0)>=MinICR," — comfortably above"," — below")," the minimum benchmark of ",TEXT(MinICR,"0.00x"),". Average Gross DSCR over the projection period works out to ",TEXT('4_DSCR'!C19,"0.00x"),IF('4_DSCR'!C19>=MinDSCR_Avg," — within the acceptable corridor of "&TEXT(MinDSCR_Avg,"0.00x")&"."," — short of the "&TEXT(MinDSCR_Avg,"0.00x")&" benchmark; structuring/sponsor support to be discussed.")) -> Interest coverage stood at 0.00x — below the minimum benchmark of 1.50x. Average Gross DSCR over the projection period works out to 0.00x — short of the 1.50x benchmark; structuring/sponsor support to be discussed.
A9: 6. Industry & Macro Context | B9: =IFERROR(CONCATENATE("The ",IndustryName," sector outlook is ",VLOOKUP(IndustryName,Industry_Outlook!$A:$H,2,FALSE()),". ",VLOOKUP(IndustryName,Industry_Outlook!$A:$H,4,FALSE())," Key drivers: ",VLOOKUP(IndustryName,Industry_Outlook!$A:$H,6,FALSE())," Key risks to monitor: ",VLOOKUP(IndustryName,Industry_Outlook!$A:$H,7,FALSE())),"[Awaiting industry selection on the Setup sheet — once selected, this paragraph auto-populates with the latest sector outlook, drivers, and risks from the Industry Outlook database.]") -> [Awaiting industry selection on the Setup sheet — once selected, this paragraph auto-populates with the latest sector outlook, drivers, and risks from the Industry Outlook database.]
A10: 7. Red Flag Synthesis | B10: =CONCATENATE("Of the 30 automated red-flag tests run on the financials, ",COUNTIF('12_Red_Flags'!F6:F100,"⚠*")," flagged for attention while ",COUNTIF('12_Red_Flags'!F6:F100,"✓*")," passed. ",IF(COUNTIF('12_Red_Flags'!F6:F100,"⚠*")=0,"No material red flags emerged; the credit profile is clean.",IF(COUNTIF('12_Red_Flags'!F6:F100,"⚠*")<=3,"Concerns are minor and adequately addressed by standard covenants.",IF(COUNTIF('12_Red_Flags'!F6:F100,"⚠*")<=7,"Multiple concerns require structured covenants and tighter monitoring (refer Sheet 13 for theme-wise mitigants).","Material credit concerns surfaced — proposal merits reconsideration or significant restructuring before sanction.")))) -> Of the 30 automated red-flag tests run on the financials, 7 flagged for attention while 25 passed. Multiple concerns require structured covenants and tighter monitoring (refer Sheet 13 for theme-wise mitigants).
A11: 8. Recommendation | B11: =CONCATENATE("Based on the above analysis, the proposal for ",ProposalType,IF(COUNTIF('12_Red_Flags'!F6:F100,"⚠*")<=3," is recommended for sanction subject to standard covenants and ",IF(COUNTIF('12_Red_Flags'!F6:F100,"⚠*")<=7," may be considered for sanction with strengthened covenants and "," requires senior committee deliberation in light of the multiple flagged areas; before progressing the bank should secure ")),IF(ProposalType="Greenfield Unit","milestone-based disbursement linked to project completion, DSRA equivalent to 1 quarter of debt service, and sponsor undertaking for cost overruns.",IF(ProposalType="Enhancement","verification of incremental WC need against MPBF, end-use undertaking, and quarterly sales-vs-projection review.",IF(ProposalType="Renewal with Reduction","standard quarterly stock & book-debt statement and half-yearly compliance certificate.","the standard covenants set out in the bank's policy framework, with quarterly review during the currency of the limits.")))) -> Based on the above analysis, the proposal for may be considered for sanction with strengthened covenants and the standard covenants set out in the bank's policy framework, with quarterly review during the currency of the limits.
A12: 9. Sign-off | B12: =CONCATENATE("Prepared by: _____________________ | Date: ",TEXT(TODAY(),"DD-MMM-YYYY")," | Reviewed by: _____________________ | Approved by: _____________________") -> Prepared by: _____________________ | Date: 08-May-2026 | Reviewed by: _____________________ | Approved by: _____________________

Sheet Industry_Outlook
A1: Industry | B1: Outlook | C1: Prior_Performance | D1: Forecast_FY26 | E1: Forecast_FY27 | F1: Key_Drivers | G1: Key_Risks | H1: Source
A2: AIRPORT | B2: Positive | C2: FY25: Strong passenger traffic growth ~12-14%; airport modernisation cycle in execution. | D2: FY26 traffic muted (0-3% domestic) due to airspace closures from W. Asia conflict; concession revenues stable on passenger spend. | E2: FY27 recovery expected with traffic at 6-8% domestic, capex cycle continuing. | F2: Govt UDAN scheme (40M passengers target); new greenfield airports under PPP; non-aero revenue from F&B/retail. | G2: Sensitivity to airline financial health; jet-fuel pass-through; FX on USD-denominated debt; regulatory tariff resets. | H2: ICRA Mar 2026 + IBEF Aviation 2026
A3: ALUMINIUM | B3: Stable | C3: FY25: Healthy demand from packaging, EVs, infra; LME prices firm; capacity utilisation >90%. | D3: FY26 demand growth 6-8% with downstream pull from auto, construction; margins under pressure from rising power costs. | E3: FY27 demand 7-9% with EV battery casing and infrastructure projects; integrated players advantaged. | F3: Domestic EV/battery push; PLI for value-added aluminium; Sec 232 US tariff exemptions support exports. | G3: Coal/power cost spikes; LME volatility; Chinese supply pressure; bauxite/alumina input availability. | H3: CRISIL Ratings Round-up Sep 2025 + ICRA
